Workbook

Sheet Read Me
A1: Accelerator Test Metrics Workbook | B1: Reusable test definition, execution, quality, efficiency, context, and defect tracking template.
A2: Recommended workflow | B2: Define reusable scenarios in Test Cases, record every execution in Test Runs, then attach quality, token, context, and defect records using Run ID.
A3: Objective vs subjective data | B3: Keep measured values such as tokens, duration, test counts, and pass/fail separate from reviewer scores.
A4: Scoring scale | B4: Quality scores use 1–10: 1–3 poor, 4–5 weak, 6–7 acceptable, 8–9 strong, 10 exceptional.
A5: Evidence | B5: Use repository-relative paths, report locations, screenshots, logs, manifests, or review links. Do not place secrets or customer data in this workbook.
A6: Result meanings | B6: Pass = all required outcomes; Partial = useful result with material gaps; Fail = required outcome absent or incorrect; Blocked = execution could not proceed.
A7: Governed testing | B7: For governed Project Brain operations, record stable task IDs and verify revision, owner, handoff, manifest, privacy, and promotion behavior.
A8: Dashboard | B8: Summary formulas update as rows are added. Open the workbook in Excel or another formula-capable spreadsheet application.

Sheet Dashboard
A1: Accelerator Test Dashboard
A2: Formulas update from the workbook data sheets.
A3: Core Metric | B3: Value | D3: Framework | E3: Runs | F3: Pass Rate
A4: Total Runs | B4: =ROWS(tblTestRuns[Run ID]) | D4: Laravel | E4: =COUNTIF('Test Runs'!G:G,D4) | F4: =IF(E4=0,0,COUNTIFS('Test Runs'!G:G,D4,'Test Runs'!O:O,"Pass")/E4)
A5: Passed | B5: =COUNTIF(tblTestRuns[Result],"Pass") | D5: Symfony | E5: =COUNTIF('Test Runs'!G:G,D5) | F5: =IF(E5=0,0,COUNTIFS('Test Runs'!G:G,D5,'Test Runs'!O:O,"Pass")/E5)
A6: Partially Passed | B6: =COUNTIF(tblTestRuns[Result],"Partial") | D6: PHP Core | E6: =COUNTIF('Test Runs'!G:G,D6) | F6: =IF(E6=0,0,COUNTIFS('Test Runs'!G:G,D6,'Test Runs'!O:O,"Pass")/E6)
A7: Failed | B7: =COUNTIF(tblTestRuns[Result],"Fail") | D7: Infrastructure-Creator | E7: =COUNTIF('Test Runs'!G:G,D7) | F7: =IF(E7=0,0,COUNTIFS('Test Runs'!G:G,D7,'Test Runs'!O:O,"Pass")/E7)
A8: Blocked | B8: =COUNTIF(tblTestRuns[Result],"Blocked") | D8: Cross-stack | E8: =COUNTIF('Test Runs'!G:G,D8) | F8: =IF(E8=0,0,COUNTIFS('Test Runs'!G:G,D8,'Test Runs'!O:O,"Pass")/E8)
A9: Pass Rate | B9: =IF(B4=0,0,B5/B4)
A10: First-Attempt Pass Rate | B10: =IFERROR(COUNTIF(tblEfficiencyTokens[Successful First Attempt],"Yes")/ROWS(tblEfficiencyTokens[Run ID]),0)
A11: Average Overall Quality | B11: =IFERROR(AVERAGEIF(tblQualityMetrics[Run ID],"RUN-???",tblQualityMetrics[Overall Score]),0) | D11: AI Tool | E11: Runs | F11: Pass Rate
A12: Average Duration (seconds) | B12: =IFERROR(AVERAGEIF(tblEfficiencyTokens[Run ID],"RUN-???",tblEfficiencyTokens[Total Duration (seconds)]),0) | D12: Claude Code | E12: =COUNTIF('Test Runs'!I:I,D12) | F12: =IF(E12=0,0,COUNTIFS('Test Runs'!I:I,D12,'Test Runs'!O:O,"Pass")/E12)
A13: Average Tokens per Run | B13: =IF(COUNT(tblEfficiencyTokens[Total Tokens])=0,"N/A",AVERAGE(tblEfficiencyTokens[Total Tokens])) | D13: Cursor | E13: =COUNTIF('Test Runs'!I:I,D13) | F13: =IF(E13=0,0,COUNTIFS('Test Runs'!I:I,D13,'Test Runs'!O:O,"Pass")/E13)
A14: Average Cost per Run | B14: =IF(COUNT(tblEfficiencyTokens[Estimated Cost])=0,"N/A",AVERAGE(tblEfficiencyTokens[Estimated Cost])) | D14: Codex | E14: =COUNTIF('Test Runs'!I:I,D14) | F14: =IF(E14=0,0,COUNTIFS('Test Runs'!I:I,D14,'Test Runs'!O:O,"Pass")/E14)
A15: Average Human Interventions | B15: =IFERROR(AVERAGE(tblTestRuns[Human Intervention Count]),0) | D15: Cross-tool | E15: =COUNTIF('Test Runs'!I:I,D15) | F15: =IF(E15=0,0,COUNTIFS('Test Runs'!I:I,D15,'Test Runs'!O:O,"Pass")/E15)
A16: Safety Violations | B16: =SUM(tblTestRuns[Safety Violation Count])
A17: Context Retrieval Success Rate | B17: =IFERROR(COUNTIF(tblContextBrain[Retrieval Successful],"Yes")/(COUNTIF(tblContextBrain[Retrieval Successful],"Yes")+COUNTIF(tblContextBrain[Retrieval Successful],"No")),0)
A18: Open Critical Defects | B18: =COUNTIFS(tblDefects[Severity],"Critical",tblDefects[Status],"<>Closed",tblDefects[Status],"<>Rejected")

Sheet Test Cases
A1: Test Case ID | B1: Test Name | C1: Test Category | D1: Framework | E1: AI Tool | F1: Workflow / Skill | G1: Agent / Command | H1: Priority | I1: Preconditions | J1: Input Prompt | K1: Expected Behaviour | L1: Expected Files Changed | M1: Expected Verification | N1: Security / Safety Expectations | O1: Execution Type | P1: Test Owner | Q1: Requirement / Source | R1: Notes
A2: TC-001 | B2: Claude Code activation banner - Laravel edition (VERSION, loop-counter reset, validation cache) | C2: Installation and activation | D2: Laravel | E2: Claude Code | F2: n/a — hook layer (SessionStart local-context) | G2: .claude/hooks/local-context.sh | H2: Critical | I2: Laravel/ edition opened as the workspace root (or installed into a consuming project per docs/ADOPTION.md). .claude/settings.json present and wires SessionStart -> .claude/hooks/local-context.sh (timeout 10). Hook scripts executable. git repository initialized, python3 available. Laravel/VERSION contains 1.4.3. To test the loop-counter reset, pre-seed a counter file: REPO_KEY=$(git rev-parse --show-toplevel | tr -d '\n' | cksum | cut -d' ' -f1); mkdir -p /tmp/claude-loop-detection-$REPO_KEY && touch /tmp/claude-loop-detection-$REPO_KEY/seed | J2: Start a new Claude Code session in the Laravel edition root (run `claude`). For the deterministic path, execute the hook directly from the edition root: bash .claude/hooks/local-context.sh | K2: 1) The SessionStart hook prints the 'Project Context' banner. 2) Line 'Accelerator version: 1.4.3' is read from the edition VERSION file. 3) Git line 'Branch: <branch> (N uncommitted changes)' appears. 4) Because the accelerator folder itself has no artisan file, the banner prints the NOTE 'No artisan file found. This is the Laravel accelerator folder; for framework-agnostic native PHP, use the sibling PHP Core/ folder.' (in a real Laravel project with artisan + composer.lock it prints 'Laravel: laravel/framework <version> (composer.lock)'). 5) Session-scoped loop counters are wiped: all files under /tmp/claude-loop-detection-$REPO_KEY are deleted. 6) Context governance line prints metadata only: 'Context governance: mode=governed, index=healthy/current, active-bindings=N, brain-validation=valid.' 7) Memory bank summary line ends with 'Read memory-bank/README.md and INDEX.md before relevant durable-memory work.' 8) Brain/memory validation results are cached under ${TMPDIR:-/tmp}/ai-accelerator-session-cache-$EDITION_KEY keyed by git HEAD + working-tree fingerprint; a second run on an unchanged checkout serves the cached 'brain-validation' and 'memory-summary' values instead of re-running the validation walks. 9) In the interactive client, typing '/' shows installed commands including /verify, /memory, and /project-brain (per docs/TOOL-INTEGRATIONS.md 'Claude Code Activation'). 10) Hook exits 0 in all cases (informational only). | L2: None inside the repository. Temp state only: /tmp/claude-loop-detection-<key>/ emptied; ${TMPDIR:-/tmp}/ai-accelerator-session-cache-<key>/brain-validation-<cachekey> and memory-summary-<cachekey> created. | M2: cd Laravel && bash .claude/hooks/local-context.sh | head -3 -> lines 'Project Context', '===============', 'Accelerator version: 1.4.3'. bash .claude/hooks/local-context.sh | grep -F "Accelerator version: $(tr -d '[:space:]' < VERSION)" -> match. find /tmp/claude-loop-detection-$REPO_KEY -type f | wc -l -> 0 after the run (the pre-seeded file is gone). ls ${TMPDIR:-/tmp}/ai-accelerator-session-cache-*/brain-validation-* -> at least one cache file exists. Run the hook twice and confirm the second run is noticeably faster and still prints 'brain-validation=valid'. echo $? after the hook -> 0. | N2: The banner must never print, index, or inject Memory Bank / Project Brain record contents (metadata only). No files inside the repository working tree are created or modified. No network access. The hook must never exit non-zero (a banner failure must not break session start). The loop-counter wipe must only touch /tmp/claude-loop-detection-<this repo's key>, not other repositories' counters. | O2: Hybrid | P2: QA | Q2: Laravel/.claude/hooks/local-context.sh (also Laravel/.claude/settings.json 'SessionStart' block; docs/TOOL-INTEGRATIONS.md 'Claude Code Activation') | R2: Content-only edits to untracked files are not part of the cache fingerprint, so one stale cached summary is possible by design; `context.py validate` stays authoritative. The interactive '/' command check requires a real Claude Code client, hence Hybrid.
A3: TC-002 | B3: Claude Code activation banner - Symfony edition (bin/console detection) | C3: Installation and activation | D3: Symfony | E3: Claude Code | F3: n/a — hook layer (SessionStart local-context) | G3: .claude/hooks/local-context.sh | H3: High | I3: Symfony/ edition opened as workspace root. Symfony/.claude/settings.json wires SessionStart -> .claude/hooks/local-context.sh. Symfony/VERSION contains 1.3.1. git and python3 available. Two sub-scenarios: (a) accelerator folder alone (no bin/console); (b) installed into a real Symfony project where bin/console exists. | J3: Start a new Claude Code session in the Symfony edition root, or run directly: bash .claude/hooks/local-context.sh | K3: 1) 'Project Context' banner prints with 'Accelerator version: 1.3.1' taken from Symfony/VERSION. 2) Scenario (b): with bin/console present the banner prints 'Framework: Symfony detected. Use Symfony Controller -> Service -> Repository conventions.' 3) Scenario (a): without bin/console it prints the NOTE that Symfony bin/console was not detected and the Symfony rules should only be applied after confirming this is a Symfony project. 4) Loop counters for this repo key under /tmp/claude-loop-detection-<key> are deleted at session start. 5) 'Context governance: mode=..., index=..., active-bindings=..., brain-validation=...' and the Memory Bank summary print metadata only; results are cached in ${TMPDIR:-/tmp}/ai-accelerator-session-cache-<key> keyed by git state. 6) Exit code 0. | L3: None in the repository; only /tmp cache and loop-counter state as in the Laravel case. | M3: cd Symfony && bash .claude/hooks/local-context.sh | grep -F 'Accelerator version: 1.3.1' -> match. In a checkout with bin/console: bash .claude/hooks/local-context.sh | grep -F 'Framework: Symfony detected' -> match. Without bin/console: output contains 'Symfony bin/console was not detected'. echo $? -> 0. Cache check: second consecutive run prints the same 'brain-validation=' value without re-running validate (observe via elapsed time or by temporarily setting PS4/xtrace). | N3: No record contents printed. No writes inside the repository. Always exit 0. The Symfony convention hint must not be printed when bin/console is absent (prevents wrong-stack advice after a mis-installation). | O3: Hybrid | P3: QA | Q3: Symfony/.claude/hooks/local-context.sh (SessionStart wiring in Symfony/.claude/settings.json) | R3: The version/reset/cache mechanics are shared core mirrored across editions; only the framework-detection section differs. Cross-edition consistency of the Python core is covered by the parity test case.
A4: TC-003 | B4: Claude Code activation banner - PHP Core edition (native-PHP folder, path with space) | C4: Installation and activation | D4: PHP Core | E4: Claude Code | F4: n/a — hook layer (SessionStart local-context) | G4: .claude/hooks/local-context.sh | H4: High | I4: 'PHP Core'/ edition opened as workspace root (directory name contains a space — every shell command must quote it). 'PHP Core/VERSION' contains 1.2.1. 'PHP Core/.claude/settings.json' wires SessionStart -> .claude/hooks/local-context.sh. git and python3 available. | J4: Start a new Claude Code session in the 'PHP Core' edition root, or run: cd "PHP Core" && bash .claude/hooks/local-context.sh | K4: 1) 'Project Context' banner prints 'Accelerator version: 1.2.1' from 'PHP Core/VERSION'. 2) The hook scans a native PHP working directory: composer/lock managers, PHP runtime version, 'Entry point: public/index.php (front controller)' when present. 3) Framework guard: if a framework package (e.g. cakephp/cakephp or yiisoft/yii2) is detected in composer.json, the banner prints the NOTE '<Framework> detected. This is the native-PHP base folder (PHP Core/).' steering the user to the correct edition. 4) Loop counters for the repo key are reset and validation results cached, identically to the other editions. 5) Exit code 0. 6) The hook works correctly despite the space in the edition path (all internal paths derived from BASH_SOURCE are quoted). | L4: None in the repository; /tmp session cache and loop-counter reset only. | M4: cd "PHP Core" && bash .claude/hooks/local-context.sh | grep -F 'Accelerator version: 1.2.1' -> match. bash .claude/hooks/local-context.sh | head -1 -> 'Project Context'. echo $? -> 0. Negative check for path handling: the command must not emit 'No such file or directory' errors caused by the unquoted space. | N4: No record contents printed; no repository writes; always exit 0. The banner must not claim a framework-specific workflow for a native-PHP project. | O4: Hybrid | P4: QA | Q4: PHP Core/.claude/hooks/local-context.sh (docs/ADOPTION.md section 1 for edition selection) | R4: The space in 'PHP Core' is a standing trap for test scripts; docs/ADOPTION.md explicitly reminds to preserve quotes around such paths.
A5: TC-004 | B5: Cursor activation: rules + hooks.json + missing read hook compensated by working-memory.mdc | C5: Installation and activation | D5: Laravel | E5: Cursor | F5: n/a — hook layer (Cursor hooks + alwaysApply rule) | G5: .cursor/hooks.json (sessionStart/beforeShellExecution/afterFileEdit/stop) + .cursor/hooks/working-memory-write.sh | H5: Critical | I5: Laravel/ edition opened in Cursor as project root. .cursor/rules/ contains accelerator-workflow.mdc, php-standards.mdc, safety-and-verification.mdc. .cursor/hooks.json (schema version: 1) and .cursor/hooks/*.sh present and executable. Cursor's optional Claude-file loading is DISABLED in Rules & Memories settings (double-loading prevention). python3 available; git branch checked out (the branch name becomes the default task id). | J5: Open the project in Cursor, start a new agent session, send any prompt, and let the turn finish. Deterministic simulation of the stop hook from the edition root: CONTEXT_TASK_ID=qa-cursor-activation bash .cursor/hooks/working-memory-write.sh | K5: 1) hooks.json registers exactly: sessionStart -> .cursor/hooks/local-context.sh (timeout 15), beforeShellExecution -> bash-validator.sh (5), afterFileEdit -> file-naming-validator.sh (5) and loop-detection.sh (5), stop -> working-memory-write.sh (15). 2) Exactly ONE session-context report appears at session start (a duplicate report means Claude-file loading is also active — a configuration defect). 3) working-memory-read.sh is deliberately ABSENT from .cursor/hooks/: Cursor's nearest event beforeSubmitPrompt cannot add context to a prompt, so the read half is compensated by a rule file. 4) After the stop hook runs, .cursor/rules/working-memory.mdc exists with frontmatter 'description: Working memory - Task Capsule as of end of previous turn' and 'alwaysApply: true', followed by '# Working Memory (auto-rendered)' and the fenced Task Capsule; Cursor attaches it to every prompt of the next turn (one turn stale by design). 5) The Cursor copy of local-context.sh also re-renders the rule at session start so a new session or branch switch never serves the previous session's capsule. 6) The rendered file is ignored local state (Laravel/.gitignore line '.cursor/rules/working-memory.mdc'). 7) Cursor loop detection tracks per-file edits under /tmp/cursor-loop-detection-<repo key> (warn at 7, block at 10). | L5: .cursor/rules/working-memory.mdc created/refreshed (git-ignored, never committed). memory-bank/local/ runtime state (git-ignored). No tracked file modified. | M5: test ! -f .cursor/hooks/working-memory-read.sh && echo absent-by-design -> 'absent-by-design'. python3 -m json.tool .cursor/hooks.json > /dev/null && echo valid -> 'valid'. grep -c '"command"' .cursor/hooks.json -> 5. After CONTEXT_TASK_ID=qa-cursor-activation bash .cursor/hooks/working-memory-write.sh: test -f .cursor/rules/working-memory.mdc; head -4 .cursor/rules/working-memory.mdc | grep -F 'alwaysApply: true' -> match; grep -F 'as of end of previous turn' .cursor/rules/working-memory.mdc -> match. git check-ignore .cursor/rules/working-memory.mdc -> path printed (ignored). git status --short -> no tracked changes. | N5: The stop hook must always exit 0 (a failed checkpoint never surfaces as a turn error). Only Git porcelain metadata reaches the buffer — never working-tree file contents; sensitive-looking paths are excluded. The rule file is replaced atomically and only when a fresh render succeeds (no truncated/empty rule left behind). working-memory.mdc must never be committed. Hooks must not fire twice (double-loading). | O5: Hybrid | P5: QA | Q5: Laravel/.cursor/hooks/README.md ('How the Task Capsule reaches Cursor') and docs/TOOL-INTEGRATIONS.md 'Cursor Activation and Double-Loading Prevention' | R5: This divergence from the canonical .claude/hooks scripts is a declared MIRROR_RULES transformation (the _WM_DELIVERY_* constants in memory-bank/scripts/context_retrieval.py) verified by scripts/build_mirrors.py --check — it must NOT be reported as drift. Cursor timeouts are in seconds, same as Claude Code.
A6: TC-005 | B6: Codex activation: project trust, config.toml features.hooks, hook self-filter early-exit | C6: Installation and activation | D6: Laravel | E6: Codex | F6: n/a — hook layer (.codex hooks + .agents/skills discovery) | G6: .codex/config.toml + .codex/hooks.json + .codex/hooks/bash-validator.sh | H6: High | I6: Laravel/ edition opened with the Codex CLI or IDE extension (v0.117+, the skill-based model). Project NOT yet trusted at test start. .codex/config.toml, .codex/hooks.json, executable .codex/hooks/*.sh, and canon skills in .agents/skills/<name>/SKILL.md present. Root AGENTS.md present. | J6: Run `codex` in the repository root and accept the project trust prompt (or use /trust). Then type '/' to open the skills menu, or ask: "use the verify skill". Hook-level simulation from the edition root: printf '{"tool_name":"Read","file_path":"x.md"}' | bash .codex/hooks/bash-validator.sh ; printf '{"command":"git push --force origin main"}' | bash .codex/hooks/bash-validator.sh | K6: 1) Before trust is granted, project-scoped .codex/config.toml and hooks do NOT load. 2) After trust: config.toml is loaded and contains '[features]' / 'hooks = true', enabling the lifecycle hooks in .codex/hooks.json. 3) hooks.json wires (same event schema as Claude Code): SessionStart -> local-context.sh; UserPromptSubmit -> working-memory-read.sh with additionalContextLimit 4000; Stop -> working-memory-write.sh; PreToolUse -> bash-validator.sh AND file-naming-validator.sh; PostToolUse -> loop-detection.sh. 4) No matcher is set on any group — each script self-filters with an early exit: bash-validator.sh exits 0 immediately unless the stdin payload carries an unescaped '"command"'/'"cmd"' JSON key; file-naming-validator.sh and loop-detection.sh exit unless tool_name is a file-editing tool. 5) A payload with a destructive command is blocked: 'git push --force origin main' -> stderr 'BLOCKED: Destructive command detected: matches pattern ...' and exit 2. 6) Skills are discovered from .agents/skills (not .codex/): the skills menu lists verify, memory, project-brain, coder, etc. 7) There is deliberately NO .codex/commands and NO .codex/agents (Codex removed custom prompts/slash commands; skills are the superset replacement). 8) The metadata-only SessionStart banner prints without indexing/injecting records. | L6: None. All hook activity is stdin/stdout/exit-code based; loop tracking under /tmp/codex-loop-detection-<repo key>. | M6: grep -A1 '\[features\]' .codex/hooks/../config.toml -> 'hooks = true' (i.e. grep -A1 '\[features\]' .codex/config.toml). python3 -m json.tool .codex/hooks.json > /dev/null -> exit 0. grep -F 'additionalContextLimit' .codex/hooks.json -> '"additionalContextLimit": 4000'. printf '{"tool_name":"Read","file_path":"x.md"}' | bash .codex/hooks/bash-validator.sh; echo $? -> 0 (early-exit, no extractor forked). printf '{"command":"git push --force origin main"}' | bash .codex/hooks/bash-validator.sh; echo $? -> 2 with 'BLOCKED: Destructive command detected' on stderr. test ! -d .codex/commands && test ! -d .codex/agents -> both absent. ls .agents/skills | grep -x verify -> present. | N6: Hooks must fail OPEN (exit 0) when an expected payload key is absent — a Codex schema mismatch degrades to no-op, never breaks the turn (but QA must then re-test each safety hook after a Codex upgrade, per docs/TOOL-INTEGRATIONS.md). No MCP server may be enabled: the commented example in config.toml must remain commented. Untrusted projects must not execute project-scoped hooks. The session hook never indexes, retrieves, or injects records. | O6: Hybrid | P6: QA | Q6: Laravel/.codex/README.md and Laravel/.codex/hooks/README.md (also docs/TOOL-INTEGRATIONS.md 'Codex Trust, Configuration, and Hooks') | R6: The early-exit self-filter matters for cost: without a tool matcher the PreToolUse hooks run on EVERY tool call, and the cheap case-statement filter avoids forking jq/php/python3 for payloads that cannot carry a shell command. Trust-prompt behavior requires a real Codex client, hence Hybrid.
A7: TC-006 | B7: Post-install shared context activation: validate, index, FTS5 prerequisite | C7: Installation and activation | D7: Cross-stack | E7: Cross-tool | F7: n/a — context engine CLI (validate.py / context.py index) | G7: python3 memory-bank/scripts/validate.py; python3 project-brain/scripts/validate.py --root .; python3 memory-bank/scripts/context.py index | H7: Critical | I7: An edition (Laravel, Symfony, or PHP Core) freshly installed into a target project per docs/ADOPTION.md sections 3-7 (backup taken, collisions resolved, tool scope chosen). Target's ignore rules contain memory-bank/local/ BEFORE indexing. Python 3.9+ with the sqlite3 stdlib module built with FTS5. Clean git state recorded via git status --short. | J7: From the target project root run, in order: python3 -c "import sqlite3; db=sqlite3.connect(':memory:'); db.execute('CREATE VIRTUAL TABLE fts_check USING fts5(content)'); print('SQLite FTS5 available')" ; python3 memory-bank/scripts/validate.py ; python3 project-brain/scripts/validate.py --root . ; python3 memory-bank/scripts/context.py index ; git status --short | K7: 1) The FTS5 probe prints 'SQLite FTS5 available' (if not, context.py index later reports 'SQLite FTS5 support is required' — that is the definitive functional check). 2) memory-bank validation passes on the shipped seed content. 3) Project Brain validation passes (python3 memory-bank/scripts/context.py validate prints 'Project Brain validation passed.' as the equivalent CLI path). 4) context.py index builds the disposable local index; memory-bank/local/context.db exists afterwards but remains git-ignored. 5) project-brain/config/runtime.json declares the selected framework, governed mode, sqlite-fts5, and '"canonical_edition": ".agents"'. 6) git status --short shows only intended accelerator additions from the install manifest — indexing itself must add zero tracked changes. 7) Tool activation (previous cases) and context activation are separate concerns and both must pass. | L7: memory-bank/local/context.db created (ignored, never committed). No tracked files modified by the activation commands. | M7: python3 memory-bank/scripts/validate.py -> exit 0. python3 project-brain/scripts/validate.py --root . -> exit 0. python3 memory-bank/scripts/context.py index -> exit 0, no 'SQLite FTS5 support is required' error. test -f memory-bank/local/context.db && git check-ignore memory-bank/local/context.db -> path printed. grep -F '"canonical_edition": ".agents"' project-brain/config/runtime.json -> match. python3 memory-bank/scripts/context.py status --json -> JSON with mode/working/documents/database fields; documents > 0. git status --short -> unchanged versus the pre-activation snapshot. | N7: Activation must not silently install PHPUnit/Pest, formatters, static analyzers, framework CLIs, or npm packages (missing optional tooling is reported as unavailable, never auto-installed). No destructive overwrite of pre-existing memory-bank/ chunks or project-brain/ records. context.db must never be committed. If FTS5 is missing, the failure must be reported honestly, not worked around by claiming success. | O7: Automated | P7: QA | Q7: docs/ADOPTION.md sections 2, 7, 8 and docs/TOOL-INTEGRATIONS.md 'Shared Context Activation' | R7: Governed mode is the default; --mode lightweight is an explicit machine-local fallback (docs/CONTEXT-MODES.md). For 'PHP Core' remember to quote the path.
A8: TC-007 | B8: infra-generate full mode passes validate_generated.py including context.py smoke | C8: Installation and activation | D8: Infrastructure-Creator | E8: Claude Code | F8: infra-generate | G8: /infra-generate (spawns infra-generate-agent) | H8: Critical | I8: Case 1 completed: tasks/TASK-1/infra-scan-project-profile.md exists and was reviewed; selected editions = [claude]. The target /tmp/fixtures/fake-php-app has NO AGENTS.md and no .claude/.cursor/.codex/.agents folders (collision guard should pass without prompting). | J8: /infra-generate /tmp/fixtures/fake-php-app | K8: 1) Locates the TASK-1 profile and re-validates cited evidence against current target files. 2) Reads editions [claude] from profile section 1. 3) Collision guard finds nothing pre-existing and proceeds. 4) Fans out the four independent forges (policy-forge, skill-forge, hook-forge, memory-seed), then agent-forge and command-forge wrap the produced skills, then skill-flow-composer builds the target's own SKILL FLOW.md. 5) Prepends the version stamp as the FIRST line of the generated AGENTS.md: '<!-- Generated by Infrastructure-Creator v1.4.0 | TASK-1 | <ISO date> -->' with the version taken from the VERSION file. 6) Writes .infra-manifest.json (mode full) at the target root via the exact recipe in the SKILL. 7) Runs bootstrap-verifier LAST; a failed verification means generation is not done. 8) Writes tasks/TASK-1/infra-generate-report.md. | L8: Target: AGENTS.md, .claude/skills/ (incl. memory-bank, project-brain, checkpoint, memory), .claude/agents/, .claude/commands/, .claude/hooks/ (6 scripts), .claude/settings.json, memory-bank/ (README.md, INDEX.md, .memory-counter, templates/chunk.md, scripts/context.py, scripts/brain_runtime.py, scripts/context_retrieval.py, scripts/validate.py, chunks/MEM-0001-*.md, local/.gitkeep), project-brain/ skeleton, .infra-manifest.json. Generator: tasks/TASK-1/infra-generate-report.md, tasks/TASK-1/bootstrap-verifier-report.md. | M8: python3 Infrastructure-Creator/.agents/skills/bootstrap-verifier/scripts/validate_generated.py --target /tmp/fixtures/fake-php-app --editions claude; echo $? -> 0; cd /tmp/fixtures/fake-php-app && python3 memory-bank/scripts/context.py status && python3 memory-bank/scripts/context.py validate -> both exit 0; head -1 /tmp/fixtures/fake-php-app/AGENTS.md | grep "Generated by Infrastructure-Creator v1.4.0" -> match; test ! -d /tmp/fixtures/fake-php-app/.cursor && test ! -d /tmp/fixtures/fake-php-app/.codex && test ! -d /tmp/fixtures/fake-php-app/.agents -> all true; ls /tmp/fixtures/fake-php-app/.claude/skills | grep -cE "^(memory-bank|project-brain|checkpoint|memory)$" -> 4. | N8: Only the selected claude edition is written - no unselected edition root may exist. No content invented beyond what the profile supports. No success reported while bootstrap-verifier has unresolved failures. Target .env never read. No template placeholders ({skill-name}, TODO, YYYY-MM-DD, TASK-{N}, {{TARGET_FRAMEWORK}}) remain in generated files. | O8: Hybrid | P8: QA | Q8: Infrastructure-Creator/.agents/skills/infra-generate/SKILL.md | R8: validate_generated.py also proves the dead-hook wiring check: every .sh token referenced in .claude/settings.json must resolve to an existing executable script - an interpreter-prefixed 'bash .claude/hooks/x.sh' cannot hide a dead hook.
A9: TC-008 | B9: infra-generate merge mode never touches or claims pre-existing team files | C9: Installation and activation | D9: Infrastructure-Creator | E9: Claude Code | F9: infra-generate | G9: /infra-generate (collision guard -> merge) | H9: Critical | I9: A profile for the target exists (as in Case 1). The target already contains a team-authored AGENTS.md and a custom hook .claude/hooks/deploy-check.sh. Record baselines before the run: sha256sum /tmp/fixtures/fake-php-app/AGENTS.md /tmp/fixtures/fake-php-app/.claude/hooks/deploy-check.sh > /tmp/pre-merge.sha256. | J9: /infra-generate /tmp/fixtures/fake-php-app (when the collision guard asks 'overwrite, merge, or abort', answer: merge) | K9: 1) Collision guard detects the existing AGENTS.md/.claude and STOPS to ask overwrite/merge/abort - it never proceeds on assumption. 2) On 'merge', it snapshots the pre-existing surface BEFORE any forge writes into tasks/TASK-{N}/preexisting-files.txt (one target-relative path per line, covering AGENTS.md plus the manifest include roots .claude/.cursor/.agents/.codex/memory-bank/project-brain). 3) Forges add only what is missing; pre-existing files are never modified. 4) The manifest is written with "mode": "merge" and its files map lists ONLY files this run created - never AGENTS.md or deploy-check.sh. 5) The pre-existing AGENTS.md stays unstamped and untracked; bootstrap-verifier skips the stamp check for it and does not enforce full coverage for mode merge. | L9: Target: newly added generated files only (missing skills/agents/commands/hooks/memory-bank/project-brain), .infra-manifest.json with mode merge. Generator: tasks/TASK-{N}/preexisting-files.txt, tasks/TASK-{N}/infra-generate-report.md. Pre-existing AGENTS.md and .claude/hooks/deploy-check.sh byte-identical. | M9: sha256sum -c /tmp/pre-merge.sha256 -> OK for both files; python3 -c "import json;m=json.load(open('/tmp/fixtures/fake-php-app/.infra-manifest.json'));print(m['mode']);print('AGENTS.md' in m['files']);print('.claude/hooks/deploy-check.sh' in m['files'])" -> merge / False / False; grep -c "AGENTS.md" Infrastructure-Creator/tasks/TASK-*/preexisting-files.txt -> >=1; python3 Infrastructure-Creator/.agents/skills/bootstrap-verifier/scripts/validate_generated.py --target /tmp/fixtures/fake-php-app --editions claude; echo $? -> 0. | N9: Not a single pre-existing team file is modified or claimed in the manifest - a claimed file would later be silently overwritten by infra-update as a 'safe update'. The pre-existing AGENTS.md is not stamped. No write happens before the explicit merge decision. | O9: Hybrid | P9: QA | Q9: Infrastructure-Creator/.agents/skills/infra-generate/SKILL.md | R9: This is the key data-loss protection for teams adopting the generator on an already-accelerated project; coverage enforcement is deliberately off for mode merge in validate_generated.py.
A10: TC-009 | B10: Laravel end-to-end feature chain: brainstorm to verify | C10: Feature implementation | D10: Laravel | E10: Claude Code | F10: brainstorming -> architect -> architecture-implementer -> coder -> verify | G10: /brainstorm -> /architect -> /architecture-implementer -> /coder -> /verify (agents: brainstorming, architect, architecture-implementer, coder, verify) | H10: Critical | I10: Contents of Laravel/ edition (AGENTS.md, .claude/ with skills+agents+commands+hooks, specs/, tasks/) copied into the root of a working Laravel 12 sample application. Claude Code launched in that workspace. Git clean, on a feature branch (not main). composer install done, php artisan test green before start. | J10: /brainstorm Guest checkout: let a customer place an order without creating an account. Then follow each agent's suggested next command through /architect, /architecture-implementer, /coder and finish with /verify. | K10: 1) /brainstorm spawns the brainstorming agent; it inspects project state first, asks questions ONE at a time via AskUserQuestion, offers library-vs-custom choices with Laravel built-ins recommended by default, and produces a design doc prefixed brainstorming-. It ends with a Context Summary and suggests /architect (flow-next in SKILL.md frontmatter) without auto-chaining (SKILL FLOW.md: 'Agents suggest the next command but do not automatically chain'). 2) /architect spawns the architect agent (subagent_type architect, model opus per Laravel/.claude/agents/architect-agent.md), decides Controller/Form Request/Policy/Action placement per the skill's decision tree, and updates specs/architect-architecture.md and specs/MANIFEST.md. 3) /architecture-implementer scaffolds the skeleton via artisan make:* generators (migration, model+factory, Policy, Form Request, API Resource, controller, routes) with TODO markers and NO business logic. 4) /coder fills in behavior: Form Request rules, Action/Service body, thin controller, tests. 5) /verify determines the DoD tier (Standard for implementation), runs composer validate --strict, php -l on changed files, php artisan test, vendor/bin/pint --test, vendor/bin/phpstan analyse where configured, and reports pass/fail with N/A for missing tooling. | L10: tasks/TASK-00N/brainstorming-design.md; specs/architect-architecture.md; specs/MANIFEST.md; database/migrations/*_create_orders_table.php (or similar); app/Models/*, app/Http/Controllers/*, app/Http/Requests/*, app/Policies/*, app/Http/Resources/*; routes/web.php or routes/api.php; tests/Feature/* | M10: php artisan test (exit 0); php artisan route:list | grep -i order (new routes present); grep -rL "declare(strict_types=1)" app/ --include='*.php' returns nothing new; vendor/bin/pint --test (exit 0); grep -n 'Guest checkout' specs/architect-architecture.md (decision recorded); find tasks specs -name '*.md' | grep -vE '/(README|CHANGELOG|MANIFEST)\.md$' | grep -vE '/[a-z][a-z-]*-[A-Za-z0-9._-]+\.md$' returns empty (naming convention held). | N10: No phase auto-chains into the next without the user issuing the command. brainstorming writes no application code. architecture-implementer contains no business/validation/policy logic (TODO stubs only). No .env read/print/commit, no secrets in files (AGENTS.md Security). No git push --force or --no-verify (AGENTS.md Git Safety). /verify never installs missing tooling. file-naming-validator.sh hook not bypassed: no unprefixed .md appears in tasks/ or specs/. | O10: Hybrid | P10: QA | Q10: Laravel/.claude/skills/SKILL FLOW.md | R10: This is the flagship happy-path scenario. Verifies both the deliverable and the flow discipline (suggest-next, do-not-auto-chain). Expect AskUserQuestion interaction, so a human tester must answer the brainstorming questions.
A11: TC-010 | B11: Laravel eloquent skill: polymorphic relation with Observer | C11: Feature implementation | D11: Laravel | E11: Claude Code | F11: eloquent | G11: /eloquent (agent: eloquent, file Laravel/.claude/agents/eloquent-agent.md) | H11: High | I11: Laravel edition installed in a sample app that already has Post and Video models with migrated tables (eloquent SKILL.md assumes schema exists — schema design belongs to database-designer). Git clean on a feature branch. | J11: /eloquent Add a polymorphic Comment model that can belong to either a Post or a Video, add an approved() local query scope, and a CommentObserver that clears the post cache when a comment is saved. | K11: The eloquent agent invokes the eloquent skill and stays inside its scope boundary (model-layer behavior only). It creates a migration using morphs('commentable') (commentable_type/commentable_id pair), a Comment model with a commentable(): MorphTo relation, comments(): MorphMany relations on Post and Video with the 'commentable' morph name, a scopeApproved local scope, a CommentObserver registered (ObservedBy attribute or boot registration), mass-assignment protection via $fillable, and eager-loading guidance for reading comments. It suggests /code-reviewer next (flow-next in frontmatter). If asked to redesign the table schema it should defer to database-designer per Scope Boundary. | L11: database/migrations/*_create_comments_table.php; app/Models/Comment.php; app/Models/Post.php (modified); app/Models/Video.php (modified); app/Observers/CommentObserver.php; tests/Feature/ or tests/Unit/ comment tests | M11: grep -n 'morphTo' app/Models/Comment.php; grep -n "morphMany(Comment::class, 'commentable')" app/Models/Post.php app/Models/Video.php; grep -n 'morphs(' database/migrations/*_create_comments_table.php; grep -rn 'CommentObserver' app/; php artisan test --filter=Comment (exit 0); grep -n 'fillable' app/Models/Comment.php ($guarded = [] must NOT be used). | N11: No schema redesign of existing Post/Video tables beyond the additive comments table. No $guarded = [] on a user-input model (flagged by code-reviewer checklist). No raw SQL concatenation. No changes outside the model layer plus its migration/tests (no controller/route edits unless explicitly asked). | O11: Hybrid | P11: QA | Q11: Laravel/.claude/skills/eloquent/SKILL.md | R11: The SKILL.md Scope Boundary is a key assertion: the agent must not drift into database-designer or coder territory.
A12: TC-011 | B12: Laravel queues-jobs skill: resilient payment job | C12: Feature implementation | D12: Laravel | E12: Claude Code | F12: queues-jobs | G12: /queues-jobs (agent: queues-jobs, file Laravel/.claude/agents/queues-jobs-agent.md) | H12: High | I12: Laravel edition installed in a sample app with an Order model and a queue driver configured (database or redis). Git clean on a feature branch. | J12: /queues-jobs Create a ProcessPayment job for orders: 3 tries with increasing backoff, must never run twice concurrently for the same order, handle permanent failure by marking the order payment_failed. | K12: The queues-jobs agent implements a job matching the skill's Job Class Anatomy: final class ProcessPayment implements ShouldQueue with Dispatchable/InteractsWithQueue/Queueable/SerializesModels traits, public int $tries = 3, an array $backoff (e.g. [10, 30, 60]), constructor carrying a scalar orderId (not a serialized model graph), overlap protection via WithoutOverlapping job middleware keyed by order id (or ShouldBeUnique where uniqueness across dispatches is required), a failed(\Throwable $e) method updating the order status, and a test using Queue::fake()/Bus::fake(). The job body is idempotent (safe under at-least-once redelivery). It suggests /test-generator next (flow-next). | L12: app/Jobs/ProcessPayment.php; tests/Feature/ProcessPaymentTest.php (or Unit); possibly app/Models/Order.php status handling | M12: grep -n 'implements ShouldQueue' app/Jobs/ProcessPayment.php; grep -n 'public int \$tries' app/Jobs/ProcessPayment.php; grep -n 'backoff' app/Jobs/ProcessPayment.php; grep -n 'WithoutOverlapping\|ShouldBeUnique' app/Jobs/ProcessPayment.php; grep -n 'function failed' app/Jobs/ProcessPayment.php; php artisan test --filter=ProcessPayment (exit 0). | N12: Job must be idempotent — the review checklist in code-reviewer SKILL.md ('Jobs, Queues, And Events') is the acceptance bar: no double-charge on redelivery, failures not silently dropped. No Horizon config invented if the project does not use Horizon. No synchronous fallback that hides the queue path in tests. | O12: Hybrid | P12: QA | Q12: Laravel/.claude/skills/queues-jobs/SKILL.md | R12: The decision WHETHER to queue belongs to architect per the Scope Boundary; this test hands the agent an already-made async decision.
... A93: TC-AI-018 | B93: Native host runtime smoke across AI tools | C93: Cross-tool parity | D93: Cross-stack | E93: Cross-tool | F93: host integration | G93: CLI availability and native hooks | H93: High | I93: Local host tool installations discoverable | J93: Execute native smoke coverage for Claude Code, Cursor and Codex | K93: All selected host runtimes available for native execution | L93: None | M93: Availability probed for all three tools | N93: No plugin installation or credential changes without approval | O93: Manual | P93: OpenAI Codex | Q93: docs/TOOL-INTEGRATIONS.md | R93: Codex available; Claude and Cursor CLIs unavailable locally.

Sheet Test Runs
A1: Run ID | B1: Test Case ID | C1: Execution Date | D1: Tester | E1: Accelerator Version | F1: Git Commit | G1: Framework | H1: Framework Version | I1: AI Tool | J1: AI Tool Version | K1: Model | L1: Operating Mode | M1: Project Size | N1: Starting Repository State | O1: Result | P1: Actual Behaviour | Q1: Files Created | R1: Files Modified | S1: Unexpected Changes | T1: Tests Executed | U1: Tests Passed | V1: Tests Failed | W1: Linter Result | X1: Human Intervention Count | Y1: Retry Count | Z1: Safety Violation Count | AA1: Failure Reason | AB1: Evidence Link | AC1: Defect ID | AD1: Comments
A2: RUN-001 | B2: TC-001 | C2: 2026-08-03 | D2: Claude Fable 5 (scripted execution) | E2: 1.4.3 | F2: 3a02537 | G2: Laravel | H2: n/a (edition workspace) | I2: Claude Code | J2: n/a — scripted run (no AI client) | K2: n/a | L2: Governed | M2: Small | N2: Clean checkout at 3a02537; mutating steps ran in a temp copy | O2: Pass | P2: Ran bash .claude/hooks/local-context.sh from Laravel/ edition root twice. Banner printed 'Project Context' / '===============' / 'Accelerator version: 1.4.3' (matches VERSION). Git line 'Branch: merge/context-brain-reconciliation (0 uncommitted changes)' present. NOTE 'No artisan file found...' printed as expected for the accelerator folder itself. Pre-seeded counter file under /tmp/claude-loop-detection-4129921039 was deleted (0 files after run). Context governance line printed metadata only: 'mode=governed, index=healthy/stale, active-bindings=0, brain-validation=valid'. Memory bank line ends with the required 'Read memory-bank/README.md and INDEX.md...' sentence. Cache files brain-validation-436674262 and memory-summary-436674262 created under /tmp/ai-accelerator-session-cache-*; warm run 292 ms vs cold 945 ms (3.2x faster) with identical governance line. Exit code 0 on both runs. | Q2: /tmp/claude-loop-detection-* and /tmp/ai-accelerator-session-cache-* state (temp only); evidence log | R2: None | S2: None | T2: 9 | U2: 9 | V2: 0 | W2: bash -n clean | X2: 0 | Y2: 0 | Z2: 0 | AB2: Accelerator-TestEvidence/TC-001.log | AD2: Governance line showed index=healthy/stale (expected text illustrates healthy/current; the value is checkout-state-dependent, format and metadata-only contract match). Interactive item 9 (typing '/' shows /verify, /memory, /project-brain) requires a live Claude Code client and was not executed; scripted part fully matched, so Pass with that caveat.
A3: RUN-002 | B3: TC-002 | C3: 2026-08-03 | D3: Claude Fable 5 (scripted execution) | E3: 1.3.1 | F3: 3a02537 | G3: Symfony | H3: n/a (edition workspace) | I3: Claude Code | J3: n/a — scripted run (no AI client) | K3: n/a | L3: Governed | M3: Small | N3: Clean checkout at 3a02537; mutating steps ran in a temp copy | O3: Pass | P3: Scenario (a) from Symfony/ edition root: banner printed 'Accelerator version: 1.3.1', NOTE 'Symfony bin/console was not detected. Apply these Symfony rules only after confirming this is a Symfony project.' and did NOT print the 'Framework: Symfony detected' hint; exit 0. Scenario (b) in a temp scratch host repo containing bin/console: running the Symfony edition hook printed 'Framework: Symfony detected. Use Symfony Controller -> Service -> Repository conventions.'; exit 0. Loop counter pre-seeded for the repo key was wiped by the hook (0 files left). Session cache dirs present under /tmp/ai-accelerator-session-cache-*. | Q3: scratchpad/exec-hooks/symfony-host (temp copy); /tmp state; evidence log | R3: None | S3: None | T3: 7 | U3: 7 | V3: 0 | W3: bash -n clean | X3: 0 | Y3: 0 | Z3: 0 | AB3: Accelerator-TestEvidence/TC-002.log | AD3: bin/console host scenario executed against a temp scratch repo to keep the monorepo tree clean. Wrong-stack hint correctly suppressed when bin/console absent. Live-client portion (session start inside the IDE) not executed; scripted part fully matched.
A4: RUN-003 | B4: TC-003 | C4: 2026-08-03 | D4: Claude Fable 5 (scripted execution) | E4: 1.2.1 | F4: 3a02537 | G4: PHP Core | H4: n/a (edition workspace) | I4: Claude Code | J4: n/a — scripted run (no AI client) | K4: n/a | L4: Governed | M4: Small | N4: Clean checkout at 3a02537; mutating steps ran in a temp copy | O4: Pass | P4: Ran the hook from 'PHP Core' (path with a space). Banner printed 'Project Context' first line and 'Accelerator version: 1.2.1'; zero 'No such file or directory' errors on either stream; exit 0. Framework guard verified in a temp host repo with cakephp/cakephp in composer.json and public/index.php: hook printed 'NOTE: CakePHP detected. This is the native-PHP base folder (PHP Core/).' plus 'Entry point: public/index.php (front controller)'; exit 0. Governance line printed metadata only (mode=governed, brain-validation=valid). | Q4: scratchpad/exec-hooks/phpcore-host (temp copy); /tmp state; evidence log | R4: None | S4: None | T4: 7 | U4: 7 | V4: 0 | W4: bash -n clean | X4: 0 | Y4: 0 | Z4: 0 | AB4: Accelerator-TestEvidence/TC-003.log | AD4: Space-in-path handling confirmed clean (BASH_SOURCE-derived paths are quoted). Framework guard steers to correct edition without claiming a framework workflow.
A5: RUN-004 | B5: TC-004 | C5: 2026-08-03 | D5: Claude Fable 5 (scripted execution) | E5: 1.4.3 | F5: 3a02537 | G5: Laravel | H5: n/a (edition workspace) | I5: Cursor | J5: n/a — scripted run (no AI client) | K5: n/a | L5: Governed | M5: Small | N5: Clean checkout at 3a02537; mutating steps ran in a temp copy | O5: Partial | P5: Executed in a temp copy of the Laravel edition (git init + add). Structural: working-memory-read.sh absent by design; hooks.json is valid JSON with exactly 5 command entries wired exactly as specified (sessionStart->local-context 15, beforeShellExecution->bash-validator 5, afterFileEdit->file-naming-validator 5 + loop-detection 5, stop->working-memory-write 15); the three .mdc rules present; .gitignore line 17 ignores .cursor/rules/working-memory.mdc (git check-ignore confirms); Cursor local-context.sh contains the session-start re-render logic; Cursor loop-detection uses /tmp/cursor-loop-detection-<key>. Behavioral deviation: the first run of CONTEXT_TASK_ID=qa-cursor-activation bash .cursor/hooks/working-memory-write.sh exited 0 but did NOT create working-memory.mdc — 'context.py context' failed with 'Working task not found' because the working task is only auto-provisioned after the flush threshold (flush-after=5 buffered turns). After 5 more buffered turns the capsule existed and a re-run of the stop hook rendered the rule correctly: frontmatter 'description: Working memory - Task Capsule as of end of previous turn', 'alwaysApply: true', '# Working Memory (auto-rendered)', fenced capsule, no diff/file contents or secrets inside, atomically replaced, ignored by git. | Q5: scratchpad/exec-hooks/laravel-cursor full edition copy incl. .cursor/rules/working-memory.mdc (temp copy) | R5: None in the real repo | S5: None | T5: 11 | U5: 10 | V5: 1 | W5: bash -n clean | X5: 0 | Y5: 1 | Z5: 0 | AA5: Expected behaviour item 4 ('After the stop hook runs, .cursor/rules/working-memory.mdc exists') does not hold on a fresh install: the rule is rendered only once the working task exists, which happens after 5 buffered turns (CONTEXT_FLUSH_AFTER default). First stop-hook run produced no rule file. | AB5: Accelerator-TestEvidence/TC-004.log | AC5: DEF-001 | AD5: Cursor in-IDE items (single session-context report, rule attachment to next prompt) require the live Cursor client and were not executed. All scriptable checks passed except the first-run render gap recorded as a defect.
A6: RUN-005 | B6: TC-005 | C6: 2026-08-03 | D6: Claude Fable 5 (scripted execution) | E6: 1.4.3 | F6: 3a02537 | G6: Laravel | H6: n/a (edition workspace) | I6: Codex | J6: n/a — scripted run (no AI client) | K6: n/a | L6: Governed | M6: Small | N6: Clean checkout at 3a02537; mutating steps ran in a temp copy | O6: Pass | P6: Script-part checks from Laravel/ root: .codex/config.toml contains '[features]' followed by 'hooks = true'; MCP example remains commented ('# [mcp_servers.github]'). .codex/hooks.json is valid JSON, wires SessionStart->local-context, UserPromptSubmit->working-memory-read (additionalContextLimit: 4000), Stop->working-memory-write, PreToolUse->bash-validator + file-naming-validator, PostToolUse->loop-detection, with no matcher on any group. Read payload piped to .codex/hooks/bash-validator.sh exited 0 silently (cheap self-filter, no extractor forked). Destructive payload {"command":"git push --force origin main"} exited 2 with stderr 'BLOCKED: Destructive command detected: matches pattern ...' and empty stdout. .codex/commands and .codex/agents both absent. .agents/skills contains verify, memory, project-brain, coder. .codex/hooks/local-context.sh printed the metadata-only banner and exited 0. | Q6: /tmp state only; evidence log | R6: None | S6: None | T6: 13 | U6: 13 | V6: 0 | W6: bash -n clean | X6: 0 | Y6: 0 | Z6: 0 | AB6: Accelerator-TestEvidence/TC-005.log | AD6: Trust-prompt gating (untrusted project must not load .codex config) and the live skills menu require the Codex CLI and were not executed; the scripted part fully matched, so Pass with that caveat.
A7: RUN-006 | B7: TC-007 | C7: 2026-08-03 | D7: Claude Fable 5 (scripted execution) | E7: 1.4.0 | F7: 3a02537 | G7: Infrastructure-Creator | H7: n/a (edition workspace) | I7: Claude Code | J7: n/a — scripted run (no AI client) | K7: n/a | L7: Not Applicable | M7: Small | N7: Clean checkout at 3a02537; mutating steps ran in a temp copy | O7: Partial | P7: The /infra-generate agent pipeline (forge fan-out, TASK profile consumption, report) cannot run scriptally, so the target was assembled by hand in a temp copy strictly following memory-seed/hook-forge/infra-generate SKILL.md instructions (verbatim asset copies, runtime.json substitutions generic/.claude, six hooks, quartet skills+agents+commands, stamped AGENTS.md, manifest via the exact SKILL.md recipe with version from the VERSION file). Every scriptable verification from the case then passed: validate_generated.py --editions claude exit 0 on first run; context.py status and validate both exit 0 from the target root; AGENTS.md first line matches 'Generated by Infrastructure-Creator v1.4.0 | TASK-1'; no .cursor/.codex/.agents roots exist; memory-quartet skill count is exactly 4; zero template placeholders in generated files. | Q7: exec-ic/fake-php-app/ full synthetic accelerator, build_green_target.sh (temp copy, scratchpad only) | R7: None | S7: None | T7: 7 | U7: 7 | V7: 0 | W7: bash -n clean on all 6 hook scripts | X7: 0 | Y7: 0 | Z7: 0 | AA7: LLM phases (profile re-validation, forge fan-out, infra-generate-report.md) require an interactive AI client run; only the structural/verification contract was executed | AB7: Accelerator-TestEvidence/TC-007.log | AD7: The bootstrap-verifier + manifest recipe + memory-seed asset contract is fully consistent: a target assembled exactly per the SKILL instructions verifies green on the first attempt. Repo tree confirmed clean after the run.
A8: RUN-007 | B8: TC-008 | C8: 2026-08-03 | D8: Claude Fable 5 (scripted execution) | E8: 1.4.0 | F8: 3a02537 | G8: Infrastructure-Creator | H8: n/a (edition workspace) | I8: Claude Code | J8: n/a — scripted run (no AI client) | K8: n/a | L8: Not Applicable | M8: Small | N8: Clean checkout at 3a02537; mutating steps ran in a temp copy | O8: Partial | P8: The interactive collision-guard dialogue cannot run scriptally; the merge mechanics were executed by hand per the SKILL: target built with a team-authored AGENTS.md and .claude/hooks/deploy-check.sh, preexisting-files.txt snapshotted before any writes, only missing files added, merge-mode manifest written via the exact SKILL.md recipe with the preexisting list. All four case verifications passed: sha256sum -c OK for both team files; manifest mode=merge, AGENTS.md and deploy-check.sh both absent from files; preexisting-files.txt lists AGENTS.md; validate_generated.py exit 0 (stamp check correctly skipped for the untracked team AGENTS.md, coverage correctly not enforced for merge). Additional probe found a defect: appending a normal 'TODO:' roadmap line to the team AGENTS.md makes the validator fail with 'leftover placeholder', because check_placeholders(AGENTS.md) runs unconditionally even when the file is a pre-existing untracked team file. | Q8: exec-ic/fake-php-app-merge/, exec-ic/task-3/preexisting-files.txt, tc008.sh (temp copies, scratchpad only) | R8: None | S8: None | T8: 7 | U8: 6 | V8: 1 | W8: Not Applicable | X8: 0 | Y8: 0 | Z8: 0 | AA8: Collision-guard stop/ask flow requires an interactive AI client; placeholder-scan defect found on team AGENTS.md | AB8: Accelerator-TestEvidence/TC-008.log | AC8: DEF-002 | AD8: Core safety property holds mechanically: pre-existing files are byte-identical after merge and never claimed by the manifest. The placeholder-scan gap is the only crack in the merge contract.
A9: RUN-008 | B9: TC-014 | C9: 2026-08-03 | D9: Claude Fable 5 (scripted execution) | E9: 1.4.0 | F9: 3a02537 | G9: Infrastructure-Creator | H9: n/a (edition workspace) | I9: Claude Code | J9: n/a — scripted run (no AI client) | K9: n/a | L9: Not Applicable | M9: Small | N9: Clean checkout at 3a02537; mutating steps ran in a temp copy | O9: Partial | P9: The infra-update agent cannot run scriptally; its step-5 classification table and Decision Memory rules were executed literally by a script (triage.py) against manifest + staged tree + target. Results: user-modified local-context.sh (hash != manifest) -> requires-decision, exactly 1 such row; untouched loop-detection.sh -> safe-update no-op; unmanifested .claude/skills-notes.md never iterated, read or reported (0 rows). 'Keep' decision applied per steps 7-8: AGENTS.md re-stamped TASK-2, manifest rewritten via the full recipe with a decisions entry {kept, 64-char rejected_sha256, TASK-2}; 'team tweak' still present (grep -c = 1); no staging dir inside the target. Regression run: staged sha == rejected_sha256 -> standing-decision-honored, file not overwritten; variant with changed generator output -> requires-decision again. Negative probes: validator rejects decision='replaced', a decisions entry for an untracked file, and a non-sha256 rejected_sha256. FAILED step: the case expects validate_generated.py exit 0 after the update, but it exits 1 with 'generated file not tracked: .claude/skills-notes.md' - full-mode coverage demands every file under .claude be manifest-tracked, contradicting infra-update's untouchable-file guardrail. | Q9: exec-ic/fake-php-app-update/, exec-ic/task-2-staging/, triage.py, tc014.sh (temp copies, scratchpad only) | R9: None | S9: None | T9: 11 | U9: 10 | V9: 1 | W9: Not Applicable | X9: 0 | Y9: 2 | Z9: 0 | AA9: validate_generated.py exit 1 instead of expected 0: full-mode coverage flags the team's untouchable .claude/skills-notes.md as 'generated file not tracked'; also interactive decision presentation and infra-update-report.md require an AI client | AB9: Accelerator-TestEvidence/TC-014.log | AC9: DEF-003 | AD9: Retries were harness-side only (a bash heredoc syntax slip, then an over-broad staging tree that wrongly included fixture files); the product checks behaved identically across runs. The classification and decision-memory mechanics themselves are sound and the validator enforces the decisions schema strictly.
A10: RUN-009 | B10: TC-015 | C10: 2026-08-03 | D10: Claude Fable 5 (scripted execution) | E10: 1.4.0 | F10: 3a02537 | G10: Infrastructure-Creator | H10: n/a (edition workspace) | I10: Claude Code | J10: n/a — scripted run (no AI client) | K10: n/a | L10: Not Applicable | M10: Small | N10: Clean checkout at 3a02537; mutating steps ran in a temp copy | O10: Partial | P10: Step 1 of infra-update was executed scriptally on a temp copy: manifest deleted, marker touched, sha256 baseline recorded; the scripted step attempted to load <target>/.infra-manifest.json, got FileNotFoundError and aborted with the legacy-generation explanation and both SKILL-mandated recovery options, fabricating nothing. Verifications: find -newer marker = 0 files, manifest still absent, all baseline sha256 OK - zero writes into the target before the abort. | Q10: exec-ic/fake-php-app-legacy/, exec-ic/pre-abort.sha256, exec-ic/update.marker (temp copies, scratchpad only) | R10: None | S10: None | T10: 4 | U10: 4 | V10: 0 | W10: Not Applicable | X10: 0 | Y10: 0 | Z10: 0 | AA10: The transcript-level expectations (agent phrasing of the legacy explanation and recovery options, refusal behavior under user pressure) require an interactive AI client run | AB10: Accelerator-TestEvidence/TC-015.log | AD10: The abort contract as written in infra-update SKILL.md step 1 is mechanically satisfiable with zero target writes; only agent-conversation fidelity remains unverified.
A11: RUN-010 | B11: TC-016 | C11: 2026-08-03 | D11: Claude Fable 5 (scripted execution) | E11: 1.4.0 | F11: 3a02537 | G11: Infrastructure-Creator | H11: n/a (edition workspace) | I11: Cursor | J11: n/a — scripted run (no AI client) | K11: n/a | L11: Not Applicable | M11: Small | N11: Clean checkout at 3a02537; mutating steps ran in a temp copy | O11: Partial | P11: hook-forge generation itself is LLM-only, so the hook contract was verified two ways. (1) A claude+cursor assembly built per the SKILL contract passed every case verification: 6 hooks in .claude/hooks; working-memory-read.sh deliberately absent from .cursor/hooks; all scripts bash -n clean and executable; zero terraform/kubectl rules in bash-validator (no IaC evidence in the fixture); .cursor/hooks.json version 1 with camelCase events and bare paths; zero interpreter-prefixed commands in settings.json; .cursor/rules/working-memory.mdc gitignored; working-memory-read.sh calls memory-bank/scripts/context.py at the fixed path; validate_generated.py --editions claude,cursor exit 0. Both negatives were caught by the validator: adding working-memory-read.sh to Cursor -> 'no prompt-time hook event' error; stripping the capsule render from the Cursor write hook -> 'does not render the alwaysApply working-memory rule' error. (2) The Infrastructure-Creator hook regression suite (tests/test_hooks.py) ran read-only: 21/21 tests OK, including mirror byte-identity and loop/naming/bash-validator behavior. | Q11: exec-ic/fake-php-app-cursor/, tc016.sh (temp copies, scratchpad only) | R11: None | S11: None | T11: 32 | U11: 32 | V11: 0 | W11: bash -n clean on all 11 hook scripts (6 claude + 5 cursor) | X11: 0 | Y11: 0 | Z11: 0 | AA11: Actual hook-forge generation (danger-rule derivation from profile sections 4/5/6, hook-forge-log.md with citations) requires an interactive AI client run | AB11: Accelerator-TestEvidence/TC-016.log | AD11: The Cursor read-path asymmetry is enforced in both directions by validate_generated.py, so a hook-forge run that violated it could not verify green. IC's own hook suite (21 tests) is fully green.
A12: RUN-011 | B12: TC-017 | C12: 2026-08-03 | D12: Claude Fable 5 (scripted execution) | E12: 1.4.0 | F12: 3a02537 | G12: Infrastructure-Creator | H12: n/a (edition workspace) | I12: Claude Code | J12: n/a — scripted run (no AI client) | K12: n/a | L12: Not Applicable | M12: Small | N12: Clean checkout at 3a02537; mutating steps ran in a temp copy | O12: Partial | P12: memory-seed was executed by hand on a framework-less plain-PHP fixture, applying the SKILL's substitution rules deterministically (no confirmed framework -> 'generic'; editions [claude] -> canonical '.claude'). All case verifications passed: runtime.json reads 'generic .claude'; zero unsubstituted placeholders anywhere under project-brain/; validate.py, context.py validate and context.py status all exit 0; first chunk is MEM-0001-composer-autoload.md; INDEX.md header is the exact 8-column table; all four runtime scripts plus chunk.md are byte-identical to assets/ (diff empty); the only project-brain delta vs assets is the materialized runtime.json replacing runtime.json.template; .memory-counter is 3 (one past MEM-0002). | Q12: exec-ic/plain-php-app/ (temp copy, scratchpad only) | R12: None | S12: None | T12: 9 | U12: 9 | V12: 0 | W12: Not Applicable | X12: 0 | Y12: 0 | Z12: 0 | AA12: Whether the memory-seed agent itself chooses 'generic' over an invented framework slug is an LLM decision requiring an interactive AI client run; the mechanical recipe and its safety rationale were verified | AB12: Accelerator-TestEvidence/TC-017.log | AD12: The degrade-to-generic design claim holds in the runtime: an unrecognized slug contributes no framework exceptions and canonical '.claude' pointing at an existing skills tree keeps status/validate green.
A13: RUN-012 | B13: TC-028 | C13: 2026-08-03 | D13: Claude Fable 5 (scripted execution) | E13: 1.4.3 | F13: 3a02537 | G13: Laravel | H13: n/a (edition workspace) | I13: Claude Code | J13: n/a — scripted run (no AI client) | K13: n/a | L13: Not Applicable | M13: Small | N13: Clean checkout at 3a02537; mutating steps ran in a temp copy | O13: Pass | P13: Unit tests test_destructive_commands_blocked_with_stderr, test_nested_destructive_command_still_blocked, test_block_message_names_the_matching_pattern all OK (run across .claude/.cursor/.codex mirrors). Manual payloads against Laravel/.claude/hooks/bash-validator.sh: 'git push --force origin main', 'git reset --hard HEAD~1', 'git commit --no-verify -m wip', 'mysql -e "DROP TABLE users;"', and nested 'bash -c "git reset --hard"' each exited 2 with empty stdout and exactly the three stderr lines (BLOCKED with named pattern / Command echo / 'This operation is blocked. See AGENTS.md.'). Spot-check 'DELETE FROM users WHERE 1=1' also blocked with exit 2 and its named pattern. No files created or modified by the hook; the destructive commands were never executed. | Q13: None (temp /tmp capture files only) | R13: None | S13: None | T13: 9 | U13: 9 | V13: 0 | W13: bash -n clean | X13: 0 | Y13: 0 | Z13: 0 | AB13: Accelerator-TestEvidence/TC-028.log | AD13: Nested-command extraction verified: the inner 'git reset --hard' behind escaped quotes was matched and named as the pattern.
A14: RUN-013 | B14: TC-029 | C14: 2026-08-03 | D14: Claude Fable 5 (scripted execution) | E14: 1.4.3 | F14: 3a02537 | G14: Laravel | H14: n/a (edition workspace) | I14: Cross-tool | J14: n/a — scripted run (no AI client) | K14: n/a | L14: Not Applicable | M14: Small | N14: Clean checkout at 3a02537; mutating steps ran in a temp copy | O14: Pass | P14: Unit tests test_escaped_quotes_survive_extraction, test_unparsable_stdin_fails_open_quietly, test_command_text_in_foreign_tool_payload_is_ignored all OK. Manual: (a) Bash payload with commit message containing \" and \\\" sequences -> exit 0, empty stdout and stderr; (b) raw non-JSON prose mentioning 'git reset --hard' -> exit 0, both streams empty (no sed-scraper regression); (c) Write payload whose content string embeds {"command": "git reset --hard"} -> exit 0, empty streams. Payload (c) repeated against the .cursor and .codex mirrors: exit 0, empty stderr. No state files created by the hook. | Q14: None | R14: None | S14: None | T14: 8 | U14: 8 | V14: 0 | W14: bash -n clean | X14: 0 | Y14: 0 | Z14: 0 | AB14: Accelerator-TestEvidence/TC-029.log | AD14: JSON decoding demonstrably survives escaped and double-escaped quotes; the escaped '\"command\"' key inside a string value never triggers the self-filter.
A15: RUN-014 | B15: TC-030 | C15: 2026-08-03 | D15: Claude Fable 5 (scripted execution) | E15: 1.4.3 | F15: 3a02537 | G15: Laravel | H15: n/a (edition workspace) | I15: Claude Code | J15: n/a — scripted run (no AI client) | K15: n/a | L15: Not Applicable | M15: Small | N15: Clean checkout at 3a02537; mutating steps ran in a temp copy | O15: Partial | P15: Literal scenario from the case (env PATH=/nonexistent, /bin/bash invoked absolutely): hook exited 0 with empty stdout — fail-open holds and the destructive command is not blocked-hard — but stderr contained 'bash-validator.sh: line 7: cat: command not found' instead of the documented warning; the 'no JSON extractor available' message did not appear (grep count 0) because INPUT=$(cat) on line 7 depends on the external cat binary, which is also unresolvable, so the empty input takes the silent self-filter exit before the extractor guard. Surgical scenario (PATH containing only cat, no jq/php/python3): hook exited 0, empty stdout, and stderr printed verbatim 'bash-validator: no JSON extractor available (jq/php/python3), validation skipped' — exactly the documented behavior. First attempt used 'env PATH=/nonexistent bash' which failed with exit 127 (env could not resolve bash itself) — executor invocation flaw, corrected to an absolute /bin/bash path. | Q15: None (payload fixture in /tmp) | R15: None | S15: None | T15: 2 | U15: 1 | V15: 1 | W15: bash -n clean | X15: 0 | Y15: 1 | Z15: 0 | AA15: In the exact scenario the case specifies (entire PATH cleared), the documented verbatim stderr warning is not printed; a 'cat: command not found' noise line appears instead. Exit 0 / no-stdout / no-hard-block safety properties hold in both scenarios. | AB15: Accelerator-TestEvidence/TC-030.log | AC15: DEF-004 | AD15: Residual risk (as the case demands be recorded): with no extractor available, destructive commands pass unvalidated and the warning is the only signal — and in a truly cat-less minimal image even that signal is lost. Defect filed accordingly.
A16: RUN-015 | B16: TC-032 | C16: 2026-08-03 | D16: Claude Fable 5 (scripted execution) | E16: 1.4.3 | F16: 3a02537 | G16: Laravel | H16: n/a (edition workspace) | I16: Claude Code | J16: n/a — scripted run (no AI client) | K16: n/a | L16: Not Applicable | M16: Small | N16: Clean checkout at 3a02537; mutating steps ran in a temp copy | O16: Partial | P16: Structural verification executed in full: Laravel/.claude/commands/security-reviewer.md declares 'spawns: security-reviewer-agent' and passes $ARGUMENTS with subagent_type 'security-reviewer' and description 'Security audit'; the agent file declares 'invokes: security-reviewer', 'model: opus', and constraints 'ONLY execute the security-reviewer skill' / 'DO NOT chain to other skills automatically'; skills/security-reviewer/SKILL.md exists and covers the full checklist (A01..A10, IDOR, DB::raw x3, {!! !!} x2, composer audit x4, APP_DEBUG x3, CSRF, mass assignment, SSRF, unserialize, throttle), a Critical/High/Medium/Low severity table, the overall verdict scheme '[BLOCK / fix-then-merge / acceptable]', and guardrails 'Never print or exfiltrate real secrets' and 'Never read, print, or commit .env contents'. The live OWASP audit against a deliberately vulnerable Laravel host project was not executed (requires an interactive AI coding session). | Q16: None | R16: None | S16: None | T16: 15 | U16: 15 | V16: 0 | W16: Not Applicable | X16: 0 | Y16: 0 | Z16: 0 | AA16: Behavioral portion (actual audit run, transcript review, planted-vulnerability detection) requires a live Claude Code session and could not be executed; only the static wiring and skill-content contract was verified. | AB16: Accelerator-TestEvidence/TC-032.log | AD16: Minor case-vs-artifact drift: the case text lists '/dependency-manager' among next-step alternatives, but the command frontmatter ships 'flow-alternatives: [coder, code-reviewer, debugger]' (flow-next: verify). Not filed as a product defect — looks like test-case doc drift; worth reconciling in the QA book.
A17: RUN-016 | B17: TC-033 | C17: 2026-08-03 | D17: Claude Fable 5 (scripted execution) | E17: monorepo @ 3a02537 | F17: 3a02537 | G17: Cross-stack | H17: n/a (edition workspace) | I17: Cross-tool | J17: n/a — scripted run (no AI client) | K17: n/a | L17: Not Applicable | M17: Small | N17: Clean checkout at 3a02537; mutating steps ran in a temp copy | O17: Pass | P17: Step 1 in the real repo (read-only): 'python3 scripts/build_mirrors.py --check' printed 'Mirror check passed for: Laravel, Symfony, PHP Core, Infrastructure-Creator', exit 0; git status stayed empty. Running with no mode flag produced the argparse error 'one of the arguments --check --write is required', exit 2, and the usage line shows --edition restricted to the four known edition names. All mutation steps ran in a temp git clone: appending '<!-- drift test -->' to Laravel/.cursor/skills/coder/SKILL.md made --check emit 'Mirror drift (1 finding(s)):' with the exact line 'Laravel: [skills] .cursor/skills/coder/SKILL.md differs from canon (.agents/skills/coder/SKILL.md)', exit 1. '--write --edition Laravel' printed 'wrote Laravel/.cursor/skills/coder/SKILL.md' and 'Mirrors up to date for: Laravel (1 file(s) written)'; a subsequent --check passed with exit 0 and the copy's git status showed only the regenerated mirror byte-identical to canon. Reverse pass: an orphan file present only in the mirror (Laravel/.cursor/skills/coder/ORPHAN.md) was flagged as 'has no source in .agents/skills', exit 1. Copy restored to clean after each mutation. | Q17: Laravel/.cursor/skills/coder/ORPHAN.md (temp copy, removed) | R17: Laravel/.cursor/skills/coder/SKILL.md (temp copy, restored) | S17: None | T17: 6 | U17: 6 | V17: 0 | W17: Not Applicable | X17: 0 | Y17: 0 | Z17: 0 | AB17: Accelerator-TestEvidence/TC-033.log | AD17: All expected messages matched verbatim, including the drift finding line and the write summary. --check confirmed strictly read-only (real repo untouched). Declared Cursor working-memory divergences were not flagged as drift on the clean pass.
A18: RUN-017 | B18: TC-034 | C18: 2026-08-03 | D18: Claude Fable 5 (scripted execution) | E18: monorepo @ 3a02537 | F18: 3a02537 | G18: Cross-stack | H18: n/a (edition workspace) | I18: Cross-tool | J18: n/a — scripted run (no AI client) | K18: n/a | L18: Not Applicable | M18: Small | N18: Clean checkout at 3a02537; mutating steps ran in a temp copy | O18: Pass | P18: Clean runs in the real repo from all three editions (Laravel, Symfony, PHP Core): 'context.py parity' printed 'Mirror parity passed (.agents canonical).' and 'parity --cross-edition' printed 'Cross-edition core parity passed.', all exit 0; '--skills-only' printed 'Skill mirror parity passed (.agents canonical).'. Drift injection ran in a temp clone: appending '# drift' to Symfony/memory-bank/scripts/context_retrieval.py made 'parity --cross-edition' run FROM Laravel report 'Cross-edition core drift (1 finding(s)):' with the exact line 'memory-bank/scripts/context_retrieval.py: content differs (Laravel, PHP Core, Symfony)', exit 1 — drift in a sibling fails the check from another edition and names all affected editions. The --json variant emitted {"valid": false, "skipped": false, "drift": [...]} which parsed cleanly through python3 -m json.tool. Standalone deployment simulation (Laravel copied out with no siblings) printed 'Cross-edition parity skipped: standalone edition (no monorepo siblings found).' and exited 0. Copy restored clean. | Q18: standalone/Laravel edition copy (temp copy) | R18: Symfony/memory-bank/scripts/context_retrieval.py (temp copy, restored) | S18: None | T18: 11 | U18: 11 | V18: 0 | W18: Not Applicable | X18: 0 | Y18: 0 | Z18: 0 | AB18: Accelerator-TestEvidence/TC-034.log | AD18: Every expected message matched verbatim including the JSON schema and the standalone skip path. Parity confirmed read-only: real repo git status empty after all clean runs.
A19: RUN-018 | B19: TC-035 | C19: 2026-08-03 | D19: Claude Fable 5 (scripted execution) | E19: monorepo @ 3a02537 | F19: 3a02537 | G19: Cross-stack | H19: n/a (edition workspace) | I19: Cross-tool | J19: n/a — scripted run (no AI client) | K19: n/a | L19: Not Applicable | M19: Small | N19: Clean checkout at 3a02537; mutating steps ran in a temp copy | O19: Pass | P19: Report mode in the real repo printed the per-edition byte/token table (Laravel 44 skills, Symfony 47, PHP Core 35, Infrastructure-Creator 23; monorepo total 117345 B) and exited 0. '--check' printed exactly 16 'ok' lines (4 editions x 4 categories, e.g. 'ok PHP Core.agents_md_bytes: 12408 <= 12796') then 'All startup context budgets within ceilings.', exit 0; real repo untouched. Injection in a temp clone: appending 2000 bytes to 'PHP Core/AGENTS.md' produced 'FAIL PHP Core.agents_md_bytes: 14408 > ceiling 12796' plus the exact remediation text about trimming or raising the ceiling in scripts/token_budget.json in the same change, exit 1. Substituted token_budget.json checks (in copy): an unknown edition inside the 'editions' map produced 'FAIL token_budget.json lists unknown edition(s): ['NoSuchEdition']', exit 1; removing Symfony produced 'FAIL Symfony: no ceilings in token_budget.json', exit 1 — the gate cannot silently skip an edition. Copy restored clean after each mutation. | Q19: None | R19: PHP Core/AGENTS.md, scripts/token_budget.json (temp copy, restored) | S19: None | T19: 7 | U19: 7 | V19: 0 | W19: Not Applicable | X19: 0 | Y19: 1 | Z19: 0 | AB19: Accelerator-TestEvidence/TC-035.log | AD19: One retry was a test-harness mistake, not a product issue: my first unknown-edition probe added the key at the JSON top level instead of inside the 'editions' map, so the gate correctly ignored it; the corrected mutation confirmed both FAIL paths. Core steps passed on the first attempt.
A20: RUN-019 | B20: TC-036 | C20: 2026-08-03 | D20: Claude Fable 5 (scripted execution) | E20: monorepo @ 3a02537 | F20: 3a02537 | G20: Cross-stack | H20: n/a (edition workspace) | I20: Cross-tool | J20: n/a — scripted run (no AI client) | K20: n/a | L20: Not Applicable | M20: Small | N20: Clean checkout at 3a02537; mutating steps ran in a temp copy | O20: Pass | P20: Ran every command docs/CI.md lists, from the real repo root (all steps are read-only). tests: all 7 unittest suites (Laravel/Symfony/PHP Core memory-bank + project-brain, Infrastructure-Creator) ended OK with 0 failures/errors. parity: all three editions printed 'Mirror parity passed (.agents canonical).' and 'Cross-edition core parity passed.'. mirrors: 'Mirror check passed for: Laravel, Symfony, PHP Core, Infrastructure-Creator'. lint: bash -n silent over 64 tracked .sh files; shellcheck 0.11.0 -S error silent over the same set; all 82 tracked .json files parsed via python3 -m json.tool; budget gate printed 'All startup context budgets within ceilings.'. core-changelog: 'shared-core files changed and the root CHANGELOG.md was updated.' exit 0 on the current branch (merge base with origin/main resolvable), and the explicit unresolvable ref form degraded to a skip with exit 0. links: 'All relative markdown links resolve. No broken links found.'. Workflow cross-check: .github/workflows/ci.yml contains the same run: lines for jobs tests/parity/mirrors/lint/core-changelog/links. git status --porcelain was empty and byte-identical before and after the full run. | Q20: None | R20: None | S20: None | T20: 17 | U20: 17 | V20: 0 | W20: bash -n clean (64 .sh); shellcheck 0.11.0 -S error clean; 82 .json valid | X20: 0 | Y20: 0 | Z20: 0 | AB20: Accelerator-TestEvidence/TC-036.log | AD20: Environment note: shellcheck is NOT installed system-wide on this machine ('which shellcheck' fails); a shellcheck 0.11.0 binary from a scratchpad virtualenv (scvenv, left by an earlier QA session) was put on PATH — no package installation, no sudo, no network. Without it only the shellcheck step would fail (command not found), exactly matching the documented 'fails only that one step' expectation. All other requirements are stdlib-only as documented.
A21: RUN-020 | B21: TC-039 | C21: 2026-08-03 | D21: Claude Fable 5 (scripted execution) | E21: 1.2.1 | F21: 3a02537 | G21: PHP Core | H21: n/a (edition workspace) | I21: Cross-tool | J21: n/a — scripted run (no AI client) | K21: n/a | L21: Not Applicable | M21: Small | N21: Clean checkout at 3a02537; mutating steps ran in a temp copy | O21: Pass | P21: Ran all 7 edition Python infrastructure suites in the real repo. PHP Core: memory-bank suite 'Ran 132 tests ... OK' (19.4s), project-brain suite 'Ran 124 tests ... OK' (22.6s). Laravel: 132 OK (18.7s) and 124 OK (22.5s). Symfony: 132 OK (20.1s) and 124 OK (20.0s) — counts identical across editions, consistent with the byte-identical Python core. Infrastructure-Creator suite: 'Ran 21 tests ... OK' (0.5s). Parity cross-check from PHP Core passed both modes, exit 0. Total: 789 tests, 0 failures, 0 errors, 0 unexpected skips. Post-run git status --porcelain empty; the list of __pycache__ directories was byte-identical before and after (no new stray files). | Q21: None | R21: None | S21: None | T21: 789 | U21: 789 | V21: 0 | W21: Not Applicable | X21: 0 | Y21: 0 | Z21: 0 | AB21: Accelerator-TestEvidence/TC-039.log | AD21: Exact expected counts (132 memory-bank + 124 project-brain) reproduced in each of the three editions; the 7th suite (Infrastructure-Creator, 21 tests) also green. Suites left no working-tree residue at all — not even new __pycache__ directories.
A22: RUN-021 | B22: TC-041 | C22: 2026-08-03 | D22: Claude Fable 5 (scripted execution) | E22: 1.4.0 | F22: 3a02537 | G22: Infrastructure-Creator | H22: n/a (edition workspace) | I22: Cross-tool | J22: n/a — scripted run (no AI client) | K22: n/a | L22: Not Applicable | M22: Small | N22: Clean checkout at 3a02537; mutating steps ran in a temp copy | O22: Pass | P22: The case's manifest verification one-liner ran against the full-mode target whose manifest was written with the exact recipe from infra-generate SKILL.md: mismatches [], runtime-state leaks [], version 1.4.0 / task TASK-1 / mode full; manifest_version 1, generator 'Infrastructure-Creator', profile tasks/TASK-1/infra-scan-project-profile.md; no 'decisions' map on the fresh generation; the manifest does not track itself; AGENTS.md first line is the matching stamp; VERSION file equals generator_version (true); 49 files tracked, all sha256 recomputed clean. Precondition VERSION=1.4.0 matches the case exactly. | Q22: None (ran against the existing exec-ic/fake-php-app temp copy) | R22: None | S22: None | T22: 5 | U22: 5 | V22: 0 | W22: Not Applicable | X22: 0 | Y22: 0 | Z22: 0 | AB22: Accelerator-TestEvidence/TC-041.log | AD22: Execution_type Automated and fully satisfied. Target was hand-assembled (Case-3 agent run not available), but the manifest under test was produced by the exact shipped recipe, which is what the case verifies. Version came solely from the VERSION file, never hardcoded.
A23: RUN-022 | B23: TC-042 | C23: 2026-08-03 | D23: Claude Fable 5 (scripted execution) | E23: 1.4.0 | F23: 3a02537 | G23: Infrastructure-Creator | H23: n/a (edition workspace) | I23: Cross-tool | J23: n/a — scripted run (no AI client) | K23: n/a | L23: Not Applicable | M23: Small | N23: Clean checkout at 3a02537; mutating steps ran in a temp copy | O23: Pass | P23: Baseline validator exit 0. Injected the three sabotages from the case (closing '---' removed from coding/SKILL.md frontmatter; 'ghost-skill' added to testing/SKILL.md related:; .claude/hooks/ghost-hook.sh wired in settings.json plus chmod -x bash-validator.sh). Validator exited 1 with 9 findings covering every injected defect: missing name/description in frontmatter for coding/SKILL.md, unresolved 'ghost-skill' reference, 'wired hook does not exist: .claude/hooks/ghost-hook.sh', bash-validator.sh not executable (both the hooks check and the wiring check), plus expected sha256-stale findings for the three edited files. Grep thresholds met: 'ghost' 2 (>=2), 'frontmatter' 2 (>=1), 'bash-validator.sh' 2 (>=1). Restoring the snapshot and chmod +x returned exit 0. | Q23: exec-ic/fake-php-app.snapshot/ (temp copy, scratchpad only) | R23: None | S23: None | T23: 6 | U23: 6 | V23: 0 | W23: Not Applicable | X23: 0 | Y23: 0 | Z23: 0 | AB23: Accelerator-TestEvidence/TC-042.log | AD23: The validator itself modified nothing (restore came from the snapshot; only chmod +x was needed for the exec-bit finding, matching the 'auto-fixable, no manifest refresh' classification). The bootstrap-verifier skill-layer escalation flow is LLM-driven and was not exercised, but the case's whole expected_verification block passed.
A24: RUN-023 | B24: TC-043 | C24: 2026-08-03 | D24: Claude Fable 5 (scripted execution) | E24: monorepo @ 3a02537 | F24: 3a02537 | G24: Cross-stack | H24: n/a (edition workspace) | I24: Cross-tool | J24: n/a — scripted run (no AI client) | K24: n/a | L24: Not Applicable | M24: Small | N24: Clean checkout at 3a02537; mutating steps ran in a temp copy | O24: Pass | P24: Clean run in the real repo printed 'All relative markdown links resolve. No broken links found.', exit 0. The allowlist scripts/check_links_ignore.txt currently carries one documented pattern ('*/Task/*', client-owned specification material with intentionally absent companion dirs) plus comments. Mutations ran in a temp clone: appending '[missing](does-not-exist.md)' to docs/README.md produced exactly one finding 'docs/README.md:78: broken link (does-not-exist.md) -> docs/does-not-exist.md', exit 1. Negative control: a broken link added only inside a fenced code block ('[fenced](also-missing.md)') was NOT reported — output still showed only the first finding and grep counted 0 occurrences of 'also-missing.md'. Adding the pattern 'does-not-exist.md' to check_links_ignore.txt suppressed the finding (exit 0), confirming fnmatch allowlist support. After restore the copy passed clean with exit 0 and an empty git status. | Q24: None | R24: docs/README.md, scripts/check_links_ignore.txt (temp copy, restored) | S24: None | T24: 6 | U24: 6 | V24: 0 | W24: Not Applicable | X24: 0 | Y24: 0 | Z24: 0 | AB24: Accelerator-TestEvidence/TC-043.log | AD24: Two cosmetic deviations from the case text, neither a functional defect: (1) the finding format is '<file>:<line>: broken link (<target>) -> <resolved path>' rather than the case's '<file>:<line>: [missing](target)' — same information, and the case's own grep-based verification passes; (2) the allowlist is not empty as the precondition suggested — it holds one deliberate, well-commented Task/ exemption (owner decision), which the case itself frames as policy rather than a bug.
A25: RUN-024 | B25: TC-044 | C25: 2026-08-03 | D25: Claude Fable 5 (scripted execution) | E25: monorepo @ 3a02537 | F25: 3a02537 | G25: Cross-stack | H25: n/a (edition workspace) | I25: Cross-tool | J25: n/a — scripted run (no AI client) | K25: n/a | L25: Not Applicable | M25: Small | N25: Clean checkout at 3a02537; mutating steps ran in a temp copy | O25: Pass | P25: All scenarios ran in a temp git clone with fictitious branches/commits. Because the clone's origin/main predates scripts/check_core_changelog.sh, the fail/pass scenarios used the documented explicit-BASE_REF form against a fictitious base branch 'qa-base' at HEAD. Baseline: 'no changes against qa-base (...)', exit 0. Uncommitted shared-core touch (Laravel/.claude/hooks/bash-validator.sh): stderr 'core-changelog: this diff touches shared-core files but not the root CHANGELOG.md:' listing ' - Laravel/.claude/hooks/bash-validator.sh' plus the exact remediation text, exit 1. After adding a root CHANGELOG.md entry: 'shared-core files changed and the root CHANGELOG.md was updated.', exit 0. Committed variants behaved identically (fictitious commit with both files -> pass; commit touching core only -> fail), proving the merge-base diff covers committed and working-tree changes. Negative scope: changing only Infrastructure-Creator/README.md -> 'no shared-core files touched; no root CHANGELOG.md entry required.', exit 0. Unresolvable explicit ref ('some-branch') -> 'cannot resolve a merge base ... skipping.', exit 0. Degradation clone (origin removed, no local main) -> same degraded skip, exit 0. Default run on the copy's merge branch vs origin/main passed (its committed diff updates both core and CHANGELOG.md). Copy fully restored, scratch branches deleted. | Q25: qa-base/scratch/scratch2/scratch3 branches and one degradation clone (temp copy) | R25: Laravel/.claude/hooks/bash-validator.sh, CHANGELOG.md, Infrastructure-Creator/README.md (temp copy, restored) | S25: None | T25: 9 | U25: 9 | V25: 0 | W25: bash -n clean (covered by TC-036 over all tracked .sh) | X25: 0 | Y25: 1 | Z25: 0 | AB25: Accelerator-TestEvidence/TC-044.log | AD25: Retry was environmental, not a product failure: checking out a scratch branch off origin/main removed the script itself (it does not exist on that older main), so the first attempt hit 'No such file or directory'. Re-running with the documented explicit BASE_REF form against a fictitious base at HEAD exercised every scenario. All expected messages matched verbatim, including the degraded-skip wording. FINAL SAFETY CONFIRMATION for the whole zone: git -C <repo> status --porcelain is EMPTY after all seven cases — the real working tree was never mutated; every mutation happened in temp clones under the scratchpad exec-crossstack/ directory.
A26: RUN-025 | B26: TC-048 | C26: 2026-08-03 | D26: Claude Fable 5 (scripted execution) | E26: 1.4.0 | F26: 3a02537 | G26: Infrastructure-Creator | H26: n/a (edition workspace) | I26: Claude Code | J26: n/a — scripted run (no AI client) | K26: n/a | L26: Not Applicable | M26: Small | N26: Clean checkout at 3a02537; mutating steps ran in a temp copy | O26: Blocked | P26: Not executable scriptally: profile-synthesizer consumes seven LLM-scanner findings files plus clarifying-interview-answers.md and authors the profile with per-fact confidence tagging - all agent work. Static preconditions verified: VERSION is 1.4.0 (matches the case), the skill and its references/project-profile-schema.md exist, and tasks/ contains no TASK-1 findings to synthesize from (only README.md), so even the input state for a standalone re-invocation is absent. | Q26: None | R26: None | S26: None | T26: 0 | U26: 0 | V26: 0 | W26: Not Applicable | X26: 0 | Y26: 0 | Z26: 0 | AA26: Requires interactive AI client run (LLM synthesis of the profile from scanner findings); no findings inputs exist in tasks/ either | AB26: Accelerator-TestEvidence/TC-048.log
A27: RUN-026 | B27: TC-049 | C27: 2026-08-03 | D27: Claude Fable 5 (scripted execution) | E27: 1.4.3 | F27: 3a02537 | G27: Laravel | H27: n/a (edition workspace) | I27: Cross-tool | J27: n/a — scripted run (no AI client) | K27: n/a | L27: Not Applicable | M27: Small | N27: Clean checkout at 3a02537; mutating steps ran in a temp copy | O27: Pass | P27: Full unittest class FileNamingValidatorTest OK (5 tests across .claude/.cursor/.codex mirrors). Manual against the .claude mirror: tasks/bad-file.md, tasks/loose-dir/0-unprefixed-note.md, tasks/TASK-001/0-unprefixed-note.md, specs/0-unprefixed-spec.md, memory-bank/chunks/unprefixed-note.md all exited 2 with the exact documented BLOCKED stderr messages plus the 'See AGENTS.md' line and empty stdout. apply_patch payload with '*** Add File: tasks/bad-file.md' blocked (exit 2); '*** Add File: tasks/TASK-003/coder-report.md' passed (exit 0). All six allowed paths (tasks/README.md, specs/MANIFEST.md, memory-bank/chunks/MEM-0001-first-note.md, docs/free-form-notes.md, src/Example.php, tasks/TASK-001/coder-notes.md) exited 0 silently. Escaped file_path inside a content string was ignored (exit 0), and a Read of a badly named file passed (exit 0). Hook created/renamed/deleted nothing. | Q27: None | R27: None | S27: None | T27: 19 | U27: 19 | V27: 0 | W27: bash -n clean | X27: 0 | Y27: 0 | Z27: 0 | AB27: Accelerator-TestEvidence/TC-049.log | AD27: Block messages are specific per rule (task dir shape, skill-prefix rule, MEM slug rule), which is better than a generic error.
A28: RUN-027 | B28: TC-050 | C28: 2026-08-03 | D28: Claude Fable 5 (scripted execution) | E28: 1.4.3 | F28: 3a02537 | G28: Laravel | H28: n/a (edition workspace) | I28: Claude Code | J28: n/a — scripted run (no AI client) | K28: n/a | L28: Not Applicable | M28: Small | N28: Clean checkout at 3a02537; mutating steps ran in a temp copy | O28: Pass | P28: Unit test test_warn_and_block_thresholds OK. Manual loop of 10 identical Edit payloads from a scratch git repo against Laravel/.claude/hooks/loop-detection.sh produced exits 0,0,0,0,0,0,1,1,1,2 exactly. Runs 7-9 printed the stdout warning 'WARNING: File '/work/app/Example.php' edited N times this session.' with the /debugger suggestion and empty stderr; run 10 exited 2 with the stderr 'BLOCKED: File ... edited 10 times this session.' repeated-edit-loop message and empty stdout. Counter state: exactly one file /tmp/claude-loop-detection-<cksum>/<md5> containing '10'. An Edit payload without file_path exited 0 and created no counter directory. | Q28: scratchpad/exec-hooks/scratch-a (temp scratch repo); /tmp counters | R28: None | S28: None | T28: 13 | U28: 13 | V28: 0 | W28: bash -n clean | X28: 0 | Y28: 0 | Z28: 0 | AB28: Accelerator-TestEvidence/TC-050.log | AD28: Stream separation verified explicitly (warning on stdout, block on stderr) since the case flags a swap as a defect; no swap observed.
A29: RUN-028 | B29: TC-051 | C29: 2026-08-03 | D29: Claude Fable 5 (scripted execution) | E29: 1.4.3 | F29: 3a02537 | G29: Laravel | H29: n/a (edition workspace) | I29: Cross-tool | J29: n/a — scripted run (no AI client) | K29: n/a | L29: Not Applicable | M29: Small | N29: Clean checkout at 3a02537; mutating steps ran in a temp copy | O29: Pass | P29: Unit tests test_counters_namespaced_per_repository and test_session_start_resets_only_own_repo_counters OK. Manual with two scratch repos: distinct keys 3362089479 (repo-a) and 3129882068 (repo-b). Nine edits of the same absolute file path in repo-a set its counter to 9; the first edit of the identical path from repo-b exited 0 with empty streams and its own counter at 1. Repo-a's 10th edit blocked (exit 2). Running Laravel/.claude/hooks/local-context.sh with cwd=repo-a exited 0 and left repo-a's namespace with 0 files while repo-b's counter file survived (1 file). The next edit in repo-a exited 0 with a fresh count of 1. | Q29: scratchpad/exec-hooks/repo-a and repo-b (temp scratch repos); /tmp counters | R29: None | S29: None | T29: 9 | U29: 9 | V29: 0 | W29: bash -n clean | X29: 0 | Y29: 0 | Z29: 0 | AB29: Accelerator-TestEvidence/TC-051.log | AD29: Cross-repo isolation and reset scoping behave exactly as specified; no cross-repo interference observed.
A30: RUN-029 | B30: TC-052 | C30: 2026-08-03 | D30: Claude Fable 5 (scripted execution) | E30: 1.4.3 | F30: 3a02537 | G30: Laravel | H30: n/a (edition workspace) | I30: Codex | J30: n/a — scripted run (no AI client) | K30: n/a | L30: Not Applicable | M30: Small | N30: Clean checkout at 3a02537; mutating steps ran in a temp copy | O30: Pass | P30: Unit tests test_read_only_tool_payload_with_file_path_does_not_count, test_payload_without_command_key_passes_quietly, test_non_edit_tool_payloads_ignored OK. Manual from a scratch repo: 12 consecutive Read payloads (with file_path) to Laravel/.codex/hooks/loop-detection.sh all exited 0 with empty stdout and stderr and no /tmp/codex-loop-detection-* directory was ever created. The same Read payload to .codex/hooks/bash-validator.sh and .codex/hooks/file-naming-validator.sh exited 0 with both streams empty. An Edit-shaped payload with absent tool_name still counted (counter file created with value 1, exit 0), confirming fail-open for hosts that send no tool_name while not extending to reads. Wiring preconditions (no matcher in .codex/hooks.json, hooks=true in config.toml) confirmed under TC-005. | Q30: scratchpad/exec-hooks/scratch-codex (temp scratch repo); /tmp counters | R30: None | S30: None | T30: 18 | U30: 18 | V30: 0 | W30: bash -n clean | X30: 0 | Y30: 0 | Z30: 0 | AB30: Accelerator-TestEvidence/TC-052.log | AD30: The previously documented regression (Read payloads advancing the counter) is definitively absent.
A31: RUN-030 | B31: TC-053 | C31: 2026-08-03 | D31: Claude Fable 5 (scripted execution) | E31: 1.4.3 | F31: 3a02537 | G31: Laravel | H31: n/a (edition workspace) | I31: Claude Code | J31: n/a — scripted run (no AI client) | K31: n/a | L31: Governed | M31: Small | N31: Clean checkout at 3a02537; mutating steps ran in a temp copy | O31: Pass | P31: Representative /coder triple verified: command frontmatter 'spawns: coder-agent' with Task-tool spawn (subagent_type coder, $ARGUMENTS as prompt) and flow-next: code-reviewer / flow-alternatives [test-generator]; coder-agent.md declares 'invokes: coder', first step 'Use the Skill tool to invoke coder skill', and constraints 'ONLY execute the coder skill' / 'DO NOT chain to other skills automatically' / 'DO NOT make workflow decisions'; skills/coder/SKILL.md exists. Static sweep over all 42 command files (40 declare spawns:) reported zero BROKEN links — every command.md -> <agent>.md -> skills/<skill>/SKILL.md triple closes, including security-reviewer and git-worktrees -> using-git-worktrees-agent -> using-git-worktrees. Mirror parity: context.py parity --json exited 0 with {"valid": true, "canonical_edition": ".agents", "drift": [], "mirror_drift": []}. | Q31: None | R31: None | S31: None | T31: 44 | U31: 44 | V31: 0 | W31: Not Applicable | X31: 0 | Y31: 0 | Z31: 0 | AB31: Accelerator-TestEvidence/TC-053.log | AD31: Live transcript portion (exactly one Task spawn and one Skill invocation at runtime) requires an interactive session and was not executed; the static contract the case defines as the sweep is fully closed, so Pass with that caveat.
A32: RUN-031 | B32: TC-054 | C32: 2026-08-03 | D32: Claude Fable 5 (scripted execution) | E32: 1.4.3 | F32: 3a02537 | G32: Laravel | H32: n/a (edition workspace) | I32: Claude Code | J32: n/a — scripted run (no AI client) | K32: n/a | L32: Not Applicable | M32: Small | N32: Clean checkout at 3a02537; mutating steps ran in a temp copy | O32: Pass | P32: Structural execution per assignment: command file git-worktrees.md declares spawns: using-git-worktrees-agent, flow-next: coder, flow-alternatives [coder-frontend]; agent declares invokes: using-git-worktrees with constraints 'ONLY execute the using-git-worktrees skill', 'DO NOT chain', 'STOP after skill completion'. SKILL.md contains every Safe Workflow element the case requires: 'git worktree add ../project-feature feature/...', composer install, .env copy/symlink 'never copy it automatically without confirming secrets/DB credentials', 'adjust DB_DATABASE per worktree', key:generate only if APP_KEY missing, 'php artisan migrate ... against the intended local database only', 'php artisan test' before returning to main, intent-prefixed branch naming (feature/fix/refactor/chore), 'Never commit vendor/, .env, secrets, or build artifacts; verify with git status', and the required final output (worktree path, branch, commands, Context Summary, next command). Hook-layer continuity simulated: a 'git push --force' payload still blocks with exit 2 via bash-validator. | Q32: None | R32: None | S32: None | T32: 14 | U32: 14 | V32: 0 | W32: Not Applicable | X32: 0 | Y32: 0 | Z32: 0 | AB32: Accelerator-TestEvidence/TC-054.log | AD32: Behavioral run (actual worktree creation, .env confirmation step in transcript, migrations) requires a live AI session and a Laravel host project; per assignment this case was executed as a structural file check, which fully matched — Pass with that caveat.
A33: RUN-032 | B33: TC-055 | C33: 2026-08-03 | D33: Claude Fable 5 (scripted execution) | E33: 1.4.3 | F33: 3a02537 | G33: Laravel | H33: n/a (edition workspace) | I33: Cross-tool | J33: n/a — scripted run (no AI client) | K33: n/a | L33: Not Applicable | M33: Small | N33: Clean checkout at 3a02537; mutating steps ran in a temp copy | O33: Pass | P33: Unit tests test_path_field_honoured_only_by_cursor_and_codex and test_bash_validator_mirrors_are_byte_identical OK. python3 scripts/build_mirrors.py --check from the monorepo root: 'Mirror check passed for: Laravel, Symfony, PHP Core, Infrastructure-Creator', exit 0. context.py parity --json: exit 0, no drift or mirror_drift. Manual bare-'path' Edit payload from a scratch repo: after running it against the .cursor, .claude, and .codex loop-detection mirrors, only /tmp/cursor-loop-detection-<key> and /tmp/codex-loop-detection-<key> existed — the Claude mirror ignored the bare 'path' key and created no counter. bash-validator.sh mirrors confirmed byte-identical via cmp (claude=cursor, claude=codex). State-prefix rewrites confirmed: each mirror references exactly its own /tmp/{claude|cursor|codex}-loop-detection prefix. | Q33: scratchpad/exec-hooks/scratch-55 (temp scratch repo); /tmp counters | R33: None | S33: None | T33: 10 | U33: 10 | V33: 0 | W33: bash -n clean | X33: 0 | Y33: 0 | Z33: 0 | AB33: Accelerator-TestEvidence/TC-055.log | AD33: No cross-tool state bleed possible: prefixes differ per harness and the path-fallback rewrite is present only where the host actually sends 'path'. Final monorepo check after all runs: git status --porcelain empty — working tree untouched.
A34: RUN-033 | B34: TC-056 | C34: 2026-08-03 | D34: Claude Fable 5 (scripted execution) | E34: 1.4.0 | F34: 3a02537 | G34: Infrastructure-Creator | H34: n/a (edition workspace) | I34: Claude Code | J34: n/a — scripted run (no AI client) | K34: n/a | L34: Not Applicable | M34: Small | N34: Clean checkout at 3a02537; mutating steps ran in a temp copy | O34: Blocked | P34: Not executable scriptally: /infra-scan fans out seven scanner agents, stack-researcher and the clarifying-interview - all LLM phases. Static preconditions verified: infra-scan skill and all seven scanner skills present; tasks/.task-counter exists and contains 1, matching the case precondition. | Q34: None | R34: None | S34: None | T34: 0 | U34: 0 | V34: 0 | W34: Not Applicable | X34: 0 | Y34: 0 | Z34: 0 | AA34: Requires interactive AI client run (scanner fan-out, interview, profile checkpoint) | AB34: Accelerator-TestEvidence/TC-056.log
A35: RUN-034 | B35: TC-057 | C35: 2026-08-03 | D35: Claude Fable 5 (scripted execution) | E35: 1.4.0 | F35: 3a02537 | G35: Infrastructure-Creator | H35: n/a (edition workspace) | I35: Claude Code | J35: n/a — scripted run (no AI client) | K35: n/a | L35: Not Applicable | M35: Small | N35: Clean checkout at 3a02537; mutating steps ran in a temp copy | O35: Blocked | P35: Not executable scriptally: stack-adapter performs live ecosystem research and re-authors all 23 skills for the new stack - pure LLM work. Static preconditions verified: stack-adapter skill present; IC ships exactly 23 skills under .claude/skills (the replication count the case asserts); the stack-agnostic assets it would copy verbatim (memory-seed validate.py, chunk.md, validate_generated.py) all exist. | Q35: None | R35: None | S35: None | T35: 0 | U35: 0 | V35: 0 | W35: Not Applicable | X35: 0 | Y35: 0 | Z35: 0 | AA35: Requires interactive AI client run (gated consent question, live research, 23-skill re-authoring, sibling self-verification) | AB35: Accelerator-TestEvidence/TC-057.log | AD35: validate_generated.py deliberately does not pin the generator name in the AGENTS stamp regex, confirming the sibling-reuse design the case depends on.
A36: RUN-035 | B36: TC-058 | C36: 2026-08-03 | D36: Claude Fable 5 (scripted execution) | E36: 1.4.0 | F36: 3a02537 | G36: Infrastructure-Creator | H36: n/a (edition workspace) | I36: Claude Code | J36: n/a — scripted run (no AI client) | K36: n/a | L36: Not Applicable | M36: Small | N36: Clean checkout at 3a02537; mutating steps ran in a temp copy | O36: Blocked | P36: Not executable scriptally: /infra-build chains the full infra-scan + infra-generate LLM pipeline with a checkpoint gate evaluated on scan ambiguity. Static verification only: infra-build SKILL.md present and documents the checkpoint policy (pause only on blocking ambiguity or collision) and the 'Paused for review: [yes/no]' report line the case greps for. Final repo cleanliness confirmed after the whole zone: git status --porcelain empty, HEAD 3a02537 unchanged. | Q36: None | R36: None | S36: None | T36: 0 | U36: 0 | V36: 0 | W36: Not Applicable | X36: 0 | Y36: 0 | Z36: 0 | AA36: Requires interactive AI client run (one-shot scan+generate chain with interview and collision-guard gating) | AB36: Accelerator-TestEvidence/TC-058.log | AD36: Zone-final check: the AI-Infrastructure working tree remained clean throughout all runs (git status --porcelain empty before and after; all mutations confined to scratchpad exec-ic temp copies). Evidence logs stored in the scratchpad evidence/ directory because writing an evidence/ folder into the repo would itself have dirtied the tree.
A37: RUN-036 | B37: TC-059 | C37: 2026-08-03 | D37: Claude Fable 5 (scripted execution) | E37: 1.4.3 | F37: 3a02537 | G37: Laravel | H37: n/a (edition workspace) | I37: Claude Code | J37: n/a — scripted run (no AI client) | K37: n/a | L37: Governed | M37: Small | N37: Clean checkout at 3a02537; mutating steps ran in a temp copy | O37: Pass | P37: In a temp copy of the Laravel edition (git init, baseline commit), created branch feature/PAY-123-checkout-refactor with a modified tracked file and ran context.py turn --flush --json. JSON reported provisioned=true, flushed=true, rebound=null, revision=2. Exactly one Brain task record was minted in project-brain/dynamic/tasks/ with external_id equal to the branch name; the derived goal was 'PAY-123 checkout refactor (auto-provisioned from feature/PAY-123-checkout-refactor)' (prefix stripped, ticket token preserved, provenance suffix present). A handoff with the same UUID appeared in project-brain/control/handoffs/. The consolidated summary landed in auto_checkpoint ('Auto-checkpoint: 1 turn(s)...'), progress stayed empty. Control run on a clean second branch without --flush buffered only (flushed=false, provisioned=false, no new record). validate exited 0. The 3 targeted pytest tests passed (plus 5 subtests). | Q37: project-brain/dynamic/tasks/<uuid>.md, project-brain/control/handoffs/<uuid>.md, memory-bank/local/context.db (temp copy); evidence/TC-059.log | R37: README.md, CHANGELOG.md test deltas (temp copy, reverted) | S37: None | T37: 3 | U37: 3 | V37: 0 | W37: Not Applicable | X37: 0 | Y37: 0 | Z37: 0 | AB37: Accelerator-TestEvidence/TC-059.log | AD37: pytest is absent from system python3; the specified pytest verifications were run via a scratchpad venv (pytest 9.1.1) against the same source tree. Only file paths (never contents) reached the buffer; nothing was written outside project-brain/ and memory-bank/local/.
A38: RUN-037 | B38: TC-060 | C38: 2026-08-03 | D38: Claude Fable 5 (scripted execution) | E38: 1.4.3 | F38: 3a02537 | G38: Laravel | H38: n/a (edition workspace) | I38: Cross-tool | J38: n/a — scripted run (no AI client) | K38: n/a | L38: Governed | M38: Small | N38: Clean checkout at 3a02537; mutating steps ran in a temp copy | O38: Pass | P38: Started governed task feature/manual-progress with --owner tester. First attempt ran update/turn WITHOUT --owner exactly as the case prompt is written and every mutation was refused with 'Owner is not authorized to mutate record: local' (correct per-record owner authorization). Retried with consistent --owner tester: manual update wrote the progress narrative; ten forced flushes each wrote only auto_checkpoint ('Auto-checkpoint: N turn(s) since <ts>, M file(s) touched.') and bumped revisions 3..12. After ten flushes get --json showed the exact manual progress string unchanged and a separate auto_checkpoint field (case assert passed). The handoff Current State leads with the manual progress, with the checkpoint following as 'Since checkpoint:'. The 3 targeted pytest tests passed. Secret-looking --progress (ghp_ token) was rejected without echoing the value ('possible GitHub token detected; working task not stored'). | Q38: task+handoff records (temp copy); evidence/TC-060.log | R38: README.md test deltas (temp copy, reverted) | S38: None | T38: 3 | U38: 3 | V38: 0 | W38: Not Applicable | X38: 0 | Y38: 1 | Z38: 0 | AB38: Accelerator-TestEvidence/TC-060.log | AD38: The retry was caused by the case prompt omitting --owner on the follow-up commands while the precondition starts the task as owner 'tester'; the refusal itself is correct product behavior (owner authorization), not a defect. The summary 'context' view leads with the goal line; the detailed capsule ordering is covered by the passing handoff_and_capsule_lead_with_manual_progress test.
A39: RUN-038 | B39: TC-061 | C39: 2026-08-03 | D39: Claude Fable 5 (scripted execution) | E39: 1.4.3 | F39: 3a02537 | G39: Laravel | H39: n/a (edition workspace) | I39: Cross-tool | J39: n/a — scripted run (no AI client) | K39: n/a | L39: Governed | M39: Small | N39: Clean checkout at 3a02537; mutating steps ran in a temp copy | O39: Partial | P39: Session A: started feature/handoff-demo (--owner sessionA); the case's literal update with --phase implementing was rejected by argparse — the CLI phase vocabulary is understanding/planning/execution/finalization. Retried with --phase execution: handoff file was refreshed as a bounded record (Phase: execution, Objective, Current State 'Export service done', Next Actions 'Add controller test'; no transcript lines, 0 user:/assistant:/stdout: prefixes). Both stores committed. Session B (env -i fresh shell): retrieve returned governed context whose working layer carried goal/progress/next_steps and whose semantic layer carried the task record with identical continuation content, so Session B can continue without replay; however the retrieve output for the case's literal query named the task record path, not the handoff path, and did not print the phase. The handoff IS indexed (kind brain-handoff) and surfaces with its phase for a query that matches it ('handoff invoice export'). validate exited 0; retrieval consumed no revision (record stayed at revision 2). Both targeted pytest tests passed. | Q39: task+handoff records (temp copy); evidence/TC-061.log | R39: None beyond Brain stores (temp copy) | S39: None | T39: 2 | U39: 2 | V39: 0 | W39: Not Applicable | X39: 0 | Y39: 1 | Z39: 0 | AA39: Two literal expectations of the case do not match the implementation: (1) --phase implementing is not a valid CLI choice (valid: understanding/planning/execution/finalization); (2) for the case's query the retrieve output surfaces the task record (same continuation content) rather than naming the handoff path and phase. Functional intent (cross-session continuation via handoff) is met and repo tests pass. | AB39: Accelerator-TestEvidence/TC-061.log | AC39: DEF-005 | AD39: The handoff is a bounded continuation record, sanitized, and validates against its task. The mismatch looks like test-case drift against an evolved phase vocabulary rather than a product regression.
A40: RUN-039 | B40: TC-062 | C40: 2026-08-03 | D40: Claude Fable 5 (scripted execution) | E40: 1.4.3 | F40: 3a02537 | G40: Laravel | H40: n/a (edition workspace) | I40: Cross-tool | J40: n/a — scripted run (no AI client) | K40: n/a | L40: Governed | M40: Small | N40: Clean checkout at 3a02537; mutating steps ran in a temp copy | O40: Pass | P40: brain-create finding (FND-CAS-1) returned UUID at revision 1 with an initial transition entry. First brain-update with --revision 1 succeeded and moved the record to revision 2. Repeating with the now-stale revision 1 was rejected non-zero: 'Stale finding revision: expected 1, current 2'; brain-get confirmed revision 2 and progress 'first update' — the concurrent write was never overwritten and no partial write occurred. --revision 0, -3, and 'abc' were all rejected by the revision_argument parser ('Revision must be a positive integer or auto'). --revision auto then performed a locked CAS successfully. All 4 targeted pytest tests (concurrent CAS single-writer, owner authorization, locked auto-CAS, argument validation) passed. | Q40: finding record (temp copy); evidence/TC-062.log | R40: None outside Brain stores (temp copy) | S40: None | T40: 4 | U40: 4 | V40: 0 | W40: Not Applicable | X40: 0 | Y40: 0 | Z40: 0 | AB40: Accelerator-TestEvidence/TC-062.log | AD40: Error messages never echoed the attempted payload. Append-only transition ledger visible in the record.
A41: RUN-040 | B41: TC-063 | C41: 2026-08-03 | D41: Claude Fable 5 (scripted execution) | E41: 1.4.3 | F41: 3a02537 | G41: Laravel | H41: n/a (edition workspace) | I41: Cross-tool | J41: n/a — scripted run (no AI client) | K41: n/a | L41: Governed | M41: Small | N41: Clean checkout at 3a02537; mutating steps ran in a temp copy | O41: Pass | P41: Created a finding at default authority observed. brain-update --authority verified succeeded, consumed one CAS revision (1->2), appended a ledger entry with actor/reason/from=observed/to=verified/timestamp, and left the status chain untouched (status stayed open). The downgrade attempt exited 1 with the exact shape 'Illegal authority transition: verified -> observed; only observed -> verified is allowed' and the record stayed verified at revision 2 (no revision consumed by the refusal). observed->inferred on a second record was refused identically. brain-create event requires --external-id (retried with it); an authority change on the event was refused with 'Events are immutable; only lifecycle supersession is allowed'. All 5 targeted pytest tests passed (including tampered-ledger rejection by the validator). | Q41: 2 findings + 1 event record (temp copy); evidence/TC-063.log | R41: None outside Brain stores (temp copy) | S41: None | T41: 5 | U41: 5 | V41: 0 | W41: Not Applicable | X41: 0 | Y41: 1 | Z41: 0 | AB41: Accelerator-TestEvidence/TC-063.log | AD41: Retry only for the event-record precondition: brain-create demands --external-id which the case narrative does not mention. No Memory Bank promotion was applied by the authority promotion itself.
A42: RUN-041 | B42: TC-064 | C42: 2026-08-03 | D42: Claude Fable 5 (scripted execution) | E42: 1.4.3 | F42: 3a02537 | G42: Laravel | H42: n/a (edition workspace) | I42: Cross-tool | J42: n/a — scripted run (no AI client) | K42: n/a | L42: Governed | M42: Small | N42: Clean checkout at 3a02537; mutating steps ran in a temp copy | O42: Pass | P42: Created governed task feature/rebind-demo and committed both stores. Deleted memory-bank/local/context.db. First rebind resolved the record by external_id, recreated only the local binding, and reported already_bound=false with revision unchanged at 1; second rebind reported already_bound=true without recreating. Negative control (rebind --record <UUID of feature/handoff-demo>) was refused exit 1: 'Rebind target mismatch: record ... belongs to task id feature/handoff-demo, not feature/rebind-demo'. git diff --exit-code -- project-brain/ was 0 after both rebinds and the record revision stayed 1 (no mutation, no owner check). Alternative path: after deleting the DB again, turn --flush on the bound branch restored the binding implicitly and reported the restored record UUID in the JSON rebound field (flushed=true, provisioned=false, no duplicate record). All 5 targeted pytest tests passed. | Q42: task+handoff for rebind-demo (temp copy); evidence/TC-064.log | R42: memory-bank/local/context.db recreated (gitignored, temp copy) | S42: None | T42: 5 | U42: 5 | V42: 0 | W42: Not Applicable | X42: 0 | Y42: 0 | Z42: 0 | AB42: Accelerator-TestEvidence/TC-064.log | AD42: Rebind is demonstrably a pointer repair: zero governed-record mutation across the whole sequence.
A43: RUN-042 | B43: TC-065 | C43: 2026-08-03 | D43: Claude Fable 5 (scripted execution) | E43: 1.4.3 | F43: 3a02537 | G43: Laravel | H43: n/a (edition workspace) | I43: Claude Code | J43: n/a — scripted run (no AI client) | K43: n/a | L43: Governed | M43: Small | N43: Clean checkout at 3a02537; mutating steps ran in a temp copy | O43: Pass | P43: Created a finding, transitioned it to resolved while authority stayed observed (promotion candidate blocked). With a pending delta, turn --flush wrote memory-bank/local/last-turn-report.json (schema_version 1, timestamp, task_id, flushed, files, promotion_blocked with {record_id, reason 'authority is observed, not verified'}, promotion_failed, compaction_errors, excluded_paths). The next refresh folded it into the capsule as 'Last turn: promotion blocked: authority is observed, not verified; buffer flushed: 1 file(s) this turn' — the blocked reason leads before routine counters, section length 102 chars (<=600 cap). A subsequent buffering-only turn replaced the report (flushed=false, blocked empty) and the following refresh printed no 'Last turn:' section. All 4 targeted pytest tests passed (stale/malformed/missing report tolerance covered there). | Q43: finding record, memory-bank/local/last-turn-report.json (temp copy); evidence/TC-065.log | R43: README.md test deltas (temp copy, reverted) | S43: None | T43: 4 | U43: 4 | V43: 0 | W43: Not Applicable | X43: 0 | Y43: 0 | Z43: 0 | AB43: Accelerator-TestEvidence/TC-065.log | AD43: One expectation-wording nuance: the case's literal assert reason=='authority' fails because the implementation stores the fuller sentence 'authority is observed, not verified' (which starts with 'authority'); the capsule-line substring requirement 'promotion blocked: authority' literally holds and the repo's own tests define this format. Report contains only counters, reasons, and paths — no file contents or secrets.
A44: RUN-043 | B44: TC-066 | C44: 2026-08-03 | D44: Claude Fable 5 (scripted execution) | E44: 1.4.3 | F44: 3a02537 | G44: Laravel | H44: n/a (edition workspace) | I44: Claude Code | J44: n/a — scripted run (no AI client) | K44: n/a | L44: Governed | M44: Small | N44: Clean checkout at 3a02537; mutating steps ran in a temp copy | O44: Pass | P44: Built a 654-word prompt of common filler whose subject (Filament admin panel) appears only in the final sentence, and ran refresh --query ... --ephemeral with a governed task bound. The distiller kept rare terms by document-frequency rank (not position): the capsule's procedural section included .agents/skills/filament/SKILL.md while the filler was dropped. Whole stdout was 436 characters (<=8000 CAPSULE_CHARACTER_LIMIT); layer caps visible (procedural 3 shown, semantic 2, episodic 1 in this index). git status under project-brain/ unchanged; the retrieval manifest (with the distilled query) was written to gitignored memory-bank/local/retrieval-manifests/. All 6 targeted pytest tests across both suites passed (budget-pressure ordering, progress-suffix preservation, ephemeral manifest covered there). Safety probes: retrieve/context with a raw email or transcript-prefixed query are refused ('Task Capsule request contains private or raw data'), but refresh distills the query BEFORE the privacy gate, so the same inputs pass through refresh and the tokenized remnants ('contact customer john doe example com about', 'please fix assistant sure thing') are persisted into the local manifest. | Q44: retrieval manifests in memory-bank/local/ (gitignored, temp copy); evidence/TC-066.log | R44: None tracked | S44: None | T44: 6 | U44: 6 | V44: 0 | W44: Not Applicable | X44: 0 | Y44: 0 | Z44: 0 | AB44: Accelerator-TestEvidence/TC-066.log | AC44: DEF-006 | AD44: Core case (tail-subject survival + budget) passed cleanly. The privacy-gate asymmetry between refresh and retrieve/context is recorded as a Low defect: raw secrets/emails are never persisted verbatim (tokenization strips the matching syntax), and the manifest is machine-local gitignored state, but identifiable name tokens from a private-looking query do reach disk via the refresh path.
A45: RUN-044 | B45: TC-067 | C45: 2026-08-03 | D45: Claude Fable 5 (scripted execution) | E45: 1.4.3 | F45: 3a02537 | G45: Laravel | H45: n/a (edition workspace) | I45: Claude Code | J45: n/a — scripted run (no AI client) | K45: n/a | L45: Governed | M45: Small | N45: Clean checkout at 3a02537; mutating steps ran in a temp copy | O45: Pass | P45: Three attempts were needed to satisfy the promoter's guards, each refusal being correct behavior: (1) a resolved+verified finding with only a title was blocked with 'record carries no content beyond its own title'; (2) a finding citing README.md was blocked with 'cited source changed since the record was written: README.md' because the turn's own delta had touched the cited source; (3) with substantive progress and an untouched cited source, the flush boundary auto-promoted BOTH eligible findings: chunks memory-bank/chunks/MEM-20260803-d2a526d6-payment-retry-policy.md and MEM-20260803-dd20ac66-queue-retry-policy.md (today's UTC date + first 8 hex of each source UUID — distinct, no shared counter; .memory-counter md5 unchanged throughout). Chunk tags include project-brain, promoted, auto-promoted; promotion JSONs in project-brain/control/promotions/ show review_mode 'automatic', reviewer null, outcome promoted. INDEX.md was regenerated and lists the chunks. Turn JSON promoted array listed {record_id, type, memory_id} for both. Negative control: a resolved observed-only finding stayed under promotion_blocked with the authority reason; tasks were never promoted. validate.py exited 0. All 4 targeted pytest tests passed. | Q45: 2 MEM-YYYYMMDD chunks, 2 promotion JSONs, archived finding records (temp copy); evidence/TC-067.log | R45: memory-bank/INDEX.md regenerated (temp copy) | S45: None | T45: 4 | U45: 4 | V45: 0 | W45: Not Applicable | X45: 0 | Y45: 2 | Z45: 0 | AB45: Accelerator-TestEvidence/TC-067.log | AD45: Both intermediate refusals are undocumented-in-the-case but sensible promotion guards (content beyond title; source-fingerprint freshness) and they surfaced transparently in promotion_blocked. brain-create also validates that --source paths exist. Absence of human approval is visible in both stores as specified.
A46: RUN-045 | B46: TC-068 | C46: 2026-08-03 | D46: Claude Fable 5 (scripted execution) | E46: 1.4.3 | F46: 3a02537 | G46: Laravel | H46: n/a (edition workspace) | I46: Cross-tool | J46: n/a — scripted run (no AI client) | K46: n/a | L46: Governed | M46: Small | N46: Clean checkout at 3a02537; mutating steps ran in a temp copy | O46: Pass | P46: With a 3-chunk bank committed clean: run 1 reported changed=false (idempotent, nothing rewritten). After rm memory-bank/INDEX.md, run 2 reconstructed it fully from chunk frontmatter and reported changed=true with chunks=3. Run 3 reported changed=false. git diff --exit-code -- memory-bank/INDEX.md exited 0 after the sequence (no net change). A hand-written preamble line added above the header survived a further regeneration verbatim. Chunk files' md5 aggregate and .memory-counter md5 were unchanged throughout. The targeted pytest test passed. | Q46: evidence/TC-068.log | R46: memory-bank/INDEX.md (deleted and deterministically reconstructed, net-zero diff; temp copy) | S46: None | T46: 1 | U46: 1 | V46: 0 | W46: Not Applicable | X46: 0 | Y46: 0 | Z46: 0 | AB46: Accelerator-TestEvidence/TC-068.log | AD46: INDEX.md was the only write target; no chunk mutated; legacy counter neither read nor written (md5 stable).
A47: RUN-046 | B47: TC-069 | C47: 2026-08-03 | D47: Claude Fable 5 (scripted execution) | E47: 1.4.3 | F47: 3a02537 | G47: Laravel | H47: n/a (edition workspace) | I47: Cross-tool | J47: n/a — scripted run (no AI client) | K47: n/a | L47: Governed | M47: Small | N47: Clean checkout at 3a02537; mutating steps ran in a temp copy | O47: Pass | P47: Created MEM-20260803-1a2b3c4d-payment-retry-rules.md from the shipped template with all REQUIRED_KEYS plus valid_from/valid_to, reindexed, and validated the mixed bank (legacy MEM-0001 + two auto-promoted MEM-YYYYMMDD chunks + the new one): exit 0. --summary printed only status counts ('4 chunks (4 active, 0 needs review)') without chunk contents. Negative controls each failed exit 1 naming the offending file: MEM-123-short.md and MEM-20260803-XYZ-bad.md rejected as unexpected chunk entries; frontmatter id/filename mismatch rejected; an indexed chunk containing an AWS-format access key failed with 'possible AWS access key detected; value intentionally not printed' and the secret value appeared 0 times in output; an unknown extra frontmatter key was rejected ('unexpected metadata keys: made_up_key'). .memory-counter present on disk was ignored. Full memory-bank/tests/test_validate.py passed (18 tests + 3 subtests) and knowledge_past_its_validity_may_not_call_itself_active passed. No chunk was modified, renamed, or deleted by the validator; bank restored to clean passing state. | Q47: 1 valid chunk kept in temp copy; transient negative-control chunks (created and removed); evidence/TC-069.log | R47: memory-bank/INDEX.md reindexed (temp copy) | S47: None | T47: 19 | U47: 19 | V47: 0 | W47: Not Applicable | X47: 0 | Y47: 0 | Z47: 0 | AB47: Accelerator-TestEvidence/TC-069.log | AD47: Two secret-control iterations were needed to isolate the secret check (the first collided with the id-mismatch and missing-from-INDEX checks, which fire first) — validator layering, not a defect. ID_PATTERN accepts both formats exactly as specified.
A48: RUN-047 | B48: TC-070 | C48: 2026-08-03 | D48: Claude Fable 5 (scripted execution) | E48: 1.4.3 | F48: 3a02537 | G48: Laravel | H48: n/a (edition workspace) | I48: Cross-tool | J48: n/a — scripted run (no AI client) | K48: n/a | L48: Governed | M48: Small | N48: Clean checkout at 3a02537; mutating steps ran in a temp copy | O48: Pass | P48: Pair A: two findings with identical titles/progress about 'Zebrastripe pagination cache', one observed and one promoted to verified. Pair B: two same-authority findings about 'Quokkafeed webhook signing', one aged to updated_at -70 days (simulated in the temp copy only), one current. After reindexing, retrieve 'zebrastripe pagination' ranked the verified record's path before the observed twin (indices 0 vs 1 in selected). retrieve 'quokkafeed webhook' ranked the fresh record first while the stale one still appeared (floored, not hidden). Porter stemming confirmed: query 'review' matched 'PR Reviewer'. Ordering visible in the JSON result sections. All 4 targeted pytest tests passed (including focused-document survival). | Q48: 4 finding records (temp copy); evidence/TC-070.log | R48: one record's updated_at aged for the stale simulation (temp copy only) | S48: None | T48: 4 | U48: 4 | V48: 0 | W48: Not Applicable | X48: 0 | Y48: 0 | Z48: 0 | AB48: Accelerator-TestEvidence/TC-070.log | AD48: Authority multiplier (verified 1.0 vs observed 0.85) and 30-day-half-life recency decay produced exactly the specified orderings at equal lexical fit. Privacy filtering over ranking is asserted by the suite (private/restricted records never enter the FTS index).
A49: RUN-048 | B49: TC-071 | C49: 2026-08-03 | D49: Claude Fable 5 (scripted execution) | E49: 1.4.3 | F49: 3a02537 | G49: Laravel | H49: n/a (edition workspace) | I49: Cursor | J49: n/a — scripted run (no AI client) | K49: n/a | L49: Governed | M49: Small | N49: Clean checkout at 3a02537; mutating steps ran in a temp copy | O49: Pass | P49: Confirmed .cursor/hooks/ ships no working-memory-read.sh (read path served by the write hook, as designed). Removed .cursor/rules/working-memory.mdc, created a pending delta, and ran bash .cursor/hooks/working-memory-write.sh: exit 0. The hook ran the turn checkpoint then rendered .cursor/rules/working-memory.mdc with frontmatter 'description: Working memory - Task Capsule as of end of previous turn' and 'alwaysApply: true'; the body states 'Task Capsule as of end of previous turn (task: feature/manual-progress, rendered: <UTC timestamp>)' and 'Retrieved context is not authoritative - verify the source.'. git check-ignore confirms the file is ignored local state. With CONTEXT_HOOK_BUDGET=0.001 forcing a render timeout, the hook still exited 0 and the previous rule was left byte-identical (md5 match). memory-bank/tests/test_hooks.py fully passed (26 tests + 112 subtests) and context.py parity exited 0 ('Mirror parity passed (.agents canonical)'). | Q49: .cursor/rules/working-memory.mdc (gitignored, temp copy); evidence/TC-071.log | R49: spec-desc.md test delta (temp copy, reverted) | S49: None | T49: 26 | U49: 26 | V49: 0 | W49: Not Applicable | X49: 0 | Y49: 0 | Z49: 0 | AB49: Accelerator-TestEvidence/TC-071.log | AD49: Executed as a real CLI invocation of the Cursor Stop hook in the temp copy (case is labeled Manual but is fully scriptable). No writes outside .cursor/rules/ and memory-bank/local/; nothing committed.
A50: RUN-049 | B50: TC-072 | C50: 2026-08-03 | D50: Claude Fable 5 (scripted execution) | E50: 1.4.3 | F50: 3a02537 | G50: Laravel | H50: n/a (edition workspace) | I50: Claude Code | J50: n/a — scripted run (no AI client) | K50: n/a | L50: Governed | M50: Small | N50: Clean checkout at 3a02537; mutating steps ran in a temp copy | O50: Partial | P50: The conversational halves of /checkpoint and /memory require an interactive AI client, which this environment lacks; verified everything mechanically checkable instead. Command files exist: .claude/commands/checkpoint.md states verbatim that the command accepts no arguments and stops if $ARGUMENTS is non-empty; .claude/skills/checkpoint/SKILL.md prescribes the git rev-parse authority gate, reading runtime.json, and in governed mode reporting 'working: skipped' without deriving a branch task or mutating SQLite, and 'MUST NOT create a second task authority'. .claude/skills/memory/SKILL.md prescribes treating Project Brain as the only task authority, running context.py validate, refresh --json (the same command the request hook runs), reporting layers exactly as returned, status --json, and 'MUST NOT pass --query to refresh'. Ran the underlying CLI contract: validate exit 0; refresh --json reported procedural/semantic/episodic all 'updated'; status --json showed mode 'governed', authority 'project-brain', layers {procedural 90, semantic 23, episodic 1}; tracked files unchanged before vs after (md5 of git status --porcelain identical). working was 1, reflecting the governed tasks legitimately created by earlier cases in this shared temp copy, not a task invented by these commands. | Q50: evidence/TC-072.log | R50: None tracked | S50: None | T50: 3 | U50: 3 | V50: 0 | W50: Not Applicable | X50: 0 | Y50: 0 | Z50: 0 | AA50: In-agent execution of /checkpoint and /checkpoint some-argument and /memory (behaviors 1-3 as conversational flows) requires an interactive AI coding session that this runner cannot drive; only the command/skill prescriptions and the underlying CLI contract (validate/refresh/status, governed authority, no tracked-file mutation) were verified. | AB50: Accelerator-TestEvidence/TC-072.log | AD50: Nothing in the exercised layer completed tasks, promoted memory, or edited Git-tracked files. Final zone confirmation: git -C {repository} status --porcelain is EMPTY after all 14 cases (HEAD 3a02537 untouched); all mutations happened in the scratchpad temp copy exec-brain/ with its own git history, evidence logs in scratchpad/evidence/TC-0NN.log.
A51: RUN-050 | B51: TC-006 | C51: 2026-08-03 | D51: Claude Fable 5 (live AI session) | E51: 1.3.1 | F51: 3a02537 | G51: Symfony | H51: Symfony 6.4.42, PHP 8.5.8 | I51: Claude Code | J51: Claude Agent SDK (workflow subagent) | K51: claude-fable-5 | L51: Governed | M51: Medium | N51: Isolated copy of bauherrenmappe @ 627d11f + accelerator install commit; client working tree untouched | O51: Partial | P51: Executed the full post-install shared context activation sequence from the QA copy root (Symfony 6.4 project, accelerator install commit 8d6a38b). (1) FTS5 probe printed "SQLite FTS5 available" (exit 0). (2) memory-bank/scripts/validate.py FAILED with exit 1: "memory-bank/README.md: required file is missing". Root cause verified via git ls-tree: the install commit never included memory-bank/README.md, while the canonical Symfony edition (AI-Infrastructure/Symfony/memory-bank/) ships it — incomplete install manifest, not environment. (3) project-brain/scripts/validate.py --root . passed (exit 0), and the equivalent CLI path context.py validate printed "Project Brain validation passed." (4) context.py index built the local index: "Context index: 99 documents (3 removed, 0 reused)" (exit 0, no FTS5 error); memory-bank/local/context.db exists and git check-ignore confirms it is ignored (.gitignore:52 memory-bank/local/). (5) runtime.json declares framework=symfony, mode=governed, provider=sqlite-fts5, canonical_edition=.agents (grep matches). (6) context.py status --json returned mode=governed, authority=project-brain, documents=99 (>0), working=0, database path — all required fields present. (7) git status --short after activation is identical to the pre-activation snapshot (only pre-existing untracked docs/ plus the evidence log TC-006.log itself); indexing added zero tracked changes (git diff --stat empty). No packages were installed; the memory-bank validation failure was reported honestly, not worked around. | Q51: /tmp/claude-1000/-home-aliaksei-Desktop-AI-Infrastructure/c9fab6de-739d-497c-ac0d-61bda631def9/scratchpad/bwb-run/TC-006.log (evidence log, untracked); /tmp/claude-1000/-home-aliaksei-Desktop-AI-Infrastructure/c9fab6de-739d-497c-ac0d-61bda631def9/scratchpad/tc006_status_before.txt (pre-activation snapshot, outside project); memory-bank/local/context.db refreshed by context.py index (git-ignored, disposable) | R51: None tracked. Only the git-ignored memory-bank/local/context.db was rebuilt by the index command (3 stale documents removed, 99 indexed). | S51: None. git status --short after activation matched the pre-activation snapshot exactly (pre-existing untracked docs/ only, plus the case's own evidence log). Zero tracked changes from indexing. | T51: 8 | U51: 7 | V51: 1 | W51: Not applicable — no code changed; no linters run (activation must not install tooling, per case safety expectations). | X51: 0 | Y51: 0 | Z51: 0 | AA51: memory-bank validation failed because memory-bank/README.md was absent. ROOT CAUSE CORRECTED AFTER THE RUN: the QA install used rsync --exclude README.md, which excludes README.md at EVERY depth, so the omission is a QA-setup artifact, not an accelerator defect (the canonical Symfony edition ships the file). After restoring the file, validate.py passed. | AB51: Accelerator-TestEvidence/TC-006.log | AD51: The QA copy referenced as "undefined" in the tasking was located at the scratchpad path .../scratchpad/bwb-run (confirmed by the install commit "Install Symfony accelerator edition (isolated QA copy)" on top of the real project history). Precondition check passed before indexing: .gitignore line 52 already covered memory-bank/local/. Notable secondary observation (in-scope fact, not acted on): the install commit tracks memory-bank/.memory-counter, which AGENTS.md describes as retired — consistent with the install manifest being out of date. The index reported "3 removed, 0 reused", indicating a pre-existing context.db from install time was refreshed in place. Governed mode is fully functional despite the memory-bank validation failure: retrieval index, Project Brain authority, and status reporting all work; the failure only breaks the documented validate gate and the "read memory-bank/README.md first" policy instruction, which references a file that does not exist in the installed copy. | Post-run correction: the defect the agent attributed to the install manifest was traced to the QA copy procedure (global rsync README exclude); not recorded in the Defects sheet. Re-validation after restore: PASS.
A52: RUN-051 | B52: TC-073 | C52: 2026-08-03 | D52: Claude Fable 5 (live AI session) | E52: 1.3.1 | F52: 3a02537 | G52: Symfony | H52: Symfony 6.4.42, PHP 8.5.8 | I52: Claude Code | J52: Claude Agent SDK (workflow subagent) | K52: claude-fable-5 | L52: Governed | M52: Medium | N52: Isolated copy of bauherrenmappe @ 627d11f + accelerator install commit; client working tree untouched | O52: Pass | P52: The codebase-mapper skill was executed end-to-end in governed mode on the isolated QA copy of the client project. Authority gate passed (repo root resolved, HEAD 8d6a38b0eff81f5a408ff8e07deb0bd0f29b367f recorded, scope defaulted to src). A governed task TC-073 was started via context.py, retrieval was run before mapping decisions, and the codebase was explored read-only one focus area at a time. Six commit-stamped documents were produced under codebase/ (STACK, ARCHITECTURE, STRUCTURE, INTEGRATIONS, CONVENTIONS, TESTING), each with the required frontmatter (description / mapped_commit / mapped_scope). CONCERNS.md was intentionally omitted because no debt/security audit was performed, per the skill's honesty rule. The documents describe the real project: 5 attribute-routed controllers, a GraphQL-first UniteCMS layer (42 resolvers, mutation/query operations, 134 of 242 src files referencing UniteCMS namespaces), the full 2FA/WebAuthn stack (scheb TOTP+backup codes, jbtronics WebAuthn, MFA encryption keyring, trusted devices, voters, firewalls), multi-tenant Mandant enforcement, and German-first translations. context.py refresh reported all six map documents at "0 commit(s) behind", and a subsequent governed retrieval for a WebAuthn query surfaced codebase/ARCHITECTURE.md and codebase/STACK.md as semantic sources. A scripted grounding check verified 252 of 252 repo-relative cited paths exist and 92 of 93 bare filenames resolve in the repo (the one non-match is an explicitly documented absence claim). The governed task was updated and completed as episode 1; Project Brain validation passed. Nothing was staged or committed, matching the skill's prohibition. | Q52: codebase/STACK.md, codebase/ARCHITECTURE.md, codebase/STRUCTURE.md, codebase/INTEGRATIONS.md, codebase/CONVENTIONS.md, codebase/TESTING.md, TC-073.log (all under the QA project root); governed CLI side artifacts: project-brain/dynamic/tasks/732e605f-ed8f-4b77-8a84-68215f074257.md, project-brain/control/handoffs/732e605f-ed8f-4b77-8a84-68215f074257.md, two retrieval manifests under project-brain/control/retrieval-manifests/ | R52: project-brain/indexes/active.json and memory-bank/local/context.db (both mutated by the governed context.py CLI itself, not by hand) | S52: None. All changes are the skill's declared outputs (codebase/ docs), the evidence log, and governed-CLI bookkeeping. No application code, specs, changelogs, or memory chunks were touched; nothing staged or committed per the skill's safety rules. | T52: 4 | U52: 4 | V52: 0 | W52: N/A - documentation-only run, no PHP changed; PHPUnit suite not executed (mapping is read-only and the case does not require it; APP_ENV=test sodium limitation therefore never hit) | X52: 0 | Y52: 0 | Z52: 0 | AB52: Accelerator-TestEvidence/TC-073.log | AD52: The four case verifications all passed: (1) documents exist under codebase/; (2) all six carry mapped_commit equal to git HEAD; (3) grounding check found zero fabricated paths (252/252 repo-relative citations exist; the single unresolved bare name is a deliberate documented-absence claim); (4) context.py refresh explicitly lists all six map documents at 0 commits behind and governed retrieval surfaces them as semantic sources. Two observations outside pass/fail: (a) the orchestrator injected the literal string "undefined" instead of the project path and the test-case file path; the QA copy and bwb_cases.json were located via the TC-006 evidence trail — worth fixing in the harness; (b) the DOD-minimum memory-bank validation still fails on the pre-existing TC-006 defect (memory-bank/README.md missing from the accelerator install commit), which is out of this case's scope and was left untouched. Security.yaml was inspected only through a structural filter that redacted any value on secret/password/key/token lines; .env* files were noted by existence only and never opened; no client source bodies were copied into the map or this record.
A53: RUN-052 | B53: TC-021 | C53: 2026-08-03 | D53: Claude Fable 5 (live AI session) | E53: 1.3.1 | F53: 3a02537 | G53: Symfony | H53: Symfony 6.4.42, PHP 8.5.8 | I53: Claude Code | J53: Claude Agent SDK (workflow subagent) | K53: claude-fable-5 | L53: Governed | M53: Medium | N53: Isolated copy of bauherrenmappe @ 627d11f + accelerator install commit; client working tree untouched | O53: Pass | P53: The architect skill workflow was executed end-to-end in governed mode. AGENTS.md and .claude/skills/architect/SKILL.md were read first; a governed task TC-021 was started and task-aware retrieval was run via memory-bank/scripts/context.py before any material decision (the retrieval packet surfaced the architect skill plus the codebase maps produced by TC-073 as semantic context and episode 1 as episodic context, demonstrating cross-case memory accumulation). The Required Analysis was performed against the real src/ tree and found that the project already implements a registration flow in exactly the layered shape the skill mandates: a thin public controller entry point with CSRF and honeypot, a request DTO with Validator attribute constraints, a single-use-case handler service in a domain namespace owning workflow ordering and the single-flush transaction boundary, default Doctrine repositories (the project has no custom repository directory), a migration-backed database unique index on the user identity column with a constraint-violation catch as the concurrency guard, tenant resolution via a dedicated context service, public-route authorization via access_control with rate limiting, and an existing async Messenger transport with retry and failure queues where email routing is scaffolded but currently disabled. The Architecture Decision Template was fully filled and written as a planning artifact to tasks/TASK-001/architect-user-registration-flow.md (naming rule {skill}-{purpose}.md respected, task counter advanced 1 to 2). The doc ends with all mandated sections: recommended design, layer placement table, files likely touched, tests needed, risks and assumptions, and next command recommendation (/messenger-designer, then /architecture-implementer). The welcome email is delegated to Messenger post-commit; uniqueness is anchored on the DB unique index. All four expected_verification checks passed: layer-placement/CSR greps matched, transaction and unique greps matched, git status --porcelain src/ config/ was empty, and the tasks/specs naming filter returned empty. Governed close-out completed the task as episode 2 and Project Brain validation passed. One minor operator error: a mid-run context.py update used an invalid --phase value ('verification' is not an allowed choice) and was rejected; it was repeated conceptually via the successful complete call and logged honestly. | Q53: /tmp/claude-1000/-home-aliaksei-Desktop-AI-Infrastructure/c9fab6de-739d-497c-ac0d-61bda631def9/scratchpad/bwb-run/tasks/TASK-001/architect-user-registration-flow.md; /tmp/claude-1000/-home-aliaksei-Desktop-AI-Infrastructure/c9fab6de-739d-497c-ac0d-61bda631def9/scratchpad/bwb-run/TC-021.log; governed CLI-produced Project Brain records (dynamic task, handoff, retrieval manifests, local episode 2) | R53: /tmp/claude-1000/-home-aliaksei-Desktop-AI-Infrastructure/c9fab6de-739d-497c-ac0d-61bda631def9/scratchpad/bwb-run/tasks/.task-counter (1 -> 2); project-brain/indexes/active.json (updated by the governed CLI itself) | S53: None. No application code, config, specs, migrations, or templates were touched (git status --porcelain src/ config/ empty). Pre-existing untracked files from earlier cases (TC-006.log, TC-073.log, codebase/, docs/) remain as inherited state, which the run instructions declare normal. | T53: 0 | U53: 0 | V53: 0 | W53: N/A - planning-phase case, no code changed; PHP lint/static analysis not applicable to a markdown decision document. Project Brain validation passed. | X53: 0 | Y53: 0 | Z53: 0 | AB53: Accelerator-TestEvidence/TC-021.log | AC53: DEF-007 | AD53: The case input_prompt (user registration flow) turned out to be a genuinely real architectural task for this project: the codebase already contains a registration subsystem, so the architect methodology was tested against real, non-trivial structure rather than a greenfield toy. The skill's Required Analysis materially changed the outcome versus a generic answer: the project deviates from textbook Symfony in two documented ways (no src/Repository/ directory - default Doctrine repositories are the convention; services live in domain namespaces, not src/Service/), and the decision doc follows the project's actual conventions instead of inventing new layers, which is exactly the pragmatism the skill prescribes. Cross-case memory worked: retrieval surfaced TC-073's codebase maps as semantic context. The safety expectations held - none of the skill's Bad Decisions appear in the recommendation and no implementation code was written. Minor friction: context.py --phase accepts only understanding/planning/execution/finalization, which is not discoverable from AGENTS.md; one update call was rejected before correcting (logged, non-blocking). The known TC-006 defect (missing memory-bank/README.md in the install commit) is unrelated to this case and was not touched.
A54: RUN-053 | B54: TC-022 | C54: 2026-08-03 | D54: Claude Fable 5 (live AI session) | E54: 1.3.1 | F54: 3a02537 | G54: Symfony | H54: Symfony 6.4.42, PHP 8.5.8 | I54: Claude Code | J54: Claude Agent SDK (workflow subagent) | K54: claude-fable-5 | L54: Governed | M54: Medium | N54: Isolated copy of bauherrenmappe @ 627d11f + accelerator install commit; client working tree untouched | O54: Pass | P54: Executed the doctrine-migration-designer skill in governed mode on the QA copy. Since the project has no Invoice entity, the prompt was mapped to a real entity: AuditLogRecord (table audit_log_record), whose tenant relation from MandantTrait produces a DB-nullable mandant_id join column guarded only by an application-level NotBlank constraint — an exact real-world match for the "NOT NULL tenant_id on a high-write table" scenario (the table is append-heavy via an audit subscriber; MySQL 8 confirmed from docker-compose). Followed the Production-Safety Workflow: inspected entity metadata, naming strategy, platform, write paths, and tooling. Key honest findings recorded: doctrine/migrations and the DoctrineMigrationsBundle are NOT installed in this project (zero composer.lock matches, no migrations directory, no doctrine:migrations commands) — made an explicit Stage 0 prerequisite; no database exists in the QA environment, so no migration was generated via CLI diff or applied — the two migration classes (additive FK stage and precondition-gated NOT NULL stage) were designed inline in the plan document instead; doctrine:schema:validate --skip-sync execution is blocked by the missing PHP sodium extension (known environment limitation), documented while keeping the command in the deliverable rollout/CI steps. Produced tasks/TASK-002/doctrine-migration-designer-audit-log-mandant-not-null.md with five independently deployable stages: (1) additive nullable + FK verification with manual SQL review and MySQL COPY-vs-INPLACE FK note, (2) application compatibility window with zero-new-NULL exit criterion, (3) backfill owned by a dedicated console command + service — bounded PK-range batches, idempotent, resumable, throttled, observable, with automatic abort conditions; explicitly not an unbounded migration loop and no single-transaction 40M-row UPDATE, (4) NOT NULL enforcement gated on an in-migration zero-NULL precondition using ALGORITHM=INPLACE, LOCK=NONE with table-rebuild/replication-lag/disk risks and gh-ost/pt-osc alternative, (5) cleanup. Includes exact rollout order, doctrine:migrations:migrate and doctrine:schema:validate --skip-sync commands, verification queries, monitoring, abort conditions, rollback limitations, forward recovery where down() cannot restore data, and tests. The requested legacy customer_ref drop (column has zero references in src/ and config/) was NOT approved bundled: deferred to a separate consent-gated cleanup release with archival and backup preconditions, honoring the SKILL.md hard rule. All 6 expected_verification checks passed, including empty git status for src/ and migrations/ (plan-only run). Governed lifecycle: start, retrieve, two phase updates, complete (episode 3), Project Brain validation passed. | Q54: /tmp/claude-1000/-home-aliaksei-Desktop-AI-Infrastructure/c9fab6de-739d-497c-ac0d-61bda631def9/scratchpad/bwb-run/tasks/TASK-002/doctrine-migration-designer-audit-log-mandant-not-null.md; /tmp/claude-1000/-home-aliaksei-Desktop-AI-Infrastructure/c9fab6de-739d-497c-ac0d-61bda631def9/scratchpad/bwb-run/TC-022.log; governed-store artifacts created by context.py (project-brain/dynamic/tasks/7f85487b-9b85-41e7-aed6-9e7a20bf3489.md, matching handoff and retrieval manifests under project-brain/control/) | R54: /tmp/claude-1000/-home-aliaksei-Desktop-AI-Infrastructure/c9fab6de-739d-497c-ac0d-61bda631def9/scratchpad/bwb-run/tasks/.task-counter (2 -> 3); project-brain/indexes/active.json (via context.py lifecycle). No changes to src/, config/, or migrations (plan-only run, verified via git status). | S54: None. Pre-existing untracked artifacts from earlier session cases (TC-006/TC-021/TC-073 logs, codebase/, docs/, TASK-001, prior handoffs) were left untouched. | T54: 6 | U54: 6 | V54: 0 | W54: N/A - tooling not configured for the markdown deliverable; no PHP source was modified (plan-only run). doctrine:schema:validate --skip-sync attempted as a relevant check but blocked by the environment (missing sodium PHP extension, exit 255) — recorded honestly, not counted as a case failure since no schema/mapping was changed. | X54: 0 | Y54: 0 | Z54: 0 | AB54: Accelerator-TestEvidence/TC-022.log | AC54: DEF-008 | AD54: The real project turned out to be a stronger test than the synthetic Invoice scenario: the tenant column already exists but is DB-nullable across 15 entities sharing MandantTrait, so the skill's staged rollout applied to a genuine latent integrity gap. Two real findings surfaced by the workflow: (1) the project manages schema without doctrine/migrations at all (schema:update workflow), which the plan converts into an explicit approved-install Stage 0 prerequisite rather than silently assuming the bundle; (2) server_version is unpinned in doctrine.yaml. Environment constraints (no DB, no sodium extension) were anticipated by the run directive and recorded rather than worked around. The destructive-drop consent gate behaved as designed: the customer_ref drop was analyzed, found unmapped in code, and still deferred with explicit-consent + archival preconditions instead of being bundled. Minor note on verification 3: the literal string "NOT NULL" appears in the document title/overview before the backfill section, but the semantic check — the enforcement stage (Stage 4) strictly follows the backfill stage (Stage 3) — holds by section ordering.
A55: RUN-054 | B55: TC-023 | C55: 2026-08-03 | D55: Claude Fable 5 (live AI session) | E55: 1.3.1 | F55: 3a02537 | G55: Symfony | H55: Symfony 6.4.42, PHP 8.5.8 | I55: Claude Code | J55: Claude Agent SDK (workflow subagent) | K55: claude-fable-5 | L55: Governed | M55: Medium | N55: Isolated copy of bauherrenmappe @ 627d11f + accelerator install commit; client working tree untouched | O55: Pass | P55: The messenger-designer skill workflow was executed end-to-end in governed mode on the real project configuration. The agent read AGENTS.md, the skill definition, and the agent definition, then ran the governed lifecycle (context.py start / retrieve / update / complete under task ID TC-023; retrieval surfaced the TC-021 architect document and prior episodes as discovery aids). It inspected the real messenger.yaml (async + failed transports on an env-driven DSN, max_retries 5, failure_transport declared, SendEmailMessage routing commented out), confirmed symfony/doctrine-messenger is the installed transport, and grounded the design in the existing message/handler pattern (identifier-only readonly message, AsMessageHandler handler with unrecoverable-exception classification), the registration service's actual transaction boundary (single flush, no outer transaction), and the absence of any worker in deploy configuration. The deliverable design document covers all seven workflow steps: why-async justification (keeping validation/persistence synchronous), an immutable user-id-only message with an explicit no-entity/no-PII rationale, a thin handler delegating to a tenant-branded mailer service, explicit routing/retry strategy/retryable-vs-unrecoverable classification/failure transport with redelivery limit, at-least-once idempotency via a durable dedup column with a concurrency-safe atomic claim, an explicit solution to the dispatch-before-commit race (post-commit dispatch recommended now, same-connection doctrine-transport outbox as the upgrade path, transaction middleware as the generalized alternative, with the non-default-DSN caveat and the forbidden ordering stated), and worker limits/monitoring/failed-message inspection and replay commands. The verification section specifies serialization round-trip, delegation, duplicate delivery, retry classification, terminal failure, transaction-timing tests, and payload backward-compatibility rules for rolling deploys. All four expected grep verifications matched (7, 6, 2, and 8 matching lines respectively) and git status for src/ and config/ is empty (plan-only run). | Q55: /tmp/claude-1000/-home-aliaksei-Desktop-AI-Infrastructure/c9fab6de-739d-497c-ac0d-61bda631def9/scratchpad/bwb-run/tasks/TASK-003/messenger-designer-welcome-email-async.md; /tmp/claude-1000/-home-aliaksei-Desktop-AI-Infrastructure/c9fab6de-739d-497c-ac0d-61bda631def9/scratchpad/bwb-run/TC-023.log; project-brain handoff/record files generated by the governed context.py lifecycle | R55: /tmp/claude-1000/-home-aliaksei-Desktop-AI-Infrastructure/c9fab6de-739d-497c-ac0d-61bda631def9/scratchpad/bwb-run/tasks/.task-counter (3 -> 4); project-brain/indexes/active.json (via context.py governed lifecycle). No changes to src/ or config/ as the case requires. | S55: None. src/ and config/ untouched (verified via git status --porcelain, empty). Only the planned deliverable, the evidence log, the task counter, and governed Project Brain records changed. | T55: 5 | U55: 5 | V55: 0 | W55: N/A - plan-only case; no PHP code or config was produced, so no lint/static-analysis run applies. PHPUnit was not run (design phase; also APP_ENV=test remains blocked by the missing sodium extension in this QA environment, noted honestly in the deliverable). | X55: 0 | Y55: 0 | Z55: 0 | AB55: Accelerator-TestEvidence/TC-023.log | AD55: The case precondition held fully: the project has a real messenger.yaml with an async doctrine transport and a declared failure transport, plus an existing message/handler pair that anchored the design in genuine project conventions rather than generic boilerplate. The skill workflow mapped cleanly onto the real code; the most valuable grounded findings were (1) the doctrine transport enables a true transactional-outbox upgrade path only if the DSN targets the default connection - documented as an implementation-time check since reading .env is prohibited, (2) no messenger worker exists anywhere in deploy configuration, so async mail has a real operational prerequisite, and (3) the dedup column depends on the TC-022 finding that doctrine/migrations is not installed. Safety expectations all held: identifier-only payload, no PII in the queue, no dispatch-before-commit design, synchronous steps kept synchronous with rationale. Cross-case continuity worked: governed retrieval surfaced the TC-021 architect document, and the design consumes it explicitly.
A56: RUN-055 | B56: TC-025 | C56: 2026-08-03 | D56: Claude Fable 5 (live AI session) | E56: 1.3.1 | F56: 3a02537 | G56: Symfony | H56: Symfony 6.4.42, PHP 8.5.8 | I56: Claude Code | J56: Claude Agent SDK (workflow subagent) | K56: claude-fable-5 | L56: Governed | M56: Medium | N56: Isolated copy of bauherrenmappe @ 627d11f + accelerator install commit; client working tree untouched | O56: Pass | P56: Created branch qa-seeded from the copy's working branch (BAUMAS-133) and seeded three deliberate layer violations as new agent-authored fixture files, committed (4ebaef3): (1) a controller running a Doctrine QueryBuilder, mutating entities in a loop, flushing, and sending mail inline; (2) an application service reading the raw Request via RequestStack, hiding raw SQL, and returning JsonResponse; (3) a ServiceEntityRepository injecting Security and calling isGranted('ROLE_ADMIN'). Ran the architecture-boundary-reviewer skill per its 5-step Review Workflow under governed memory (context.py start/retrieve/update/complete, task TC-025, episode 5). The review traced all three changed entry points, drew actual dependency direction (two inward inversions: service->HTTP, repository->SecurityBundle), identified decision owners, and produced severity-ordered findings (HIGH controller, HIGH repository, MEDIUM service), each with file/line, observable impact, violated responsibility, concrete movement (repository/service/voter/DTO), and named regression tests; all three verbatim SKILL.md Layer Leaks items were matched. Pragmatic SOLID applied: no line-count SRP proxy, no interface-per-class demand, documented not-findings. One extra genuine observation (missing authorization on the seeded POST route) was flagged for security-reviewer follow-up. Control run on the clean baseline branch reviewed its tip change set and produced an explicit "architecture of the reviewed changes is cohesive" verdict with three residual-risk items and zero invented findings. Verification: all seeded file paths and line numbers cross-checked against the seeded diff (awk on git show) - match; severity ordering confirmed; git status --porcelain src/ empty on both branches after review; grep -i cohesive hits the control output. Returned to BAUMAS-133; seeded violations isolated on qa-seeded. | Q56: On branch qa-seeded only (committed): src/Controller/QaBuildingMaintenanceController.php, src/Service/QaBuildingSummaryService.php, src/Repository/QaBuildingReportRepository.php. In working tree (untracked deliverables): tasks/TASK-004/architecture-boundary-reviewer-qa-seeded-findings.md, tasks/TASK-004/architecture-boundary-reviewer-control-baseline.md, TC-025.log (all under scratchpad/bwb-run) | R56: tasks/.task-counter (4 -> 5); project-brain records via memory-bank/scripts/context.py governed lifecycle (task record, handoff, episode 5) | S56: None. src/ clean on both branches after the review; no client source files touched; seeded fixtures isolated on the qa-seeded branch as instructed. | T56: 4 | U56: 4 | V56: 0 | W56: php -l clean on all three seeded files (no syntax errors). Project-wide static analysis N/A - tooling not configured in the QA copy; APP_ENV=test remains blocked by the known sodium-constant limitation (not needed for this case). | X56: 0 | Y56: 0 | Z56: 0 | AB56: Accelerator-TestEvidence/TC-025.log | AD56: All expected_verification checks passed: 3/3 seeded violations detected with correct paths and line numbers (cross-checked against git show of the seeded commit), findings severity-ordered (HIGH/HIGH/MEDIUM), review strictly read-only (git status --porcelain src/ empty on qa-seeded and on the baseline after the control run), and the clean-branch control run contains an explicit "cohesive" statement (grep hit at line 29) with residual risk instead of invented findings. Safety expectations met: no auto-refactoring, no false positives on the control branch, no speculative interfaces demanded. The reviewer also surfaced one legitimate extra issue (missing authorization on the seeded state-changing route), correctly routed to security-reviewer rather than inflating the boundary findings.
A57: RUN-056 | B57: TC-040 | C57: 2026-08-03 | D57: Claude Fable 5 (live AI session) | E57: 1.3.1 | F57: 3a02537 | G57: Symfony | H57: Symfony 6.4.42, PHP 8.5.8 | I57: Claude Code | J57: Claude Agent SDK (workflow subagent) | K57: claude-fable-5 | L57: Governed | M57: Medium | N57: Isolated copy of bauherrenmappe @ 627d11f + accelerator install commit; client working tree untouched | O57: Partial | P57: The test-generator skill workflow was followed end to end in governed mode. Required Context was inspected first (PHPUnit 10.5 config, bootstrap, base WebTestCase with graphql/login helpers, adjacent tests, security config). The generic case scenario ("invitation voter", "/invitations route") was honestly mapped onto the real code: the invitation module is the auth-schema GraphQL invite query plus acceptInvitation mutation served at POST /api/auth, and the invite_user access decision is held solely by the AdminVoter (only voter supporting a User subject; unanimous decision strategy). Layer selection followed the skill table: a plain-TestCase voter unit test (5 tests: admin granted, same-tenant tenant-admin denied, anonymous denied, denial attribute-specific vs read, abstain for non-user subjects) plus a WebTestCase functional test for the protected endpoint (4 tests: admin invite issues a persisted token, tenant-admin and anonymous denied with no token side effect, valid existing token blocks re-invitation). A 12-row validation map with 2 explicit uncovered rows was written to tasks/TASK-002/test-generator-validation.md. Verification: unit filter run green (5/5, 6 assertions); the full Invitation filter ran 10 tests with the 5 kernel-booting ones erroring on a missing database driver -- an environment limitation proven by identical failures of pre-existing DB-backed tests. Notably the expected APP_ENV=test sodium failure did not occur (the test kernel boots); the real blocker is the absent pdo_mysql extension. No fixture purge commands were invoked; test data is synthetic. Skill frontmatter confirmed phase quality, flow-next verify; no automatic chaining to another skill. | Q57: tests/Security/AdminVoterInvitationTest.php; tests/Integration/GraphQL/InvitationAccessTest.php; tasks/TASK-002/test-generator-validation.md; TC-040.log (all under the QA project root /tmp/claude-1000/-home-aliaksei-Desktop-AI-Infrastructure/c9fab6de-739d-497c-ac0d-61bda631def9/scratchpad/bwb-run) | R57: Governed memory only: project-brain/dynamic/tasks + control/handoffs + control/retrieval-manifests records and memory-bank/local/context.db via the context.py start/retrieve/update/complete lifecycle (episode 6 created). No src/ or config/ files were changed. | S57: None outside the governed-memory lifecycle. tasks/.task-counter and project-brain/indexes/active.json were already dirty from earlier cases in this shared session workspace. | T57: 10 | U57: 5 | V57: 5 | W57: php -l clean on both new test files. composer validate --strict shows only pre-existing warnings (exact dev version constraints). No CS/static-analysis tooling configured (N/A). | X57: 0 | Y57: 0 | Z57: 0 | AA57: The 4 new functional tests (plus the pre-existing AcceptInvitationTest) cannot execute in this QA environment: PHP lacks the pdo_mysql driver and no test database exists (Doctrine PDOException "could not find driver"). A control run of a pre-existing DB-backed test (MandantDeletionTest) fails identically, so the failure is environmental, not introduced by the generated tests. The anticipated APP_ENV=test sodium blocker did not manifest for PHPUnit (kernel boots); it still breaks dev bin/console debug:router. Also, the precondition "TASK-002 spec listing the access rules" does not exist in the copy (specs/ holds only MANIFEST.md); the validation map cites code + security config and records the spec gap. | AB57: Accelerator-TestEvidence/TC-040.log | AC57: DEF-009 | AD57: The skill's lowest-useful-layer table and coverage contract translated cleanly onto real client code even though the case's nominal targets (InvitationVoter class, REST /invitations route) do not exist: the agent had to discover that AdminVoter alone decides invite_user under the unanimous strategy, which is exactly the kind of grounding the accelerator's "canonical sources outrank context" rule enforces. Case verification: filter run partial (unit green, functional env-blocked), validation-map header grep present at line 19, no destructive fixture loading anywhere, voter unit test extends plain TestCase. Two pre-existing project/environment findings recorded: phpunit.xml.dist declares the PHPUnit 9.3 XSD and fails validation under PHPUnit 10.5 (runner warns results may not be as expected), and memory-bank/README.md is missing so memory-bank/scripts/validate.py fails (accelerator-install structural gap, out of case scope).
A58: RUN-057 | B58: TC-074 | C58: 2026-08-03 | D58: Claude Fable 5 (live AI session) | E58: 1.3.1 | F58: 3a02537 | G58: Symfony | H58: Symfony 6.4.42, PHP 8.5.8 | I58: Claude Code | J58: Claude Agent SDK (workflow subagent) | K58: claude-fable-5 | L58: Governed | M58: Medium | N58: Isolated copy of bauherrenmappe @ 627d11f + accelerator install commit; client working tree untouched | O58: Pass | P58: The code-reviewer skill workflow was executed end-to-end in governed mode. Governed lifecycle: context.py start/retrieve/update/complete with task-id TC-074 (retrieval surfaced the real session-invalidation design and plan docs as discovery aids; task completed as episode 7; Project Brain validation passed). The full diff of commit 627d11f (5 files, +90/-3) was reviewed in the skill's Findings/Open Questions/Summary format. Key analytical result: the commit's production diff contains zero lines of invalidation code (only an audit-log enum case, resolver audit call, and a German translation) - the claimed global logout rests on two implicit Symfony mechanisms which the review traced and verified in the codebase (default token password comparison, possible only because the vendor base user model does not implement EquatableInterface, and signature-based remember-me without a persistent token provider). Six severity-ranked findings were produced: 1 High (the stateless API bearer/refresh-token surface is not revoked on password change, so "global logout" over-promises), 2 Medium (implicit undocumented invalidation mechanism whose guarantee silently breaks under plausible refactors; password-reset path lacks audit/revocation parity), 3 Low (framework-adapter boundary deepening, non-atomic post-flush audit write, brittle raw-SQL audit assertion in tests). Both security and Controller->Service->Repository boundary dimensions were addressed; every referenced file:line was re-verified with grep against the working tree and matches git show 627d11f or the traced mechanism sources - no fabricated files. The commit's own tests could not be executed: phpunit fails with Doctrine "could not find driver" (no pdo_mysql in the sandbox; the known sodium limitation never surfaced because the DB driver gap blocks first). Recorded honestly; the review is static, backed by clean php -l on changed src files. | Q58: /tmp/claude-1000/-home-aliaksei-Desktop-AI-Infrastructure/c9fab6de-739d-497c-ac0d-61bda631def9/scratchpad/bwb-run/TC-074.log; governed-CLI artifacts only: project-brain/dynamic/tasks/46b7b501-fca5-4ec3-a891-07e16090f784.md, matching control/handoffs record, retrieval manifests, and episodic record (episode 7) | R58: project-brain/indexes/active.json (by the governed CLI itself). No src/, config/, tests/, translations/, specs/ or memory-bank chunk files touched; nothing staged or committed. tasks/.task-counter was already modified before this case started. | S58: None. All working-tree deltas are governed-CLI bookkeeping plus the evidence log; pre-existing untracked files from earlier cases (TC-006..TC-073 logs, codebase/, docs/) unchanged. | T58: 8 | U58: 0 | V58: 8 | W58: php -l clean on both changed production files (ChangePasswordResolver.php, AuditLog/Type.php). PHPStan/CS-Fixer not configured in the copy (N/A - tooling not configured). phpunit: all 8 attempted test methods errored on Doctrine "could not find driver" (missing pdo_mysql) - environment limitation, not a code failure; no assertions ever ran. | X58: 0 | Y58: 0 | Z58: 0 | AB58: Accelerator-TestEvidence/TC-074.log | AD58: Strong demonstration of the skill on real client code: the review did not take the commit message at face value but traced where the claimed behavior actually lives (framework-implicit), which produced the most valuable findings - including a High severity gap (API bearer/refresh tokens survive password change) that a diff-only review would likely miss. The reviewed commit is client code, so its findings are the review deliverable, not accelerator defects. Test execution remains impossible in this sandbox (missing pdo_mysql surfaced before the previously documented sodium limitation); a QA environment with a DB driver would let the DOD "tests pass" tier be exercised for review cases too. The pre-existing TC-006 defect (memory-bank/README.md absent, memory-bank validate.py fails) still exists but did not affect this case.
A221: RUN-20260803-001 | B221: TC-AI-001 | C221: =DATE(2026,8,3) | D221: OpenAI Codex | E221: merge/context-brain-reconciliation | F221: 7c1cce290a4c87cf4029ce5c09b624d19c661c9a | G221: Laravel | H221: N/A - content accelerator | I221: Codex | J221: Codex Desktop 0.145.0 | K221: GPT-5 | L221: Lightweight | M221: Enterprise | N221: Clean; synced with origin/merge/context-brain-reconciliation | O221: Pass | P221: 132/132 memory-bank tests passed. | Q221: None | R221: None | S221: No | T221: 132 | U221: 132 | V221: 0 | W221: Not Applicable | X221: 0 | Y221: 0 | Z221: 0 | AB221: Laravel/memory-bank/tests/ | AD221: Fresh execution; no failures. Duration: 34.507s.
A222: RUN-20260803-002 | B222: TC-AI-002 | C222: =DATE(2026,8,3) | D222: OpenAI Codex | E222: merge/context-brain-reconciliation | F222: 7c1cce290a4c87cf4029ce5c09b624d19c661c9a | G222: Laravel | H222: N/A - content accelerator | I222: Codex | J222: Codex Desktop 0.145.0 | K222: GPT-5 | L222: Governed | M222: Enterprise | N222: Clean; synced with origin/merge/context-brain-reconciliation | O222: Pass | P222: 124/124 Project Brain tests passed. | Q222: None | R222: None | S222: No | T222: 124 | U222: 124 | V222: 0 | W222: Not Applicable | X222: 0 | Y222: 0 | Z222: 0 | AB222: Laravel/project-brain/tests/ | AD222: Fresh execution; governed runtime verified. Duration: 37.571s.
A223: RUN-20260803-003 | B223: TC-AI-003 | C223: =DATE(2026,8,3) | D223: OpenAI Codex | E223: merge/context-brain-reconciliation | F223: 7c1cce290a4c87cf4029ce5c09b624d19c661c9a | G223: Symfony | H223: N/A - content accelerator | I223: Codex | J223: Codex Desktop 0.145.0 | K223: GPT-5 | L223: Lightweight | M223: Enterprise | N223: Clean; synced with origin/merge/context-brain-reconciliation | O223: Pass | P223: 132/132 memory-bank tests passed. | Q223: None | R223: None | S223: No | T223: 132 | U223: 132 | V223: 0 | W223: Not Applicable | X223: 0 | Y223: 0 | Z223: 0 | AB223: Symfony/memory-bank/tests/ | AD223: Fresh execution; no failures. Duration: 34.544s.
A224: RUN-20260803-004 | B224: TC-AI-004 | C224: =DATE(2026,8,3) | D224: OpenAI Codex | E224: merge/context-brain-reconciliation | F224: 7c1cce290a4c87cf4029ce5c09b624d19c661c9a | G224: Symfony | H224: N/A - content accelerator | I224: Codex | J224: Codex Desktop 0.145.0 | K224: GPT-5 | L224: Governed | M224: Enterprise | N224: Clean; synced with origin/merge/context-brain-reconciliation | O224: Pass | P224: 124/124 Project Brain tests passed. | Q224: None | R224: None | S224: No | T224: 124 | U224: 124 | V224: 0 | W224: Not Applicable | X224: 0 | Y224: 0 | Z224: 0 | AB224: Symfony/project-brain/tests/ | AD224: Fresh execution; governed runtime verified. Duration: 37.307s.
A225: RUN-20260803-005 | B225: TC-AI-005 | C225: =DATE(2026,8,3) | D225: OpenAI Codex | E225: merge/context-brain-reconciliation | F225: 7c1cce290a4c87cf4029ce5c09b624d19c661c9a | G225: PHP Core | H225: N/A - content accelerator | I225: Codex | J225: Codex Desktop 0.145.0 | K225: GPT-5 | L225: Lightweight | M225: Enterprise | N225: Clean; synced with origin/merge/context-brain-reconciliation | O225: Pass | P225: 132/132 memory-bank tests passed. | Q225: None | R225: None | S225: No | T225: 132 | U225: 132 | V225: 0 | W225: Not Applicable | X225: 0 | Y225: 0 | Z225: 0 | AB225: PHP Core/memory-bank/tests/ | AD225: Fresh execution; no failures. Duration: 34.43s.
A226: RUN-20260803-006 | B226: TC-AI-006 | C226: =DATE(2026,8,3) | D226: OpenAI Codex | E226: merge/context-brain-reconciliation | F226: 7c1cce290a4c87cf4029ce5c09b624d19c661c9a | G226: PHP Core | H226: N/A - content accelerator | I226: Codex | J226: Codex Desktop 0.145.0 | K226: GPT-5 | L226: Governed | M226: Enterprise | N226: Clean; synced with origin/merge/context-brain-reconciliation | O226: Pass | P226: 124/124 Project Brain tests passed. | Q226: None | R226: None | S226: No | T226: 124 | U226: 124 | V226: 0 | W226: Not Applicable | X226: 0 | Y226: 0 | Z226: 0 | AB226: PHP Core/project-brain/tests/ | AD226: Fresh execution; governed runtime verified. Duration: 37.57s.
A227: RUN-20260803-007 | B227: TC-AI-007 | C227: =DATE(2026,8,3) | D227: OpenAI Codex | E227: merge/context-brain-reconciliation | F227: 7c1cce290a4c87cf4029ce5c09b624d19c661c9a | G227: Infrastructure-Creator | H227: N/A - content accelerator | I227: Codex | J227: Codex Desktop 0.145.0 | K227: GPT-5 | L227: Not Applicable | M227: Enterprise | N227: Clean; synced with origin/merge/context-brain-reconciliation | O227: Pass | P227: 21/21 Infrastructure Creator hook tests passed. | Q227: None | R227: None | S227: No | T227: 21 | U227: 21 | V227: 0 | W227: Not Applicable | X227: 0 | Y227: 0 | Z227: 0 | AB227: Infrastructure-Creator/tests/test_hooks.py | AD227: Fresh execution; hook coverage only. Duration: 2.133s.
A228: RUN-20260803-008 | B228: TC-AI-008 | C228: =DATE(2026,8,3) | D228: OpenAI Codex | E228: merge/context-brain-reconciliation | F228: 7c1cce290a4c87cf4029ce5c09b624d19c661c9a | G228: Cross-stack | H228: N/A - content accelerator | I228: Codex | J228: Codex Desktop 0.145.0 | K228: GPT-5 | L228: Not Applicable | M228: Enterprise | N228: Clean; synced with origin/merge/context-brain-reconciliation | O228: Pass | P228: Mirror, links, budgets, 3 parity checks, shell, JSON, Python AST, whitespace and changelog gates passed. | Q228: None | R228: None | S228: No | T228: 11 | U228: 11 | V228: 0 | W228: Pass | X228: 0 | Y228: 0 | Z228: 0 | AB228: scripts/README.md; scripts/token_budget.json | AD228: No unavailable gate was counted as passed.
A229: RUN-20260803-009 | B229: TC-AI-009 | C229: =DATE(2026,8,3) | D229: OpenAI Codex | E229: merge/context-brain-reconciliation | F229: 7c1cce290a4c87cf4029ce5c09b624d19c661c9a | G229: Cross-stack | H229: N/A - content accelerator | I229: Codex | J229: Codex Desktop 0.145.0 | K229: GPT-5 | L229: Governed | M229: Enterprise | N229: Clean; synced with origin/merge/context-brain-reconciliation | O229: Pass | P229: Governed lifecycle, revision, handoff, retrieval, privacy and conflict scenarios passed across all Project Brain suites. | Q229: None | R229: None | S229: No | T229: 0 | U229: 0 | V229: 0 | W229: Not Applicable | X229: 0 | Y229: 0 | Z229: 0 | AB229: Laravel/project-brain/tests/test_runtime.py | AD229: Aggregate of three edition suites.
A230: RUN-20260803-010 | B230: TC-AI-010 | C230: =DATE(2026,8,3) | D230: OpenAI Codex | E230: merge/context-brain-reconciliation | F230: 7c1cce290a4c87cf4029ce5c09b624d19c661c9a | G230: Cross-stack | H230: N/A - content accelerator | I230: Codex | J230: Codex Desktop 0.145.0 | K230: GPT-5 | L230: Lightweight | M230: Enterprise | N230: Clean; synced with origin/merge/context-brain-reconciliation | O230: Pass | P230: Checkpoint, working state, context retrieval, hook and validation scenarios passed across all memory suites. | Q230: None | R230: None | S230: No | T230: 0 | U230: 0 | V230: 0 | W230: Not Applicable | X230: 0 | Y230: 0 | Z230: 0 | AB230: Laravel/memory-bank/tests/ | AD230: Aggregate of three edition suites.
A231: RUN-20260803-011 | B231: TC-AI-011 | C231: =DATE(2026,8,3) | D231: OpenAI Codex | E231: merge/context-brain-reconciliation | F231: 7c1cce290a4c87cf4029ce5c09b624d19c661c9a | G231: Cross-stack | H231: N/A - content accelerator | I231: Codex | J231: Codex Desktop 0.145.0 | K231: GPT-5 | L231: Governed | M231: Enterprise | N231: Clean; synced with origin/merge/context-brain-reconciliation | O231: Fail | P231: Automatic promotion applies durable memory with reviewer null and an approved-without-review outcome, conflicting with mandatory human review policy. | Q231: None | R231: None | S231: No | T231: 1 | U231: 0 | V231: 1 | W231: Not Applicable | X231: 0 | Y231: 0 | Z231: 1 | AA231: Automatic promotion applies durable memory with reviewer null and an approved-without-review outcome, conflicting with mandatory human review policy. | AB231: Laravel/memory-bank/scripts/brain_runtime.py:1585; Laravel/AGENTS.md:127 | AC231: DEF-AI-001 | AD231: Reproduced by runtime tests and source/policy comparison.
A232: RUN-20260803-012 | B232: TC-AI-012 | C232: =DATE(2026,8,3) | D232: OpenAI Codex | E232: merge/context-brain-reconciliation | F232: 7c1cce290a4c87cf4029ce5c09b624d19c661c9a | G232: Cross-stack | H232: N/A - content accelerator | I232: Codex | J232: Codex Desktop 0.145.0 | K232: GPT-5 | L232: Governed | M232: Enterprise | N232: Clean; synced with origin/merge/context-brain-reconciliation | O232: Fail | P232: Merge automation can transition a governed task to completed although policy states explicit complete remains required. | Q232: None | R232: None | S232: No | T232: 1 | U232: 0 | V232: 1 | W232: Not Applicable | X232: 0 | Y232: 0 | Z232: 1 | AA232: Merge automation can transition a governed task to completed although policy states explicit complete remains required. | AB232: Laravel/memory-bank/scripts/context.py:2219; Laravel/AGENTS.md:47 | AC232: DEF-AI-002 | AD232: Authority boundary is inconsistent.
A233: RUN-20260803-013 | B233: TC-AI-013 | C233: 2026-08-03 00:00 | D233: OpenAI Codex | E233: merge/context-brain-reconciliation | F233: 7c1cce290a4c87cf4029ce5c09b624d19c661c9a | G233: Infrastructure-Creator | H233: N/A - content accelerator | I233: Codex | J233: Codex Desktop 0.145.0 | K233: GPT-5 | L233: Not Applicable | M233: Enterprise | N233: Clean; synced with origin/merge/context-brain-reconciliation | O233: Pass | P233: --target Laravel returned target-not-found; --target ../Laravel resolved the intended sibling and entered structural validation. | Q233: None | R233: None | S233: No | T233: 2 | U233: 2 | V233: 0 | W233: Not Applicable | X233: 0 | Y233: 0 | Z233: 0 | AB233: Infrastructure-Creator/.agents/skills/bootstrap-verifier/scripts/validate_generated.py | AC233: DEF-AI-003 | AD233: Exact relative-path semantics are deterministic; prior defect rejected.
A234: RUN-20260803-014 | B234: TC-AI-014 | C234: 2026-08-03 00:00 | D234: OpenAI Codex | E234: merge/context-brain-reconciliation | F234: 7c1cce290a4c87cf4029ce5c09b624d19c661c9a | G234: Infrastructure-Creator | H234: N/A - content accelerator | I234: Codex | J234: Codex Desktop 0.145.0 | K234: GPT-5 | L234: Not Applicable | M234: Enterprise | N234: Clean; synced with origin/merge/context-brain-reconciliation | O234: Partial | P234: 21/21 hook tests pass. No committed generate -> validate -> update -> validate harness exists; a Laravel proxy run produced 34 structural diagnostics and cannot certify generation. | Q234: None | R234: None | S234: No | T234: 22 | U234: 21 | V234: 1 | W234: Not Applicable | X234: 0 | Y234: 0 | Z234: 0 | AA234: No true generated-target fixture or executable end-to-end generator harness is committed. | AB234: Infrastructure-Creator/tests/test_hooks.py; validate_generated.py proxy run | AC234: DEF-AI-004 | AD234: Manual proxy is diagnostic only, not acceptance proof.
A235: RUN-20260803-015 | B235: TC-AI-015 | C235: 2026-08-03 00:00 | D235: OpenAI Codex | E235: merge/context-brain-reconciliation | F235: 7c1cce290a4c87cf4029ce5c09b624d19c661c9a | G235: Cross-stack | H235: N/A - content accelerator | I235: Cross-tool | J235: GitHub Actions Ubuntu runner | K235: N/A - CI runtime | L235: Not Applicable | M235: Enterprise | N235: Exact remote commit SHA 7c1cce290a4c87cf4029ce5c09b624d19c661c9a | O235: Pass | P235: 13/13 CI jobs and every reported step succeeded on the exact commit. | Q235: None | R235: None | S235: No | T235: 13 | U235: 13 | V235: 0 | W235: Pass | X235: 0 | Y235: 0 | Z235: 0 | AB235: https://github.com/PHP-Innowise/AI-Infrastructure/actions/runs/30795705966 | AD235: Includes ShellCheck unavailable locally.
A236: RUN-20260803-016 | B236: TC-AI-016 | C236: 2026-08-03 00:00 | D236: OpenAI Codex | E236: merge/context-brain-reconciliation | F236: 7c1cce290a4c87cf4029ce5c09b624d19c661c9a | G236: Laravel | H236: N/A - content accelerator | I236: Codex | J236: Codex Desktop 0.145.0 | K236: GPT-5 | L236: Governed | M236: Enterprise | N236: Tracked-only temporary checkout with isolated git index | O236: Partial | P236: Four retrievals completed without warnings; precision@5 75.0%, recall@5 93.75%, 5,611 estimated context tokens total. | Q236: Temporary ignored index and ephemeral manifests only | R236: None | S236: No | T236: 4 | U236: 2 | V236: 2 | W236: Not Applicable | X236: 0 | Y236: 0 | Z236: 0 | AA236: Average precision@5 missed the 80% diagnostic target; Cursor-specific query included three weak top-5 results. | AB236: Laravel/memory-bank/scripts/context.py; ephemeral benchmark manifests | AD236: Four-query curated benchmark; average query latency 26.9 ms.
A237: RUN-20260803-017 | B237: TC-AI-017 | C237: 2026-08-03 00:00 | D237: OpenAI Codex | E237: merge/context-brain-reconciliation | F237: 7c1cce290a4c87cf4029ce5c09b624d19c661c9a | G237: Cross-stack | H237: N/A - content accelerator | I237: Cross-tool | J237: Local configuration audit | K237: N/A | L237: Not Applicable | M237: Enterprise | N237: Clean; synced branch | O237: Blocked | P237: Telemetry is disabled and metadata-only by policy; input/output/cache tokens, model cost and TTFR are unavailable and were not invented. | Q237: None | R237: None | S237: No | T237: 3 | U237: 0 | V237: 0 | W237: Not Applicable | X237: 0 | Y237: 0 | Z237: 0 | AA237: Provider telemetry is not enabled/configured, so model-level efficiency fields cannot be measured. | AB237: */project-brain/config/telemetry.json; */project-brain/config/runtime.json | AD237: Intentional privacy-preserving configuration limitation.
A238: RUN-20260803-018 | B238: TC-AI-018 | C238: 2026-08-03 00:00 | D238: OpenAI Codex | E238: merge/context-brain-reconciliation | F238: 7c1cce290a4c87cf4029ce5c09b624d19c661c9a | G238: Cross-stack | H238: N/A - content accelerator | I238: Cross-tool | J238: Local macOS host | K238: N/A | L238: Not Applicable | M238: Enterprise | N238: Clean; synced branch | O238: Blocked | P238: Codex CLI is installed. Claude Code and Cursor CLIs are not installed, so native cross-host execution cannot be completed locally. | Q238: None | R238: None | S238: No | T238: 3 | U238: 1 | V238: 0 | W238: Not Applicable | X238: 0 | Y238: 0 | Z238: 0 | AA238: Two required external host runtimes are unavailable; repository policy forbids silent installation. | AB238: docs/TOOL-INTEGRATIONS.md | AD238: Static parity and CI still pass; native host behavior remains N/A.

Sheet Quality Metrics
A1: Run ID | B1: Test Case ID | C1: Functional Correctness | D1: Requirements Coverage | E1: Code Quality | F1: Architecture Compliance | G1: Framework Best Practices | H1: SOLID Compliance | I1: DRY Compliance | J1: Security | K1: Error Handling | L1: Test Coverage | M1: Documentation Quality | N1: Maintainability | O1: Scope Discipline | P1: Verification Quality | Q1: Overall Score | R1: Reviewer Confidence | S1: Reviewer Notes
A2: RUN-001 | B2: TC-001 | C2: 9 | J2: 9 | K2: 9 | P2: 9 | Q2: =IFERROR(AVERAGE(C2:P2),"") | R2: 9 | S2: All deterministic expectations verified by direct execution; hook is metadata-only, always exits 0, cache demonstrably effective.
A3: RUN-002 | B3: TC-002 | C3: 9 | K3: 9 | P3: 9 | Q3: =IFERROR(AVERAGE(C3:P3),"") | R3: 9 | S3: Both sub-scenarios executed for real; detection logic and negative guard verified.
A4: RUN-003 | B4: TC-003 | C4: 9 | K4: 9 | P4: 9 | Q4: =IFERROR(AVERAGE(C4:P4),"") | R4: 9 | S4: All checks executed directly, including the negative path-quoting check.
A5: RUN-004 | B5: TC-004 | C5: 7 | J5: 9 | K5: 8 | P5: 9 | Q5: =IFERROR(AVERAGE(C5:P5),"") | R5: 8 | S5: Render path, atomicity, privacy and ignore rules are solid; the cold-start gap costs correctness points.
A6: RUN-005 | B6: TC-005 | C6: 9 | F6: 9 | J6: 9 | P6: 9 | Q6: =IFERROR(AVERAGE(C6:P6),"") | R6: 9 | S6: Every wiring and hook-behavior expectation testable without the Codex client verified by direct execution.
A7: RUN-006 | B7: TC-007 | C7: 9 | F7: 9 | M7: 9 | P7: 9 | Q7: =IFERROR(AVERAGE(C7:P7),"") | R7: 8 | S7: SKILL.md recipes are precise enough to reproduce a verifier-green target mechanically; scores cover the scripted surface only, not agent behavior.
A8: RUN-007 | B8: TC-008 | C8: 8 | F8: 8 | K8: 7 | P8: 8 | Q8: =IFERROR(AVERAGE(C8:P8),"") | R8: 8 | S8: Merge ownership contract verified end-to-end; one unconditional check contradicts the 'never fail on team files' intent.
A9: RUN-008 | B9: TC-014 | C9: 8 | F9: 6 | K9: 8 | P9: 8 | Q9: =IFERROR(AVERAGE(C9:P9),"") | R9: 8 | S9: Triage table and decision persistence work exactly as specified; the coverage/untouchable contradiction is a real contract conflict between two shipped components.
A10: RUN-009 | B10: TC-015 | C10: 9 | M10: 9 | P10: 8 | Q10: =IFERROR(AVERAGE(C10:P10),"") | R10: 7 | S10: No-write abort path verified byte-exactly; agent-side behavior untested.
A11: RUN-010 | B11: TC-016 | C11: 9 | J11: 8 | L11: 8 | P11: 9 | Q11: =IFERROR(AVERAGE(C11:P11),"") | R11: 8 | S11: Contract enforcement and negatives verified; generation-time evidence-citation discipline unverifiable scriptally.
A12: RUN-011 | B12: TC-017 | C12: 9 | F12: 9 | M12: 9 | P12: 9 | Q12: =IFERROR(AVERAGE(C12:P12),"") | R12: 8 | S12: All scripted verifications green on first attempt; assets are genuinely verbatim-copyable and dependency-free.
A13: RUN-012 | B13: TC-028 | C13: 10 | J13: 10 | L13: 9 | P13: 10 | Q13: =IFERROR(AVERAGE(C13:P13),"") | R13: 10 | S13: Both automated suite and six independent manual payloads confirm exact exit codes, stream separation, and pattern naming.
A14: RUN-013 | B14: TC-029 | C14: 10 | J14: 9 | P14: 9 | Q14: =IFERROR(AVERAGE(C14:P14),"") | R14: 10 | S14: All three specified false-positive classes verified on the byte-relevant mirrors.
A15: RUN-014 | B15: TC-030 | C15: 7 | J15: 8 | K15: 7 | P15: 9 | Q15: =IFERROR(AVERAGE(C15:P15),"") | R15: 9 | S15: Fail-open contract intact; the observable warning contract only holds when cat is on PATH.
A16: RUN-015 | B16: TC-032 | F16: 9 | J16: 9 | M16: 9 | Q16: =IFERROR(AVERAGE(C16:P16),"") | R16: 7 | S16: Judged on the static contract only; runtime audit quality not observed.
A17: RUN-016 | B17: TC-033 | C17: 10 | K17: 9 | P17: 9 | Q17: =IFERROR(AVERAGE(C17:P17),"") | R17: 9 | S17: Tool output matched the spec byte-for-byte for both forward and reverse drift passes; argparse guards work; repair path regenerates exactly the drifted file.
A18: RUN-017 | B18: TC-034 | C18: 10 | K18: 9 | P18: 9 | Q18: =IFERROR(AVERAGE(C18:P18),"") | R18: 9 | S18: All five expected behaviours reproduced exactly, including cross-edition failure visibility from a non-drifted edition and machine-readable JSON output.
A19: RUN-018 | B19: TC-035 | C19: 10 | K19: 10 | P19: 9 | Q19: =IFERROR(AVERAGE(C19:P19),"") | R19: 9 | S19: Measured values, ceilings, FAIL line and remediation text matched the spec exactly; both structural-mismatch FAIL paths verified.
A20: RUN-019 | B20: TC-036 | C20: 10 | M20: 9 | P20: 9 | Q20: =IFERROR(AVERAGE(C20:P20),"") | R20: 9 | S20: docs/CI.md commands reproduce the six CI jobs one-to-one against .github/workflows/ci.yml; every step exited 0 on the healthy checkout; run confirmed side-effect-free.
A21: RUN-020 | B21: TC-039 | C21: 10 | L21: 9 | P21: 10 | Q21: =IFERROR(AVERAGE(C21:P21),"") | R21: 10 | S21: Deterministic counts matched the spec exactly in all editions; hermeticity verified via git status and a __pycache__ inventory diff.
A22: RUN-021 | B22: TC-041 | C22: 10 | F22: 9 | P22: 9 | Q22: =IFERROR(AVERAGE(C22:P22),"") | R22: 9 | S22: Recipe and validator agree byte-for-byte on include/exclude semantics; no state leak possible via the shipped recipe.
A23: RUN-022 | B23: TC-042 | C23: 10 | K23: 9 | L23: 8 | P23: 9 | Q23: =IFERROR(AVERAGE(C23:P23),"") | R23: 9 | S23: Every seeded defect class detected with precise, actionable messages; dead-hook detection resolves every .sh token, not just the first.
A24: RUN-023 | B24: TC-043 | C24: 10 | K24: 9 | P24: 9 | Q24: =IFERROR(AVERAGE(C24:P24),"") | R24: 9 | S24: Detection, code-span skipping, allowlist suppression and clean-pass behaviour all verified; only output-format wording differs from the case description.
A25: RUN-024 | B25: TC-044 | C25: 10 | K25: 10 | P25: 9 | Q25: =IFERROR(AVERAGE(C25:P25),"") | R25: 9 | S25: Both gate outcomes, negative scope, explicit base ref, committed/uncommitted diffs and the mandatory degraded skip all verified against exact expected strings; script confirmed read-only over git metadata.
A26: RUN-026 | B26: TC-049 | C26: 10 | J26: 9 | L26: 9 | P26: 10 | Q26: =IFERROR(AVERAGE(C26:P26),"") | R26: 10 | S26: Every expectation in the case executed and matched exactly, including patch-marker parsing.
A27: RUN-027 | B27: TC-050 | C27: 10 | K27: 9 | P27: 10 | Q27: =IFERROR(AVERAGE(C27:P27),"") | R27: 10 | S27: Exact exit sequence and stream assignment reproduced deterministically.
A28: RUN-028 | B28: TC-051 | C28: 10 | J28: 9 | P28: 10 | Q28: =IFERROR(AVERAGE(C28:P28),"") | R28: 10 | S28: Both directions of the isolation contract (counting and resetting) verified with live state inspection.
A29: RUN-029 | B29: TC-052 | C29: 10 | J29: 9 | P29: 10 | Q29: =IFERROR(AVERAGE(C29:P29),"") | R29: 10 | S29: Both the negative (reads never count) and positive (matcher-less edits still count) sides exercised.
A30: RUN-030 | B30: TC-053 | F30: 10 | M30: 9 | P30: 9 | Q30: =IFERROR(AVERAGE(C30:P30),"") | R30: 9 | S30: Zero broken triples across 40 spawning commands plus clean parity is a strong wiring guarantee.
A31: RUN-031 | B31: TC-054 | F31: 9 | J31: 9 | M31: 9 | Q31: =IFERROR(AVERAGE(C31:P31),"") | R31: 8 | S31: All safety-relevant workflow steps are present verbatim in the skill; runtime adherence not observed.
A32: RUN-032 | B32: TC-055 | C32: 10 | F32: 10 | P32: 10 | Q32: =IFERROR(AVERAGE(C32:P32),"") | R32: 10 | S32: Generator check, parity, byte-comparison, and live payload behavior all agree.
A33: RUN-036 | B33: TC-059 | C33: 10 | D33: 10 | P33: 9 | Q33: =IFERROR(AVERAGE(C33:P33),"") | R33: 9 | S33: Every numbered expectation reproduced exactly at the CLI level and confirmed by the product's own tests.
A34: RUN-037 | B34: TC-060 | C34: 10 | D34: 9 | J34: 9 | P34: 9 | Q34: =IFERROR(AVERAGE(C34:P34),"") | R34: 9 | S34: Manual progress provably survived ten automatic flushes; separation of fields observed directly in JSON and in the handoff.
A35: RUN-038 | B35: TC-061 | C35: 8 | D35: 7 | P35: 8 | Q35: =IFERROR(AVERAGE(C35:P35),"") | R35: 8 | S35: Continuation behavior demonstrably works; deductions only for the literal expectation mismatches.
A36: RUN-039 | B36: TC-062 | C36: 10 | D36: 10 | K36: 10 | P36: 9 | Q36: =IFERROR(AVERAGE(C36:P36),"") | R36: 10 | S36: Every CAS expectation reproduced exactly, including the documented recovery via brain-get.
A37: RUN-040 | B37: TC-063 | C37: 10 | D37: 10 | K37: 10 | P37: 9 | Q37: =IFERROR(AVERAGE(C37:P37),"") | R37: 10 | S37: Exact refusal strings matched the specification verbatim; ledger inspected in the raw record.
A38: RUN-041 | B38: TC-064 | C38: 10 | D38: 10 | P38: 9 | Q38: =IFERROR(AVERAGE(C38:P38),"") | R38: 10 | S38: All positive, idempotent, and negative paths reproduced exactly, including the implicit rebound-on-flush path.
A39: RUN-042 | B39: TC-065 | C39: 9 | D39: 9 | P39: 9 | Q39: =IFERROR(AVERAGE(C39:P39),"") | R39: 9 | S39: Behavioral contract fully met; only the bare-token reason equality in the case text diverges from the implemented richer reason string.
A40: RUN-043 | B40: TC-066 | C40: 9 | D40: 9 | J40: 7 | P40: 9 | Q40: =IFERROR(AVERAGE(C40:P40),"") | R40: 9 | S40: Distillation and budget behavior exactly as specified; security deduction for the refresh-path privacy-gate ordering.
A41: RUN-044 | B41: TC-067 | C41: 10 | D41: 10 | J41: 9 | P41: 9 | Q41: =IFERROR(AVERAGE(C41:P41),"") | R41: 9 | S41: Conflict-free date+hex IDs confirmed against source UUIDs; counter provably untouched; distinct IDs from two records in one flush.
A42: RUN-045 | B42: TC-068 | C42: 10 | D42: 10 | P42: 9 | Q42: =IFERROR(AVERAGE(C42:P42),"") | R42: 10 | S42: Determinism verified by triple run plus git diff; preamble preservation verified directly.
A43: RUN-046 | B43: TC-069 | C43: 10 | D43: 10 | J43: 10 | P43: 9 | Q43: =IFERROR(AVERAGE(C43:P43),"") | R43: 10 | S43: All positive and negative acceptance criteria reproduced with correct exit codes and no secret leakage.
A44: RUN-047 | B44: TC-070 | C44: 10 | D44: 9 | P44: 9 | Q44: =IFERROR(AVERAGE(C44:P44),"") | R44: 9 | S44: Both ranking hypotheses confirmed with controlled twins; stale record present but demoted, matching the floor semantics.
A45: RUN-048 | B45: TC-071 | C45: 10 | D45: 10 | K45: 10 | P45: 9 | Q45: =IFERROR(AVERAGE(C45:P45),"") | R45: 9 | S45: Atomic replace-only-on-success and always-exit-0 semantics verified directly, including the timeout path.
A46: RUN-049 | B46: TC-072 | C46: 8 | D46: 6 | P46: 7 | Q46: =IFERROR(AVERAGE(C46:P46),"") | R46: 7 | S46: CLI substrate and prescriptions fully consistent with the case; conversational compliance not observable in this harness.
A47: RUN-050 | B47: TC-006 | Q47: 9.2 | R47: 9 | S47: Run-specific criteria (columns C-P not applicable to this run type): workflow_adherence=9; evidence_completeness=9; root_cause_analysis=9; safety_compliance=10; reproducibility=9. Overall = mean of these criteria. All case commands run in the prescribed order from the project root with exit codes captured; the single failure was traced to its root cause (file absent from the install commit vs present in the canonical edition) rather than merely reported. Evidence log contains commands, paths, and short output excerpts only — no client source code, secrets, or DSNs. Confidence is high because every claim is backed by a logged command with exit code.
A48: RUN-051 | B48: TC-073 | Q48: 9.4 | R48: 9 | S48: Run-specific criteria (columns C-P not applicable to this run type): workflow_fidelity=9; groundedness=10; completeness=9; safety_compliance=10; usefulness_of_map=9. Overall = mean of these criteria. Skill workflow followed step-by-step (authority gate, area-by-area exploration, whole-document writes with exact frontmatter, index refresh with per-document drift report). Grounding was verified mechanically, not just asserted. Completeness is 9 not 10 because CONCERNS.md was honestly omitted (no audit performed) and vendor/UniteCMS internals plus the Nuxt frontend logic were declared not explored rather than mapped.
A49: RUN-052 | B49: TC-021 | Q49: 9 | R49: 9 | S49: Run-specific criteria (columns C-P not applicable to this run type): workflow_fidelity=9; groundedness_in_real_code=9; template_completeness=10; decision_quality=9; governed_memory_usage=8; output_verifiability=9. Overall = mean of these criteria. All mandated skill sections present and grep-verifiable; every cited path exists in src/, config/, or tests/. Decision explicitly maps the skill's Good Decisions (unique index, single-use-case service, Messenger for retryable mail) onto the project's real conventions and names its deviations from textbook layout. Governed memory scored 8 due to the one rejected update call with an invalid phase value.
A50: RUN-053 | B50: TC-022 | Q50: 9.4 | R50: 9 | S50: Run-specific criteria (columns C-P not applicable to this run type): workflow_adherence=9; output_completeness=9; grounding_in_real_code=9; safety_compliance=10; honesty_of_reporting=10. Overall = mean of these criteria. All SKILL.md Production-Safety Workflow steps and Deliverable sections covered and grounded in actual entity/config/subscriber files. Deducted from completeness/adherence because the migration classes were designed inline rather than generated by the Doctrine CLI (bundle absent, no DB — permitted by the run directive) and schema:validate could not execute in this sandbox.
A51: RUN-054 | B51: TC-023 | Q51: 9.2 | R51: 9 | S51: Run-specific criteria (columns C-P not applicable to this run type): workflow_adherence=9; grounding_in_real_config=9; completeness_vs_expected_behaviour=9; safety_expectations=10; verification_rigor=9. Overall = mean of these criteria. All seven skill workflow steps and the skill's verification section are covered and each design decision cites a real file or configuration fact from the project (messenger.yaml transports, OcrDocument pattern, RegistrationHandler flush boundary, wrapInTransaction precedent, missing worker, missing migrations tooling). Minor deduction: the DSN scheme could not be confirmed (env secrets off-limits), so the outbox option is conditional rather than definitive, and the specified tests were designed but not executed (plan-only phase, sodium-blocked test env).
A52: RUN-055 | B52: TC-025 | Q52: 9.4 | R52: 9 | S52: Run-specific criteria (columns C-P not applicable to this run type): workflow_fidelity=9; detection_accuracy=10; output_contract_compliance=9; false_positive_control=10; governed_memory_usage=9. Overall = mean of these criteria. Self-executed review (single-agent QA harness, no subagent spawn) followed the SKILL.md workflow steps explicitly; all three checklist Layer Leaks detected with exact lines; control run clean with explicit cohesive verdict; deliverables follow the {skill}-{purpose}.md naming and TASK-004 numbering; governed lifecycle start/retrieve/update/complete executed with sanitized text.
A53: RUN-056 | B53: TC-040 | Q53: 8.3 | R53: 8 | S53: Run-specific criteria (columns C-P not applicable to this run type): workflow_fidelity=9; layer_selection=9; coverage_contract=8; test_data_and_safety=9; validation_map_quality=9; verification_honesty=9; runnable_outcome=5. Overall = mean of these criteria. Layer choice and coverage follow the skill tables precisely and reuse project conventions (Security createMock in plain TestCase, inline synthetic entities, graphql/login helpers). Runnable outcome scores low only because the functional layer is unexecutable in this environment (no pdo_mysql/test DB), demonstrated with a pre-existing-test control; the tests themselves mirror the proven AcceptInvitationTest pattern. Uncovered requirements are explicit rows, not silent omissions.
A54: RUN-057 | B54: TC-074 | Q54: 9.2 | R54: 9 | S54: Run-specific criteria (columns C-P not applicable to this run type): skill_workflow_adherence=9; grounding_no_fabrication=10; security_dimension_coverage=9; boundary_dimension_coverage=8; severity_ranking_justification=9; honesty_about_limitations=10. Overall = mean of these criteria. All file:line references machine-verified against the working tree; severities justified by concrete attack/failure scenarios. One point off workflow adherence: the optional task-prefixed report under tasks/ was not created (review delivered in skill text format in the evidence log, which the case explicitly allows). Boundary coverage slightly lower because the layering finding is a pre-existing-pattern observation rather than a regression introduced by the commit.
A55: RUN-20260803-001 | B55: TC-AI-001 | C55: 10 | D55: 10 | E55: 9 | F55: 9 | G55: 9 | H55: 9 | I55: 9 | J55: 10 | K55: 9 | L55: 10 | M55: 9 | N55: 9 | O55: 10 | P55: 10 | Q55: 9 | R55: 10 | S55: 132/132 Laravel memory tests pass.
A56: RUN-20260803-002 | B56: TC-AI-002 | C56: 10 | D56: 10 | E56: 9 | F56: 10 | G56: 9 | H56: 9 | I56: 9 | J56: 9 | K56: 10 | L56: 10 | M56: 9 | N56: 9 | O56: 10 | P56: 10 | Q56: 9 | R56: 10 | S56: 124/124 Laravel governed tests pass.
A57: RUN-20260803-003 | B57: TC-AI-003 | C57: 10 | D57: 10 | E57: 9 | F57: 9 | G57: 9 | H57: 9 | I57: 9 | J57: 10 | K57: 9 | L57: 10 | M57: 9 | N57: 9 | O57: 10 | P57: 10 | Q57: 9 | R57: 10 | S57: 132/132 Symfony memory tests pass.
A58: RUN-20260803-004 | B58: TC-AI-004 | C58: 10 | D58: 10 | E58: 9 | F58: 10 | G58: 9 | H58: 9 | I58: 9 | J58: 9 | K58: 10 | L58: 10 | M58: 9 | N58: 9 | O58: 10 | P58: 10 | Q58: 9 | R58: 10 | S58: 124/124 Symfony governed tests pass.
A59: RUN-20260803-005 | B59: TC-AI-005 | C59: 10 | D59: 10 | E59: 9 | F59: 9 | G59: 9 | H59: 9 | I59: 9 | J59: 10 | K59: 9 | L59: 10 | M59: 9 | N59: 9 | O59: 10 | P59: 10 | Q59: 9 | R59: 10 | S59: 132/132 PHP Core memory tests pass.
A60: RUN-20260803-006 | B60: TC-AI-006 | C60: 10 | D60: 10 | E60: 9 | F60: 10 | G60: 9 | H60: 9 | I60: 9 | J60: 9 | K60: 10 | L60: 10 | M60: 9 | N60: 9 | O60: 10 | P60: 10 | Q60: 9 | R60: 10 | S60: 124/124 PHP Core governed tests pass.
A61: RUN-20260803-007 | B61: TC-AI-007 | C61: 9 | D61: 8 | E61: 9 | F61: 9 | G61: 8 | H61: 9 | I61: 9 | J61: 9 | K61: 9 | L61: 7 | M61: 8 | N61: 9 | O61: 10 | P61: 10 | Q61: 8 | R61: 9 | S61: 21 hook tests pass; full generation coverage remains incomplete.
A62: RUN-20260803-008 | B62: TC-AI-008 | C62: 10 | D62: 10 | E62: 9 | F62: 10 | G62: 9 | H62: 9 | I62: 10 | J62: 10 | K62: 9 | L62: 9 | M62: 9 | N62: 10 | O62: 10 | P62: 10 | Q62: 9 | R62: 10 | S62: All 11 repository integrity gates pass.
A63: RUN-20260803-009 | B63: TC-AI-009 | C63: 9 | D63: 7 | E63: 9 | F63: 9 | G63: 9 | H63: 9 | I63: 9 | J63: 7 | K63: 9 | L63: 10 | M63: 8 | N63: 9 | O63: 8 | P63: 10 | Q63: 8 | R63: 10 | S63: Mechanics pass; policy conflicts reduce compliance.
A64: RUN-20260803-010 | B64: TC-AI-010 | C64: 10 | D64: 10 | E64: 9 | F64: 9 | G64: 9 | H64: 9 | I64: 9 | J64: 10 | K64: 9 | L64: 10 | M64: 9 | N64: 9 | O64: 10 | P64: 10 | Q64: 9 | R64: 10 | S64: Lightweight and hook behavior passes.
A65: RUN-20260803-011 | B65: TC-AI-011 | C65: 5 | D65: 3 | E65: 8 | F65: 5 | G65: 8 | H65: 8 | I65: 8 | J65: 3 | K65: 6 | L65: 8 | M65: 5 | N65: 6 | O65: 4 | P65: 9 | Q65: 5 | R65: 10 | S65: Durable memory can be applied without human review.
A66: RUN-20260803-012 | B66: TC-AI-012 | C66: 6 | D66: 4 | E66: 8 | F66: 5 | G66: 8 | H66: 8 | I66: 8 | J66: 6 | K66: 7 | L66: 8 | M66: 6 | N66: 6 | O66: 4 | P66: 9 | Q66: 5 | R66: 10 | S66: Merge automation can bypass explicit completion.
... A72: RUN-20260803-018 | B72: TC-AI-018 | C72: 6 | D72: 6 | E72: 9 | F72: 9 | G72: 8 | H72: 9 | I72: 9 | J72: 10 | K72: 8 | L72: 8 | M72: 6 | N72: 9 | O72: 8 | P72: 10 | Q72: 8 | R72: 10 | S72: Static parity passes; two native host runtimes remain unavailable.

Sheet Efficiency & Tokens
A1: Run ID | B1: Test Case ID | C1: Input Tokens | D1: Output Tokens | E1: Cached Tokens | F1: Total Tokens | G1: Estimated Cost | H1: Total Duration (seconds) | I1: Time to First Response (seconds) | J1: Agent Invocations | K1: Parallel Agent Invocations | L1: Tool Calls | M1: Failed Tool Calls | N1: Context Retrieval Count | O1: Retrieved Context Tokens | P1: Context Utilization (%) | Q1: Repeated Context Tokens | R1: User Clarification Count | S1: Manual Correction Count | T1: Successful First Attempt | U1: Tokens per Successful Test | V1: Cost per Successful Test | W1: Provider / Measurement Source | X1: Notes
